Workbook

Sheet README
A1: Generic apixaban vs warfarin for stroke prevention in non-valvular AF — cost-utility & budget impact model
A2: Author: Daniel Pazos Cordero (portfolio project, October 2026). Not affiliated with or endorsed by CDA-AMC.
A4: PURPOSE
A5: Re-runs the CADTH 4th-edition guidelines worked example (DOACs vs warfarin, CHADS2 = 2) with 2026 Ontario generic apixaban prices,
A6: to ask whether generic entry changes the value proposition for public drug plans. Includes a 3-year Ontario budget impact analysis.
A8: COLOUR LEGEND
A9: Blue text = hard-coded input (sourced in the Inputs sheet). Black text = formula. Green text = link to another sheet.
A10: Yellow fill = key decision lever (drug price, perspective inputs, budget-impact assumptions). Change these to run your own scenarios.
A12: SHEETS
A13: Inputs — every parameter, base value, one-way range, PSA distribution and source. Each base value has a defined name used in formulas.
A14: LifeTable — Statistics Canada 2021-2023 anchors and the Gompertz fit used for age-specific background mortality.
A15: Apixaban / Warfarin — cohort Markov traces: 120 three-month cycles (age 70 to 100). Identical formulas; only the arm flag in cell B2 differs.
... A28: the Excel deterministic results match Python to the cent (see Validation).

Sheet Inputs
A1: Parameter | B1: Name (used in formulas) | C1: Base value | D1: Low (OWSA) | E1: High (OWSA) | F1: PSA distribution | G1: Source / note
A2: Model settings
A3: Start age (years) | B3: start_age | C3: 70 | G3: CHADS2 = 2 cohort; CADTH worked example
A4: Reference age for trial-based rates | B4: ref_age | C4: 70 | G4: Age at which RE-LY-based rates apply
A5: Cycle length (years) | B5: dt | C5: 0.25 | G5: 3-month cycles, as in CADTH worked example
A6: Discount rate (costs and QALYs) | B6: disc_rate | C6: 0.015 | G6: CADTH 4th ed. reference case
A7: Willingness to pay ($/QALY) | B7: wtp | C7: 50000 | G7: Threshold used in CADTH worked example for NMB
A8: Apixaban effect waning: start (years) | B8: wane_start | C8: 2 | G8: Scenario lever (CADTH worked example scenario)
A9: Apixaban effect waning: annual decay | B9: wane_decay | C9: 0 | G9: 0 = no waning (reference case); 0.05 = CADTH scenario
A10: Validation mode (1 = CADTH 2011 prices, 0 = 2025 reference case) | B10: val_mode | C10: 0 | G10: Switch to 1 to reproduce the CADTH worked example at 2011 prices (see Validation sheet)
A11: Price year adjustment
A12: CPI 2011 (2002 = 100) | B12: cpi_2011 | C12: 119.9 | G12: Statistics Canada Table 18-10-0005-01
A13: CPI 2025 (2002 = 100) | B13: cpi_2025 | C13: 164.2 | G13: Statistics Canada Table 18-10-0005-01, annual average
A14: Inflator 2011 to 2025 | B14: inflate | C14: =IF(val_mode=1,1,cpi_2025/cpi_2011) -> 1.3694746 | G14: Formula (= 1 in validation mode, i.e. costs stay in 2011 CAD)
A15: Drug prices (ODB, per tablet) and annual drug costs
A16: Apixaban 5 mg price per tablet | B16: apx_price_tab | C16: 0.4084 | G16: ODB Formulary, generic apixaban 5 mg, accessed Oct 2026. Brand Eliquis = $1.6336 (enter it here for the brand scenario).
A17: Apixaban annual cost in 2011 (validation mode only) | B17: c_apixaban_2011 | C17: 1289.44 | G17: CADTH worked example, brand apixaban 2011 ODB price
A18: Days per year | B18: days_yr | C18: 365.25 | G18: CDA-AMC convention for annualising daily drug costs
A19: Apixaban 5 mg BID, annual | B19: c_apixaban | C19: =IF(val_mode=1,c_apixaban_2011,apx_price_tab*2*days_yr) -> 298.3362 | G19: Formula
A20: Warfarin 5 mg daily, annual | B20: c_warfarin | C20: 54.61 | D20: 27 | E20: 110 | F20: Fixed | G20: CADTH worked example (2011 ODB). Not inflated: generic prices have not tracked CPI. VERIFY against current ODB listing.
A21: INR monitoring, annual (warfarin only) | B21: c_inr_2011 | C21: 240.69 | G21: CADTH worked example (from HQO 2009), 2011 CAD
A22: INR monitoring, annual, 2025 CAD | B22: c_inr | C22: =c_inr_2011*inflate -> 329.61883 | D22: =0.5*c_inr_2011*inflate -> 164.80942 | E22: =1.5*c_inr_2011*inflate -> 494.42825 | F22: Fixed | G22: Formula: 2011 value x CPI inflator
A23: Aspirin, annual | B23: c_aspirin | C23: 39.04 | D23: 20 | E23: 60 | F23: Fixed | G23: CADTH worked example (2011 ODB), not inflated
A24: Background mortality
A25: Non-vascular death at age 70 (annual) | B25: p_nonvasc_death | C25: 0.033 | D25: 0.025 | E25: 0.041 | F25: Beta (mean = base, n = 11,794) | G25: RE-LY warfarin arm via CADTH worked example; scaled by age with the StatCan life-table gradient (LifeTable sheet)
A26: Mortality after stroke | B26: hr_death_prior_stroke | C26: 2.3 | D26: 2 | E26: 2.7 | F26: Lognormal (95% CI 2.0-2.7) | G26: CADTH 2017 worked example, Table 1 (from Coyle et al. 2013)
A27: Baseline annual event probabilities on warfarin (CHADS2 = 2)
A28: Stroke rate on warfarin (annual) | B28: p_stroke | C28: 0.016 | D28: 0.012 | E28: 0.02 | F28: Beta (mean = base, n = 11,794) | G28: CADTH 2017 worked example, Table 1 (from Coyle et al. 2013)
A29: TIA rate (annual) | B29: p_tia | C29: 0.008 | D29: 0.006 | E29: 0.01 | F29: Beta (mean = base, n = 11,794) | G29: CADTH 2017 worked example, Table 1 (from Coyle et al. 2013)
A30: ICH rate on warfarin (annual) | B30: p_ich | C30: 0.008 | D30: 0.006 | E30: 0.01 | F30: Beta (mean = base, n = 11,794) | G30: CADTH 2017 worked example, Table 1 (from Coyle et al. 2013)
A31: Major bleed rate on warfarin (annual) | B31: p_major_bleed | C31: 0.033 | D31: 0.025 | E31: 0.041 | F31: Beta (mean = base, n = 11,794) | G31: CADTH 2017 worked example, Table 1 (from Coyle et al. 2013)
A32: Minor bleed rate (annual) | B32: p_minor_bleed | C32: 0.164 | D32: 0.123 | E32: 0.205 | F32: Beta (mean = base, n = 11,794) | G32: CADTH 2017 worked example, Table 1 (from Coyle et al. 2013)
A33: MI rate (annual) | B33: p_mi | C33: 0.006 | D33: 0.0045 | E33: 0.0075 | F33: Beta (mean = base, n = 11,794) | G33: CADTH 2017 worked example, Table 1 (from Coyle et al. 2013)
A34: Event outcomes
A35: Proportion of first strokes fatal | B35: f_stroke_fatal | C35: 0.237 | D35: 0.18 | E35: 0.3 | F35: Beta (mean = base, n = 186) | G35: CADTH 2017 worked example, Table 1 (from Coyle et al. 2013)
A36: Proportion of non-fatal strokes major | B36: f_stroke_major | C36: 0.333 | D36: 0.25 | E36: 0.42 | F36: Beta (mean = base, n = 117) | G36: CADTH 2017 worked example, Table 1 (from Coyle et al. 2013)
A37: Increase in fatality of recurrent stroke | B37: hr_recur_fatal | C37: 1.57 | D37: 1.21 | E37: 2.03 | F37: Lognormal (95% CI 1.21-2.03) | G37: CADTH 2017 worked example, Table 1 (from Coyle et al. 2013)
A38: Proportion of major bleeds / ICH fatal | B38: f_bleed_fatal | C38: 0.084 | D38: 0.06 | E38: 0.11 | F38: Beta (mean = base, n = 476) | G38: CADTH 2017 worked example, Table 1 (from Coyle et al. 2013)
A39: Proportion of MIs fatal | B39: f_mi_fatal | C39: 0.121 | D39: 0.06 | E39: 0.2 | F39: Beta (mean = base, n = 66) | G39: CADTH 2017 worked example, Table 1 (from Coyle et al. 2013)
A40: Risk modifiers
A41: Stroke risk per 10 years of age | B41: rr_stroke_per_decade | C41: 1.5 | D41: 1.3 | E41: 1.7 | F41: Lognormal (95% CI 1.3-1.7) | G41: CADTH 2017 worked example, Table 1 (from Coyle et al. 2013)
A42: Stroke risk after prior stroke/ICH | B42: rr_stroke_prior | C42: 2.2 | D42: 1.2 | E42: 3.5 | F42: Lognormal (95% CI 0.78-6.35) | G42: CADTH 2017 worked example, Table 1 (from Coyle et al. 2013)
A43: Apixaban vs warfarin — odds ratios (CADTH NMA)
A44: Apixaban OR: stroke | B44: or_apx_stroke | C44: 0.79 | D44: 0.65 | E44: 0.95 | F44: Lognormal (95% CI 0.65-0.95) | G44: CADTH 2017 worked example, Table 1 (from Coyle et al. 2013)
A45: Apixaban OR: MI | B45: or_apx_mi | C45: 0.88 | D45: 0.66 | E45: 1.17 | F45: Lognormal (95% CI 0.66-1.17) | G45: CADTH 2017 worked example, Table 1 (from Coyle et al. 2013)
A46: Apixaban OR: ICH | B46: or_apx_ich | C46: 0.42 | D46: 0.3 | E46: 0.58 | F46: Lognormal (95% CI 0.3-0.58) | G46: CADTH 2017 worked example, Table 1 (from Coyle et al. 2013)
A47: Apixaban OR: major bleed | B47: or_apx_mb | C47: 0.8 | D47: 0.68 | E47: 0.94 | F47: Lognormal (95% CI 0.68-0.94) | G47: CADTH 2017 worked example, Table 1 (from Coyle et al. 2013)
A48: Aspirin vs warfarin — relative risks (after stroke, ICH or major bleed)
A49: Aspirin RR: stroke | B49: rr_asa_stroke | C49: 1.62 | D49: 0.99 | E49: 2.65 | F49: Lognormal (95% CI 0.99-2.65) | G49: CADTH 2017 worked example, Table 1 (from Coyle et al. 2013)
A50: Aspirin RR: MI | B50: rr_asa_mi | C50: 1.42 | D50: 0.84 | E50: 2.39 | F50: Lognormal (95% CI 0.84-2.39) | G50: CADTH 2017 worked example, Table 1 (from Coyle et al. 2013)
A51: Aspirin RR: ICH | B51: rr_asa_ich | C51: 0.51 | D51: 0.16 | E51: 1.6 | F51: Lognormal (95% CI 0.16-1.6) | G51: CADTH 2017 worked example, Table 1 (from Coyle et al. 2013)
A52: Aspirin RR: minor bleed | B52: rr_asa_minor | C52: 0.63 | D52: 0.32 | E52: 1.22 | F52: Lognormal (95% CI 0.32-1.22) | G52: CADTH 2017 worked example, Table 1 (from Coyle et al. 2013)
A53: Aspirin RR: major bleed | B53: rr_asa_mb | C53: 1.14 | D53: 0.47 | E53: 2.73 | F53: Lognormal (95% CI 0.47-2.73) | G53: CADTH 2017 worked example, Table 1 (from Coyle et al. 2013)
A54: Aspirin RR: TIA | B54: rr_asa_tia | C54: 1.56 | D54: 0.86 | E54: 2.83 | F54: Lognormal (95% CI 0.86-2.83) | G54: CADTH 2017 worked example, Table 1 (from Coyle et al. 2013)
A55: Utilities (annual) and decrements
A56: Utility: AF, no prior event | B56: u_af | C56: 0.81 | D56: 0.75 | E56: 0.87 | F56: Beta (mean = base, n = 42) | G56: CADTH 2017 worked example, Table 1 (from Coyle et al. 2013)
A57: Utility: after minor stroke / ICH | B57: u_minor_stroke | C57: 0.75 | D57: 0.67 | E57: 0.83 | F57: Beta (mean = base, n = 116) | G57: CADTH 2017 worked example, Table 1 (from Coyle et al. 2013)
A58: Utility: major stroke, Rankin 3-4 | B58: u_rankin_3_4 | C58: 0.39 | D58: 0.32 | E58: 0.46 | F58: Beta (mean = base, n = 179) | G58: CADTH 2017 worked example, Table 1 (from Coyle et al. 2013)
A59: Utility: major stroke, Rankin 5 | B59: u_rankin_5 | C59: 0.11 | D59: 0.06 | E59: 0.16 | F59: Beta (mean = base, n = 172) | G59: CADTH 2017 worked example, Table 1 (from Coyle et al. 2013)
A60: Share of major strokes at Rankin 5 | B60: p_rankin_5 | C60: 0.205 | D60: 0.1 | E60: 0.31 | F60: Beta (mean = base, n = 47) | G60: CADTH 2017 worked example, Table 1 (from Coyle et al. 2013)
A61: Utility loss per year over 70 | B61: dec_per_year_over_70 | C61: 0.00029 | D61: 0.00025 | E61: 0.00033 | F61: Normal (SE 2e-05) | G61: CADTH 2017 worked example, Table 1 (from Coyle et al. 2013)
A62: Disutility: MI | B62: dec_mi | C62: 0.125 | D62: 0.107 | E62: 0.143 | F62: Normal (SE 0.009) | G62: CADTH 2017 worked example, Table 1 (from Coyle et al. 2013)
A63: Disutility: major bleed | B63: dec_major_bleed | C63: 0.092 | D63: 0.072 | E63: 0.112 | F63: Normal (SE 0.01) | G63: CADTH 2017 worked example, Table 1 (from Coyle et al. 2013)
A64: Disutility: minor bleed | B64: dec_minor_bleed | C64: 0.013 | D64: 0.011 | E64: 0.015 | F64: Normal (SE 0.001) | G64: CADTH 2017 worked example, Table 1 (from Coyle et al. 2013)
A65: Disutility: TIA | B65: dec_tia | C65: 0.103 | D65: 0.087 | E65: 0.119 | F65: Normal (SE 0.008) | G65: CADTH 2017 worked example, Table 1 (from Coyle et al. 2013)
A66: Clinical event costs (one-off) and long-term annual costs — entered in 2011 CAD, inflated by formula
A67: Cost: fatal stroke (2011 CAD) | B67: c_stroke_fatal_2011 | C67: 16800 | G67: CADTH 2017 worked example, Table 1 (from Coyle et al. 2013)
A68: Cost: fatal stroke (2025 CAD) | B68: c_stroke_fatal | C68: =c_stroke_fatal_2011*inflate -> 23007.173 | D68: =0.75*c_stroke_fatal_2011*inflate -> 17255.379 | E68: =1.25*c_stroke_fatal_2011*inflate -> 28758.966 | F68: Gamma (CV 25%) | G68: Formula: 2011 value x CPI inflator
A69: Cost: minor stroke (2011 CAD) | B69: c_stroke_minor_2011 | C69: 16800 | G69: CADTH 2017 worked example, Table 1 (from Coyle et al. 2013)
A70: Cost: minor stroke (2025 CAD) | B70: c_stroke_minor | C70: =c_stroke_minor_2011*inflate -> 23007.173 | D70: =0.75*c_stroke_minor_2011*inflate -> 17255.379 | E70: =1.25*c_stroke_minor_2011*inflate -> 28758.966 | F70: Gamma (CV 25%) | G70: Formula: 2011 value x CPI inflator
A71: Cost: major stroke (acute) (2011 CAD) | B71: c_stroke_major_2011 | C71: 56864 | G71: CADTH 2017 worked example, Table 1 (from Coyle et al. 2013)
A72: Cost: major stroke (acute) (2025 CAD) | B72: c_stroke_major | C72: =c_stroke_major_2011*inflate -> 77873.802 | D72: =0.75*c_stroke_major_2011*inflate -> 58405.351 | E72: =1.25*c_stroke_major_2011*inflate -> 97342.252 | F72: Gamma (CV 25%) | G72: Formula: 2011 value x CPI inflator
A73: Cost: TIA (2011 CAD) | B73: c_tia_2011 | C73: 4296 | G73: CADTH 2017 worked example, Table 1 (from Coyle et al. 2013)
A74: Cost: TIA (2025 CAD) | B74: c_tia | C74: =c_tia_2011*inflate -> 5883.2627 | D74: =0.75*c_tia_2011*inflate -> 4412.447 | E74: =1.25*c_tia_2011*inflate -> 7354.0784 | F74: Gamma (CV 25%) | G74: Formula: 2011 value x CPI inflator
A75: Cost: ICH (2011 CAD) | B75: c_ich_2011 | C75: 16559 | G75: CADTH 2017 worked example, Table 1 (from Coyle et al. 2013)
A76: Cost: ICH (2025 CAD) | B76: c_ich | C76: =c_ich_2011*inflate -> 22677.129 | D76: =0.75*c_ich_2011*inflate -> 17007.847 | E76: =1.25*c_ich_2011*inflate -> 28346.412 | F76: Gamma (CV 25%) | G76: Formula: 2011 value x CPI inflator
A77: Cost: major bleed (2011 CAD) | B77: c_major_bleed_2011 | C77: 4392 | G77: CADTH 2017 worked example, Table 1 (from Coyle et al. 2013)
A78: Cost: major bleed (2025 CAD) | B78: c_major_bleed | C78: =c_major_bleed_2011*inflate -> 6014.7323 | D78: =0.75*c_major_bleed_2011*inflate -> 4511.0492 | E78: =1.25*c_major_bleed_2011*inflate -> 7518.4153 | F78: Gamma (CV 25%) | G78: Formula: 2011 value x CPI inflator
A79: Cost: minor bleed (2011 CAD) | B79: c_minor_bleed_2011 | C79: 104 | G79: CADTH 2017 worked example, Table 1 (from Coyle et al. 2013)
A80: Cost: minor bleed (2025 CAD) | B80: c_minor_bleed | C80: =c_minor_bleed_2011*inflate -> 142.42535 | D80: =0.75*c_minor_bleed_2011*inflate -> 106.81902 | E80: =1.25*c_minor_bleed_2011*inflate -> 178.03169 | F80: Gamma (CV 25%) | G80: Formula: 2011 value x CPI inflator
A81: Cost: fatal MI (2011 CAD) | B81: c_mi_fatal_2011 | C81: 7351 | G81: CADTH 2017 worked example, Table 1 (from Coyle et al. 2013)
A82: Cost: fatal MI (2025 CAD) | B82: c_mi_fatal | C82: =c_mi_fatal_2011*inflate -> 10067.008 | D82: =0.75*c_mi_fatal_2011*inflate -> 7550.2556 | E82: =1.25*c_mi_fatal_2011*inflate -> 12583.759 | F82: Gamma (CV 25%) | G82: Formula: 2011 value x CPI inflator
A83: Cost: non-fatal MI (2011 CAD) | B83: c_mi_nonfatal_2011 | C83: 11380 | G83: CADTH 2017 worked example, Table 1 (from Coyle et al. 2013)
A84: Cost: non-fatal MI (2025 CAD) | B84: c_mi_nonfatal | C84: =c_mi_nonfatal_2011*inflate -> 15584.621 | D84: =0.75*c_mi_nonfatal_2011*inflate -> 11688.465 | E84: =1.25*c_mi_nonfatal_2011*inflate -> 19480.776 | F84: Gamma (CV 25%) | G84: Formula: 2011 value x CPI inflator
A85: Annual cost: after major stroke (2011 CAD) | B85: c_lt_major_stroke_2011 | C85: 19069 | G85: CADTH 2017 worked example, Table 1 (from Coyle et al. 2013)
A86: Annual cost: after major stroke (2025 CAD) | B86: c_lt_major_stroke | C86: =c_lt_major_stroke_2011*inflate -> 26114.51 | D86: =0.75*c_lt_major_stroke_2011*inflate -> 19585.883 | E86: =1.25*c_lt_major_stroke_2011*inflate -> 32643.138 | F86: Gamma (CV 25%) | G86: Formula: 2011 value x CPI inflator
A87: Annual cost: after minor stroke / ICH (2011 CAD) | B87: c_lt_minor_stroke_2011 | C87: 7896 | G87: CADTH 2017 worked example, Table 1 (from Coyle et al. 2013)
A88: Annual cost: after minor stroke / ICH (2025 CAD) | B88: c_lt_minor_stroke | C88: =c_lt_minor_stroke_2011*inflate -> 10813.371 | D88: =0.75*c_lt_minor_stroke_2011*inflate -> 8110.0284 | E88: =1.25*c_lt_minor_stroke_2011*inflate -> 13516.714 | F88: Gamma (CV 25%) | G88: Formula: 2011 value x CPI inflator
A89: Derived quantities (formulas — do not edit)
A90: Annual rate: stroke | B90: r_stroke | C90: =-LN(1-p_stroke) -> 0.016129382 | G90: Formula
A91: Annual rate: TIA | B91: r_tia | C91: =-LN(1-p_tia) -> 0.0080321717 | G91: Formula
A92: Annual rate: ICH | B92: r_ich | C92: =-LN(1-p_ich) -> 0.0080321717 | G92: Formula
A93: Annual rate: major bleed | B93: r_mb | C93: =-LN(1-p_major_bleed) -> 0.033556784 | G93: Formula
A94: Annual rate: minor bleed | B94: r_minor | C94: =-LN(1-p_minor_bleed) -> 0.17912667 | G94: Formula
A95: Annual rate: MI | B95: r_mi | C95: =-LN(1-p_mi) -> 0.0060180723 | G95: Formula
A96: Fatality of recurrent stroke | B96: f_stroke_fatal_recur | C96: =MIN(f_stroke_fatal*hr_recur_fatal,1) -> 0.37209 | G96: Formula
A97: Utility: post major stroke (Rankin mix) | B97: u_major_stroke | C97: =(1-p_rankin_5)*u_rankin_3_4+p_rankin_5*u_rankin_5 -> 0.3326 | G97: Formula

Sheet Results
A1: Reference-case results — generic apixaban vs warfarin, CHADS2 = 2, age 70, lifetime, 2025 CAD
A3: Outcome (per patient) | B3: Apixaban (generic) | C3: Warfarin | D3: Incremental
A4: Total cost (discounted) | B4: =SUM(Apixaban!DT6:DT125) -> 22807.847 | C4: =SUM(Warfarin!DT6:DT125) -> 28415.756 | D4: =B4-C4 -> -5607.9085
A5: Drug and monitoring costs | B5: =SUM(Apixaban!DU6:DU125) -> 2362.0973 | C5: =SUM(Warfarin!DU6:DU125) -> 2791.2029 | D5: =B5-C5 -> -429.10568
A6: Clinical event costs | B6: =SUM(Apixaban!DV6:DV125) -> 11499.738 | C6: =SUM(Warfarin!DV6:DV125) -> 13952.852 | D6: =B6-C6 -> -2453.1141
A7: Long-term post-event costs | B7: =SUM(Apixaban!DW6:DW125) -> 8946.0119 | C7: =SUM(Warfarin!DW6:DW125) -> 11671.701 | D7: =B7-C7 -> -2725.6887
A8: QALYs (discounted) | B8: =SUM(Apixaban!DX6:DX125) -> 7.4644651 | C8: =SUM(Warfarin!DX6:DX125) -> 7.2281947 | D8: =B8-C8 -> 0.2362704
A9: Life-years (discounted) | B9: =SUM(Apixaban!DY6:DY125) -> 9.3878909 | C9: =SUM(Warfarin!DY6:DY125) -> 9.1294309 | D9: =B9-C9 -> 0.25846001
A10: Total cost (undiscounted) | B10: =SUM(Apixaban!DQ6:DQ125) -> 25757.486 | C10: =SUM(Warfarin!DQ6:DQ125) -> 31951.543 | D10: =B10-C10 -> -6194.058
A11: QALYs (undiscounted) | B11: =SUM(Apixaban!DR6:DR125) -> 8.2250407 | C11: =SUM(Warfarin!DR6:DR125) -> 7.9444876 | D11: =B11-C11 -> 0.28055307
A12: Life-years (undiscounted) | B12: =SUM(Apixaban!DS6:DS125) -> 10.352352 | C12: =SUM(Warfarin!DS6:DS125) -> 10.04332 | D12: =B12-C12 -> 0.30903264
A13: Strokes per 1,000 patients | B13: =SUM(Apixaban!DZ6:DZ125)*1000 -> 238.60513 | C13: =SUM(Warfarin!DZ6:DZ125)*1000 -> 281.7505 | D13: =B13-C13 -> -43.14537
A14: Intracranial haemorrhages per 1,000 | B14: =SUM(Apixaban!EA6:EA125)*1000 -> 35.5206 | C14: =SUM(Warfarin!EA6:EA125)*1000 -> 69.803287 | D14: =B14-C14 -> -34.282686
A15: Major bleeds per 1,000 | B15: =SUM(Apixaban!EB6:EB125)*1000 -> 292.37459 | C15: =SUM(Warfarin!EB6:EB125)*1000 -> 338.92992 | D15: =B15-C15 -> -46.555331
A17: ICER ($ per QALY gained) | D17: =IF(AND(D4<=0,D8>=0),"Apixaban dominant",IF(AND(D4>=0,D8<=0),"Apixaban dominated",D4/D8)) -> Apixaban dominant
A18: Incremental net monetary benefit at WTP | D18: =D8*wtp-D4 -> 17421.428
A20: Price threshold analysis (apixaban 5 mg, per tablet)
A21: Current ODB price per tablet | D21: =apx_price_tab -> 0.4084
A22: Discounted years on anticoagulant (apixaban arm) | D22: =SUM(Apixaban!EC6:EC125) -> 7.6961946
A23: Price at which apixaban is cost-neutral vs warfarin | D23: =D21-D4/(D22*2*days_yr) -> 1.4058811
A24: Price at which ICER = WTP | D24: =D21+(D8*wtp-D4)/(D22*2*days_yr) -> 3.5071569
A25: Note: incremental cost is linear in the apixaban price, so these thresholds are exact.
A27: Per-patient undiscounted total cost by year (feeds BIA)
A28: Year 1 | B28: =SUM(Apixaban!DQ6:DQ9) -> 1218.836 | C28: =SUM(Warfarin!DQ6:DQ9) -> 1607.397 | D28: =B28-C28 -> -388.56099
A29: Year 2 | B29: =SUM(Apixaban!DQ10:DQ13) -> 1388.8403 | C29: =SUM(Warfarin!DQ10:DQ13) -> 1833.5169 | D29: =B29-C29 -> -444.67654
A30: Year 3 | B30: =SUM(Apixaban!DQ14:DQ17) -> 1533.6424 | C30: =SUM(Warfarin!DQ14:DQ17) -> 2019.0885 | D30: =B30-C30 -> -485.44606

Sheet Validation
A1: Validation
A2: Status cells read PASS or CHECK. No IFERROR is used anywhere, so any error value that appears is a genuine error.
A4: A. Mass balance (each cycle's state occupancy must sum to 1) | B4: Minimum | C4: Maximum | D4: Status
A5: Apixaban sheet | B5: =MIN(Apixaban!DM6:DM125) -> 1 | C5: =MAX(Apixaban!DM6:DM125) -> 1 | D5: =IF(AND(ABS(B5-1)<0.000000001,ABS(C5-1)<0.000000001),"PASS","CHECK") -> PASS
A6: Warfarin sheet | B6: =MIN(Warfarin!DM6:DM125) -> 1 | C6: =MAX(Warfarin!DM6:DM125) -> 1 | D6: =IF(AND(ABS(B6-1)<0.000000001,ABS(C6-1)<0.000000001),"PASS","CHECK") -> PASS
A8: B. Excel vs Python (expected values switch with val_mode) | B8: Excel (live) | C8: Python | D8: Difference | E8: Status
A9: Apixaban: total cost (discounted) | B9: =Results!B4 -> 22807.847 | C9: =IF(val_mode=1,24919.455929835,22807.8471211961) -> 22807.847 | D9: =B9-C9 -> 0 | E9: =IF(ABS(D9)<0.01,"PASS","CHECK") -> PASS
A10: Warfarin: total cost (discounted) | B10: =Results!C4 -> 28415.756 | C10: =IF(val_mode=1,20875.1726832633,28415.7556272264) -> 28415.756 | D10: =B10-C10 -> 0 | E10: =IF(ABS(D10)<0.01,"PASS","CHECK") -> PASS
A11: Apixaban: QALYs (discounted) | B11: =Results!B8 -> 7.4644651 | C11: =IF(val_mode=1,7.46446505520995,7.46446505520995) -> 7.4644651 | D11: =B11-C11 -> 0 | E11: =IF(ABS(D11)<0.000001,"PASS","CHECK") -> PASS
A12: Warfarin: QALYs (discounted) | B12: =Results!C8 -> 7.2281947 | C12: =IF(val_mode=1,7.22819465539138,7.22819465539138) -> 7.2281947 | D12: =B12-C12 -> 0 | E12: =IF(ABS(D12)<0.000001,"PASS","CHECK") -> PASS
A13: Apixaban: life-years (discounted) | B13: =Results!B9 -> 9.3878909 | C13: =IF(val_mode=1,9.38789091607325,9.38789091607325) -> 9.3878909 | D13: =B13-C13 -> 0 | E13: =IF(ABS(D13)<0.000001,"PASS","CHECK") -> PASS
A14: Warfarin: life-years (discounted) | B14: =Results!C9 -> 9.1294309 | C14: =IF(val_mode=1,9.12943090989414,9.12943090989414) -> 9.1294309 | D14: =B14-C14 -> 0 | E14: =IF(ABS(D14)<0.000001,"PASS","CHECK") -> PASS
A15: Apixaban: strokes per 1,000 | B15: =Results!B13 -> 238.60513 | C15: =IF(val_mode=1,238.605132134123,238.605132134123) -> 238.60513 | D15: =B15-C15 -> 0 | E15: =IF(ABS(D15)<0.001,"PASS","CHECK") -> PASS
A16: Warfarin: strokes per 1,000 | B16: =Results!C13 -> 281.7505 | C16: =IF(val_mode=1,281.75050218053,281.75050218053) -> 281.7505 | D16: =B16-C16 -> 0 | E16: =IF(ABS(D16)<0.001,"PASS","CHECK") -> PASS
A17: Incremental cost | B17: =Results!D4 -> -5607.9085 | C17: =IF(val_mode=1,4044.28324657166,-5607.90850603029) -> -5607.9085 | D17: =B17-C17 -> -4.7293724e-11 | E17: =IF(ABS(D17)<0.01,"PASS","CHECK") -> PASS
A18: Incremental QALYs | B18: =Results!D8 -> 0.2362704 | C18: =IF(val_mode=1,0.236270399818563,0.236270399818563) -> 0.2362704 | D18: =B18-C18 -> -1.1546319e-14 | E18: =IF(ABS(D18)<0.000001,"PASS","CHECK") -> PASS
A19: Incremental net monetary benefit | B19: =Results!D18 -> 17421.428 | C19: =IF(val_mode=1,7769.2367443565,17421.4284969585) -> 17421.428 | D19: =B19-C19 -> -5.2750693e-10 | E19: =IF(ABS(D19)<0.05,"PASS","CHECK") -> PASS
A20: Python values are hard-coded from the notebooks (reference case and the 2011-price run). They only match while every other input is at its base value.
A22: C. Reproducing the CADTH worked example (set val_mode = 1) | B22: CADTH (2017) | C22: This model (Python) | D22: Excel (live) | E22: Difference vs CADTH
A23: Warfarin: total cost | B23: 20558 | C23: 20875.173 | D23: =IF(val_mode=1,Results!C4,"set val_mode = 1") -> set val_mode = 1 | E23: =C23/B23-1 -> 0.015428188
A24: Warfarin: QALYs | B24: 7.49 | C24: 7.2281947 | D24: =IF(val_mode=1,Results!C8,"set val_mode = 1") -> set val_mode = 1 | E24: =C24/B24-1 -> -0.034953985
A25: Warfarin: life-years | B25: 9.12 | C25: 9.1294309 | D25: =IF(val_mode=1,Results!C9,"set val_mode = 1") -> set val_mode = 1 | E25: =C25/B25-1 -> 0.001034091
A26: Apixaban: total cost | B26: 24665 | C26: 24919.456 | D26: =IF(val_mode=1,Results!B4,"set val_mode = 1") -> set val_mode = 1 | E26: =C26/B26-1 -> 0.010316478
A27: Apixaban: QALYs | B27: 7.67 | C27: 7.4644651 | D27: =IF(val_mode=1,Results!B8,"set val_mode = 1") -> set val_mode = 1 | E27: =C27/B27-1 -> -0.026797255
A28: Apixaban: life-years | B28: 9.48 | C28: 9.3878909 | D28: =IF(val_mode=1,Results!B9,"set val_mode = 1") -> set val_mode = 1 | E28: =C28/B28-1 -> -0.0097161481
A29: Incremental cost | B29: 4107 | C29: 4044.2832 | D29: =IF(val_mode=1,Results!D4,"set val_mode = 1") -> set val_mode = 1 | E29: =C29/B29-1 -> -0.015270697
A30: Incremental QALYs | B30: 0.18 | C30: 0.2362704 | D30: =IF(val_mode=1,Results!D8,"set val_mode = 1") -> set val_mode = 1 | E30: =C30/B30-1 -> 0.31261333
A31: ICER ($ per QALY) | B31: 22875 | C31: 17117.181 | D31: =IF(val_mode=1,Results!D4/Results!D8,"set val_mode = 1") -> set val_mode = 1 | E31: =C31/B31-1 -> -0.25170793
A33: CADTH values: Guidelines for the Economic Evaluation of Health Technologies: Canada, 4th ed., worked example, CHADS2 = 2 (probabilistic means).
A34: Costs, life-years and incremental cost reproduce within 2%. Incremental QALYs are 31% higher than CADTH's (ICER 25% lower), so this
A35: simplified 5-state model is somewhat favourable to apixaban; the pessimistic treatment-effect scenarios (Scenarios_PSA) address this.
A36: D. Internal checks run in Python (all passed): utilities = 1 gives QALYs = life-years; apixaban ORs = 1 with equal drug cost gives identical
A37: arms; lower stroke OR raises QALYs monotonically; a higher discount rate lowers discounted QALYs.

Sheet Scenarios_PSA
A1: Uncertainty analyses: values from the Python notebooks (not live formulas)
A2: Re-run the notebooks (05 PSA, 06 sensitivity) to regenerate. Single scenarios can also be reproduced live by changing Inputs.
A4: Scenario | B4: Incremental cost | C4: Incremental QALYs | D4: Result | E4: INMB at $50,000/QALY
A5: Reference case (generic apixaban, 2026 ODB price) | B5: -5607.9085 | C5: 0.2362704 | D5: Dominant | E5: 17421.428
A6: Brand apixaban price (Eliquis, ODB list) | B6: 1280.2518 | C6: 0.2362704 | D6: $5,419/QALY | E6: 10533.268
A7: Discount rate 0% | B7: -6194.058 | C7: 0.28055307 | D7: Dominant | E7: 20221.712
A8: Discount rate 3% | B8: -5104.6185 | C8: 0.20064613 | D8: Dominant | E8: 15136.925
A9: Time horizon 2 years (trial follow-up) | B9: -821.94134 | C9: 0.0041946947 | D9: Dominant | E9: 1031.6761
A10: Time horizon 10 years | B10: -4357.3973 | C10: 0.097462127 | D10: Dominant | E10: 9230.5037
A11: Apixaban effect wanes 5%/yr after year 2 | B11: -4912.0923 | C11: 0.20689702 | D11: Dominant | E11: 15256.943
A12: All apixaban ORs at upper 95% CI | B12: -2613.6415 | C12: 0.092487617 | D12: Dominant | E12: 7238.0224
A13: No INR monitoring cost for warfarin | B13: -3282.9416 | C13: 0.2362704 | D13: Dominant | E13: 15096.462
A14: Cohort starts at age 80 | B14: -3125.2016 | C14: 0.10517219 | D14: Dominant | E14: 8383.8112
A17: One-way sensitivity (all parameters, sorted by swing) | B17: Low value | C17: High value | D17: INMB at low | E17: INMB at high | F17: Swing
A18: Apixaban OR: stroke | B18: 0.65 | C18: 0.95 | D18: 23049.414 | E18: 11203.656 | F18: 11845.758
A19: Apixaban 5 mg BID, annual drug cost | B19: 149.1681 | C19: 1193.3448 | D19: 18569.455 | E19: 10533.268 | F19: 8036.187
A20: Non-vascular death at age 70 (annual) | B20: 0.025 | C20: 0.041 | D20: 21029.62 | E20: 14837.83 | F20: 6191.7903
A21: Apixaban OR: ICH | B21: 0.3 | C21: 0.58 | D21: 18892.66 | E21: 15481.935 | F21: 3410.7251
A22: Apixaban OR: major bleed | B22: 0.68 | C22: 0.94 | D22: 18973.708 | E22: 15686.396 | F22: 3287.312
A23: Stroke rate on warfarin (annual) | B23: 0.012 | C23: 0.02 | D23: 15844.583 | E23: 18840.105 | F23: 2995.5222
A24: ICH rate on warfarin (annual) | B24: 0.006 | C24: 0.01 | D24: 15980.089 | E24: 18824.553 | F24: 2844.4643
A25: Utility: AF, no prior event | B25: 0.75 | C25: 0.87 | D25: 16041.3 | E25: 18801.557 | F25: 2760.2575
A26: Aspirin RR: stroke | B26: 0.99 | C26: 2.65 | D26: 16405.626 | E26: 18873.403 | F26: 2467.7774
A27: INR monitoring, annual (warfarin only) | B27: 164.80942 | C27: 494.42825 | D27: 16258.945 | E27: 18583.912 | F27: 2324.9669
A28: Utility: after minor stroke / ICH | B28: 0.67 | C28: 0.83 | D28: 18085.052 | E28: 16757.805 | F28: 1327.2476
A29: Stroke risk after prior stroke/ICH | B29: 1.2 | C29: 3.5 | D29: 16877.675 | E29: 18033.986 | F29: 1156.3109
... A67: Disutility: TIA | B67: 0.087 | C67: 0.119 | D67: 17421.505 | E67: 17421.352 | F67: 0.15238458
A69: Probabilistic analysis (5,000 draws, seed 2026) | B69: Value
A70: Apixaban: expected cost | B70: 23168.051
A71: Apixaban: expected QALYs | B71: 7.4483362
A72: Warfarin: expected cost | B72: 28757.329
A73: Warfarin: expected QALYs | B73: 7.2125074
A74: Incremental cost (mean) | B74: -5589.2772
A75: Incremental cost, 2.5th percentile | B75: -8352.1472
A76: Incremental cost, 97.5th percentile | B76: -3242.3247
A77: Incremental QALYs (mean) | B77: 0.23582872
A78: Incremental QALYs, 2.5th percentile | B78: 0.12658787
A79: Incremental QALYs, 97.5th percentile | B79: 0.35878141
A80: Share of draws where apixaban is dominant | B80: 1
A81: Probability cost-effective at $50,000/QALY | B81: 1

Sheet CMA
A1: Cost comparison of oral anticoagulants at current Ontario Drug Benefit prices
A3: Regimen | B3: Dose / frequency | C3: Unit price (ODB) | D3: Units per day | E3: Daily cost | F3: Annual cost | G3: Source
A4: Apixaban 5 mg (generic) | B4: 1 tablet twice daily | C4: =apx_price_tab -> 0.4084 | D4: 2 | E4: =C4*D4 -> 0.8168 | F4: =E4*days_yr -> 298.3362 | G4: ODB formulary, Oct 2026
A5: Edoxaban 60 mg (generic) | B5: 1 tablet once daily | C5: 0.7348 | D5: 1 | E5: =C5*D5 -> 0.7348 | F5: =E5*days_yr -> 268.3857 | G5: ODB Formulary, generic edoxaban 60 mg, Oct 2026
A6: Apixaban 5 mg (Eliquis, brand) | B6: 1 tablet twice daily | C6: 1.6336 | D6: 2 | E6: =C6*D6 -> 3.2672 | F6: =E6*days_yr -> 1193.3448 | G6: ODB Formulary, Oct 2026
A7: Warfarin 5 mg + INR monitoring | B7: Daily, plus INR tests | E7: =F7/days_yr -> 1.0519612 | F7: =c_warfarin+c_inr -> 384.22883 | G7: CADTH worked example (warfarin 2011 ODB; INR inflated to 2025 CAD)
A9: Reading this table: a cost-minimization comparison is only valid between options judged to have similar clinical effects. Among DOACs that judgement belongs to the clinical review; versus warfarin, apixaban is NOT clinically equivalent (fewer strokes and ICH), which is why the main analysis is a cost-utility analysis.
A12: Rivaroxaban and dabigatran are omitted: their current ODB prices could not be verified when this model was built.

Sheet BIA
A1: Budget impact — switching residual warfarin users to generic apixaban, Ontario public drug programs, years 1-3
A3: Input | B3: Value | C3: Source / note
A4: Ontario population aged 65+ | B4: 3100000 | C4: Ontario Ministry of Finance population projections, 2025 (approx. 3.1 million)
A5: AF prevalence, age 65+ | B5: 0.059 | C5: Feinberg et al., Arch Intern Med 1995. ASSUMPTION that it applies to Ontario today
A6: Share of AF patients on an oral anticoagulant | B6: 0.6 | C6: ASSUMPTION
A7: Share of anticoagulated patients still on warfarin | B7: 0.15 | C7: ASSUMPTION. No current Ontario estimate found; most uncertain BIA input (try 5% and 30%)
A8: Uptake: share of warfarin users switched, year 1 | B8: 0.25 | C8: ASSUMPTION
A9: Uptake, year 2 | B9: 0.5 | C9: ASSUMPTION
A10: Uptake, year 3 | B10: 0.75 | C10: ASSUMPTION
A12: Eligible warfarin users (Ontario, 65+) | B12: =pop_65*af_prev*share_oac*share_warf -> 16461
A13: Drug-plan cost difference per patient-year (apixaban − warfarin drug only) | B13: =c_apixaban-c_warfarin -> 243.7262 | C13: CDA-AMC BIA reference case: drug-plan perspective, drug acquisition cost only (no mark-up / dispensing fee)
A15: Year | B15: Patients switched | C15: Drug-plan impact | D15: Health-system impact (drugs, INR, events, long-term care)
A16: Year 1 | B16: =$B$12*uptake_y1 -> 4115.25 | C16: =B16*$B$13 -> 1002994.2 | D16: =B16*hs_diff_y1 -> -1599025.6
A17: Year 2 | B17: =$B$12*uptake_y2 -> 8230.5 | C17: =B17*$B$13 -> 2005988.5 | D17: =B17*hs_diff_y2 -> -3659910.3
A18: Year 3 | B18: =$B$12*uptake_y3 -> 12345.75 | C18: =B18*$B$13 -> 3008982.7 | D18: =B18*hs_diff_y3 -> -5993195.6
A19: 3-year total | C19: =SUM(C16:C18) -> 6017965.5 | D19: =SUM(D16:D18) -> -11252132
A21: Health-system impact uses the per-patient cost difference in model years 1, 2 and 3 (Results sheet), i.e. it treats each year's switchers as starting therapy at age 70 — a simplification of a prevalent population.

Sheet LifeTable
A1: Age | B1: qx (StatCan 2021-2023) | C1: ln(qx) | E1: Gompertz fit
A2: 70 | B2: 0.01819 | C2: =LN(B2) -> -4.0068833 | E2: Slope (per year of age) | F2: =SLOPE(C2:C6,A2:A6) -> 0.10463355
A3: 75 | B3: 0.0295 | C3: =LN(B3) -> -3.523365 | E3: Intercept | F3: =INTERCEPT(C2:C6,A2:A6) -> -11.357682
A4: 80 | B4: 0.04912 | C4: =LN(B4) -> -3.013489 | E4: qx at reference age 70 (fitted) | F4: =EXP(F3+F2*ref_age) -> 0.017715167
A5: 85 | B5: 0.08399 | C5: =LN(B5) -> -2.4770575
A6: 90 | B6: 0.14746 | C6: =LN(B6) -> -1.9141983 | E6: Source: Statistics Canada, Life tables, Canada, 2021-2023, complete life table (both sexes), Table 13-10-0114.
E7: Fitted qx at each age = EXP(intercept + slope x age); used only for its age GRADIENT relative to age 70.
A9: Age | B9: Fitted qx | C9: Model background death (annual)
A10: 70 | B10: =MIN(EXP(gomp_int+gomp_slope*A10),1) -> 0.017715167 | C10: =MIN(p_nonvasc_death*B10/qx_ref,0.999) -> 0.033
A11: 71 | B11: =MIN(EXP(gomp_int+gomp_slope*A11),1) -> 0.019669215 | C11: =MIN(p_nonvasc_death*B11/qx_ref,0.999) -> 0.036640021
A12: 72 | B12: =MIN(EXP(gomp_int+gomp_slope*A12),1) -> 0.021838801 | C12: =MIN(p_nonvasc_death*B12/qx_ref,0.999) -> 0.040681549
A13: 73 | B13: =MIN(EXP(gomp_int+gomp_slope*A13),1) -> 0.024247701 | C13: =MIN(p_nonvasc_death*B13/qx_ref,0.999) -> 0.045168873
A14: 74 | B14: =MIN(EXP(gomp_int+gomp_slope*A14),1) -> 0.026922311 | C14: =MIN(p_nonvasc_death*B14/qx_ref,0.999) -> 0.050151165
A15: 75 | B15: =MIN(EXP(gomp_int+gomp_slope*A15),1) -> 0.029891941 | C15: =MIN(p_nonvasc_death*B15/qx_ref,0.999) -> 0.055683023
A16: 76 | B16: =MIN(EXP(gomp_int+gomp_slope*A16),1) -> 0.033189131 | C16: =MIN(p_nonvasc_death*B16/qx_ref,0.999) -> 0.061825064
A17: 77 | B17: =MIN(EXP(gomp_int+gomp_slope*A17),1) -> 0.036850014 | C17: =MIN(p_nonvasc_death*B17/qx_ref,0.999) -> 0.068644595
A18: 78 | B18: =MIN(EXP(gomp_int+gomp_slope*A18),1) -> 0.040914706 | C18: =MIN(p_nonvasc_death*B18/qx_ref,0.999) -> 0.076216345
A19: 79 | B19: =MIN(EXP(gomp_int+gomp_slope*A19),1) -> 0.045427748 | C19: =MIN(p_nonvasc_death*B19/qx_ref,0.999) -> 0.084623287
A20: 80 | B20: =MIN(EXP(gomp_int+gomp_slope*A20),1) -> 0.050438595 | C20: =MIN(p_nonvasc_death*B20/qx_ref,0.999) -> 0.093957546
A21: 81 | B21: =MIN(EXP(gomp_int+gomp_slope*A21),1) -> 0.056002156 | C21: =MIN(p_nonvasc_death*B21/qx_ref,0.999) -> 0.10432141
... A40: 100 | B40: =MIN(EXP(gomp_int+gomp_slope*A40),1) -> 0.40888241 | C40: =MIN(p_nonvasc_death*B40/qx_ref,0.999) -> 0.76167047

Sheet Apixaban
A1: Apixaban arm — cohort Markov trace (120 x 3-month cycles)
A2: Arm flag (1 = apixaban, 0 = warfarin) | B2: 1 | D2: Annual cost of the anticoagulant strategy (state 0) | H2: =IF($B$2=1,c_apixaban,c_warfarin+c_inr) -> 298.3362
A3: Columns grouped by state (S0 = AF on anticoagulant, S1 = post minor stroke/ICH, S2 = post major stroke, S3 = post major bleed, S4 = dead). Occupancy columns are start-of-cycle; 'New' columns feed the next row.
A5: Cycle | B5: Age | C5: Discount factor | D5: Apixaban effect multiplier (waning) | E5: Background death (annual) | F5: Stroke age factor | G5: Occupancy S0 | H5: Occupancy S1 | I5: Occupancy S2 | J5: Occupancy S3 | K5: Occupancy S4 | L5: S0: p background death | M5: S0: survivors of background death | N5: S0: p stroke | O5: S0: p ich | P5: S0: p mb | Q5: S0: p mi | R5: S0: p tia | S5: S0: p minor | T5: S0: n stroke | U5: S0: n ich | V5: S0: n mb | W5: S0: n mi | X5: S0: n tia | Y5: S0: n minor | Z5: S0: fatal strokes | AA5: S0: non-fatal major strokes | AB5: S0: non-fatal minor strokes | AC5: S0: non-fatal ICH | AD5: S0: non-fatal major bleeds | AE5: S0: fatal MI | AF5: S0: non-fatal MI | AG5: S0: remain (no state-changing event) | AH5: S0: event costs | AI5: S0: event QALY loss | AJ5: S0: all deaths this cycle | AK5: S1: p background death | AL5: S1: survivors of background death | AM5: S1: p stroke | AN5: S1: p ich | AO5: S1: p mb | AP5: S1: p mi | AQ5: S1: p tia | AR5: S1: p minor | AS5: S1: n stroke | AT5: S1: n ich | AU5: S1: n mb | AV5: S1: n mi | AW5: S1: n tia | AX5: S1: n minor | AY5: S1: fatal strokes | AZ5: S1: non-fatal major strokes | BA5: S1: non-fatal minor strokes | BB5: S1: non-fatal ICH | BC5: S1: non-fatal major bleeds | BD5: S1: fatal MI | BE5: S1: non-fatal MI | BF5: S1: remain (no state-changing event) | BG5: S1: event costs | BH5: S1: event QALY loss | BI5: S1: all deaths this cycle | BJ5: S2: p background death | BK5: S2: survivors of background death | BL5: S2: p stroke | BM5: S2: p ich | BN5: S2: p mb | BO5: S2: p mi | BP5: S2: p tia | BQ5: S2: p minor | BR5: S2: n stroke | BS5: S2: n ich | BT5: S2: n mb | BU5: S2: n mi | BV5: S2: n tia | BW5: S2: n minor | BX5: S2: fatal strokes | BY5: S2: non-fatal major strokes | BZ5: S2: non-fatal minor strokes | CA5: S2: non-fatal ICH | CB5: S2: non-fatal major bleeds | CC5: S2: fatal MI | CD5: S2: non-fatal MI | CE5: S2: remain (no state-changing event) | CF5: S2: event costs | CG5: S2: event QALY loss | CH5: S2: all deaths this cycle | CI5: S3: p background death | CJ5: S3: survivors of background death | CK5: S3: p stroke | CL5: S3: p ich | CM5: S3: p mb | CN5: S3: p mi | CO5: S3: p tia | CP5: S3: p minor | CQ5: S3: n stroke | CR5: S3: n ich | CS5: S3: n mb | CT5: S3: n mi | CU5: S3: n tia | CV5: S3: n minor | CW5: S3: fatal strokes | CX5: S3: non-fatal major strokes | CY5: S3: non-fatal minor strokes | CZ5: S3: non-fatal ICH | DA5: S3: non-fatal major bleeds | DB5: S3: fatal MI | DC5: S3: non-fatal MI | DD5: S3: remain (no state-changing event) | DE5: S3: event costs | DF5: S3: event QALY loss | DG5: S3: all deaths this cycle | DH5: New S0 (next cycle) | DI5: New S1 (next cycle) | DJ5: New S2 (next cycle) | DK5: New S3 (next cycle) | DL5: New S4 (next cycle) | DM5: Mass check (=1) | DN5: Drug cost | DO5: Long-term care cost | DP5: Event cost | DQ5: Total cost (undiscounted) | DR5: QALYs (undiscounted) | DS5: Life-years (undiscounted) | DT5: Total cost (discounted) | DU5: Drug cost (disc.) | DV5: Event cost (disc.) | DW5: Long-term cost (disc.) | DX5: QALYs (discounted) | DY5: Life-years (discounted) | DZ5: Strokes this cycle | EA5: ICH this cycle | EB5: Major bleeds this cycle | EC5: Discounted years on anticoagulant (S0)
A6: 0 | B6: =start_age+A6*dt -> 70 | C6: =(1+disc_rate)^-(A6*dt) -> 1 | D6: =IF(A6*dt>=wane_start,(1-wane_decay)^(A6*dt-wane_start),1) -> 1 | E6: =MIN(p_nonvasc_death*MIN(EXP(gomp_int+gomp_slope*INT(B6)),1)/qx_ref,0.999) -> 0.033 | F6: =rr_stroke_per_decade^((B6-ref_age)/10) -> 1 | G6: 1 | H6: 0 | I6: 0 | J6: 0 | K6: 0 | L6: =1-EXP(LN(1-E6)*dt) -> 0.0083541048 | M6: =G6*(1-L6) -> 0.9916459 | N6: =IF(Apixaban!$B$2=1,EXP(LN(or_apx_stroke)*D6)*(1-EXP(-r_stroke*F6*dt))/(1-(1-EXP(-r_stroke*F6*dt))+EXP(LN(or_apx_stroke)*D6)*(1-EXP(-r_stroke*F6*dt))),(1-EXP(-r_stroke*F6*dt))) -> 0.0031818279 | O6: =IF(Apixaban!$B$2=1,EXP(LN(or_apx_ich)*D6)*(1-EXP(-r_ich*dt))/(1-(1-EXP(-r_ich*dt))+EXP(LN(or_apx_ich)*D6)*(1-EXP(-r_ich*dt))),(1-EXP(-r_ich*dt))) -> 0.00084351325 | P6: =IF(Apixaban!$B$2=1,EXP(LN(or_apx_mb)*D6)*(1-EXP(-r_mb*dt))/(1-(1-EXP(-r_mb*dt))+EXP(LN(or_apx_mb)*D6)*(1-EXP(-r_mb*dt))),(1-EXP(-r_mb*dt))) -> 0.0066944691 | Q6: =IF(Apixaban!$B$2=1,EXP(LN(or_apx_mi)*D6)*(1-EXP(-r_mi*dt))/(1-(1-EXP(-r_mi*dt))+EXP(LN(or_apx_mi)*D6)*(1-EXP(-r_mi*dt))),(1-EXP(-r_mi*dt))) -> 0.0013232192 | R6: =(1-EXP(-r_tia*dt)) -> 0.0020060282 | S6: =(1-EXP(-r_minor*dt)) -> 0.043793769 | T6: =M6*N6 -> 0.0031552465 | U6: =M6*O6 -> 0.00083646645 | V6: =M6*P6 -> 0.0066385428 | W6: =M6*Q6 -> 0.0013121648 | X6: =M6*R6 -> 0.0019892696 | Y6: =M6*S6 -> 0.043427911 | Z6: =T6*f_stroke_fatal -> 0.00074779343 | AA6: =T6*(1-f_stroke_fatal)*f_stroke_major -> 0.00080168188 | AB6: =T6*(1-f_stroke_fatal)*(1-f_stroke_major) -> 0.0016057712 | AC6: =U6*(1-f_bleed_fatal) -> 0.00076620327 | AD6: =V6*(1-f_bleed_fatal) -> 0.0060809052 | AE6: =W6*f_mi_fatal -> 0.00015877195 | AF6: =W6-AE6 -> 0.0011533929 | AG6: =M6-T6-U6-V6-AE6 -> 0.98085687 | AH6: =Z6*c_stroke_fatal+AA6*c_stroke_major+AB6*c_stroke_minor+U6*c_ich+V6*c_major_bleed+AE6*c_mi_fatal+AF6*c_mi_nonfatal+X6*c_tia+Y6*c_minor_bleed -> 212.93878 | AI6: =dt*(AF6*dec_mi+AD6*dec_major_bleed+Y6*dec_minor_bleed+X6*dec_tia) -> 0.00036826875 | AJ6: =G6*L6+Z6+U6-AC6+V6-AD6+AE6 -> 0.0098885709 | AK6: =1-EXP(LN(1-E6)*hr_death_prior_stroke*dt) -> 0.019110191 | AL6: =H6*(1-AK6) -> 0 | AM6: =(1-EXP(-r_stroke*F6*rr_stroke_prior*rr_asa_stroke*dt)) -> 0.014268505 | AN6: =(1-EXP(-r_ich*rr_asa_ich*dt)) -> 0.0010235777 | AO6: =(1-EXP(-r_mb*rr_asa_mb*dt)) -> 0.0095180967 | AP6: =(1-EXP(-r_mi*rr_asa_mi*dt)) -> 0.0021341352 | AQ6: =(1-EXP(-r_tia*rr_asa_tia*dt)) -> 0.0031276457 | AR6: =(1-EXP(-r_minor*rr_asa_minor*dt)) -> 0.027818195 | AS6: =AL6*AM6 -> 0 | AT6: =AL6*AN6 -> 0 | AU6: =AL6*AO6 -> 0 | AV6: =AL6*AP6 -> 0 | AW6: =AL6*AQ6 -> 0 | AX6: =AL6*AR6 -> 0 | AY6: =AS6*f_stroke_fatal_recur -> 0 | AZ6: =AS6*(1-f_stroke_fatal_recur)*f_stroke_major -> 0 | BA6: =AS6*(1-f_stroke_fatal_recur)*(1-f_stroke_major) -> 0 | BB6: =AT6*(1-f_bleed_fatal) -> 0 | BC6: =AU6*(1-f_bleed_fatal) -> 0 | BD6: =AV6*f_mi_fatal -> 0 | BE6: =AV6-BD6 -> 0 | BF6: =AL6-AS6-AT6-AU6-BD6 -> 0 | BG6: =AY6*c_stroke_fatal+AZ6*c_stroke_major+BA6*c_stroke_minor+AT6*c_ich+AU6*c_major_bleed+BD6*c_mi_fatal+BE6*c_mi_nonfatal+AW6*c_tia+AX6*c_minor_bleed -> 0 | BH6: =dt*(BE6*dec_mi+BC6*dec_major_bleed+AX6*dec_minor_bleed+AW6*dec_tia) -> 0 | BI6: =H6*AK6+AY6+AT6-BB6+AU6-BC6+BD6 -> 0 | BJ6: =1-EXP(LN(1-E6)*hr_death_prior_stroke*dt) -> 0.019110191 | BK6: =I6*(1-BJ6) -> 0 | BL6: =(1-EXP(-r_stroke*F6*rr_stroke_prior*rr_asa_stroke*dt)) -> 0.014268505 | BM6: =(1-EXP(-r_ich*rr_asa_ich*dt)) -> 0.0010235777 | BN6: =(1-EXP(-r_mb*rr_asa_mb*dt)) -> 0.0095180967 | BO6: =(1-EXP(-r_mi*rr_asa_mi*dt)) -> 0.0021341352 | BP6: =(1-EXP(-r_tia*rr_asa_tia*dt)) -> 0.0031276457 | BQ6: =(1-EXP(-r_minor*rr_asa_minor*dt)) -> 0.027818195 | BR6: =BK6*BL6 -> 0 | BS6: =BK6*BM6 -> 0 | BT6: =BK6*BN6 -> 0 | BU6: =BK6*BO6 -> 0 | BV6: =BK6*BP6 -> 0 | BW6: =BK6*BQ6 -> 0 | BX6: =BR6*f_stroke_fatal_recur -> 0 | BY6: =BR6*(1-f_stroke_fatal_recur)*f_stroke_major -> 0 | BZ6: =BR6*(1-f_stroke_fatal_recur)*(1-f_stroke_major) -> 0 | CA6: =BS6*(1-f_bleed_fatal) -> 0 | CB6: =BT6*(1-f_bleed_fatal) -> 0 | CC6: =BU6*f_mi_fatal -> 0 | CD6: =BU6-CC6 -> 0 | CE6: =BK6-BR6-BS6-BT6-CC6 -> 0 | CF6: =BX6*c_stroke_fatal+BY6*c_stroke_major+BZ6*c_stroke_minor+BS6*c_ich+BT6*c_major_bleed+CC6*c_mi_fatal+CD6*c_mi_nonfatal+BV6*c_tia+BW6*c_minor_bleed -> 0 | CG6: =dt*(CD6*dec_mi+CB6*dec_major_bleed+BW6*dec_minor_bleed+BV6*dec_tia) -> 0 | CH6: =I6*BJ6+BX6+BS6-CA6+BT6-CB6+CC6 -> 0 | CI6: =1-EXP(LN(1-E6)*dt) -> 0.0083541048 | CJ6: =J6*(1-CI6) -> 0 | CK6: =(1-EXP(-r_stroke*F6*rr_asa_stroke*dt)) -> 0.0065111099 | CL6: =(1-EXP(-r_ich*rr_asa_ich*dt)) -> 0.0010235777 | CM6: =(1-EXP(-r_mb*rr_asa_mb*dt)) -> 0.0095180967 | CN6: =(1-EXP(-r_mi*rr_asa_mi*dt)) -> 0.0021341352 | CO6: =(1-EXP(-r_tia*rr_asa_tia*dt)) -> 0.0031276457 | CP6: =(1-EXP(-r_minor*rr_asa_minor*dt)) -> 0.027818195 | CQ6: =CJ6*CK6 -> 0 | CR6: =CJ6*CL6 -> 0 | CS6: =CJ6*CM6 -> 0 | CT6: =CJ6*CN6 -> 0 | CU6: =CJ6*CO6 -> 0 | CV6: =CJ6*CP6 -> 0 | CW6: =CQ6*f_stroke_fatal -> 0 | CX6: =CQ6*(1-f_stroke_fatal)*f_stroke_major -> 0 | CY6: =CQ6*(1-f_stroke_fatal)*(1-f_stroke_major) -> 0 | CZ6: =CR6*(1-f_bleed_fatal) -> 0 | DA6: =CS6*(1-f_bleed_fatal) -> 0 | DB6: =CT6*f_mi_fatal -> 0 | DC6: =CT6-DB6 -> 0 | DD6: =CJ6-CQ6-CR6-CS6-DB6 -> 0 | DE6: =CW6*c_stroke_fatal+CX6*c_stroke_major+CY6*c_stroke_minor+CR6*c_ich+CS6*c_major_bleed+DB6*c_mi_fatal+DC6*c_mi_nonfatal+CU6*c_tia+CV6*c_minor_bleed -> 0 | DF6: =dt*(DC6*dec_mi+DA6*dec_major_bleed+CV6*dec_minor_bleed+CU6*dec_tia) -> 0 | DG6: =J6*CI6+CW6+CR6-CZ6+CS6-DA6+DB6 -> 0 | DH6: =AG6 -> 0.98085687 | DI6: =AB6+AC6+BF6+BA6+BB6+BC6+CY6+CZ6 -> 0.0023719745 | DJ6: =AA6+AZ6+BY6+CX6+CE6+BZ6+CA6+CB6 -> 0.00080168188 | DK6: =AD6+DD6+DA6 -> 0.0060809052 | DL6: =K6+AJ6+BI6+CH6+DG6 -> 0.0098885709 | DM6: =SUM(DH6:DL6) -> 1 | DN6: =dt*(G6*Apixaban!$H$2+(H6+I6+J6)*c_aspirin) -> 74.58405 | DO6: =dt*(H6*c_lt_minor_stroke+I6*c_lt_major_stroke) -> 0 | DP6: =AH6+BG6+CF6+DE6 -> 212.93878 | DQ6: =DN6+DO6+DP6 -> 287.52283 | DR6: =dt*(G6*(u_af-dec_per_year_over_70*MAX(B6-ref_age,0))+H6*(u_minor_stroke-dec_per_year_over_70*MAX(B6-ref_age,0))+I6*(u_major_stroke-dec_per_year_over_70*MAX(B6-ref_age,0))+J6*(u_af-dec_per_year_over_70*MAX(B6-ref_age,0)))-AI6-BH6-CG6-DF6 -> 0.20213173 | DS6: =dt*(G6+H6+I6+J6) -> 0.25 | DT6: =DQ6*C6 -> 287.52283 | DU6: =DN6*C6 -> 74.58405 | DV6: =DP6*C6 -> 212.93878 | DW6: =DO6*C6 -> 0 | DX6: =DR6*C6 -> 0.20213173 | DY6: =DS6*C6 -> 0.25 | DZ6: =T6+AS6+BR6+CQ6 -> 0.0031552465 | EA6: =U6+AT6+BS6+CR6 -> 0.00083646645 | EB6: =V6+AU6+BT6+CS6 -> 0.0066385428 | EC6: =G6*dt*C6 -> 0.25
A7: 1 | B7: =start_age+A7*dt -> 70.25 | C7: =(1+disc_rate)^-(A7*dt) -> 0.99628477 | D7: =IF(A7*dt>=wane_start,(1-wane_decay)^(A7*dt-wane_start),1) -> 1 | E7: =MIN(p_nonvasc_death*MIN(EXP(gomp_int+gomp_slope*INT(B7)),1)/qx_ref,0.999) -> 0.033 | F7: =rr_stroke_per_decade^((B7-ref_age)/10) -> 1.0101882 | G7: =DH6 -> 0.98085687 | H7: =DI6 -> 0.0023719745 | I7: =DJ6 -> 0.00080168188 | J7: =DK6 -> 0.0060809052 | K7: =DL6 -> 0.0098885709 | L7: =1-EXP(LN(1-E7)*dt) -> 0.0083541048 | M7: =G7*(1-L7) -> 0.97266269 | N7: =IF(Apixaban!$B$2=1,EXP(LN(or_apx_stroke)*D7)*(1-EXP(-r_stroke*F7*dt))/(1-(1-EXP(-r_stroke*F7*dt))+EXP(LN(or_apx_stroke)*D7)*(1-EXP(-r_stroke*F7*dt))),(1-EXP(-r_stroke*F7*dt))) -> 0.0032142065 | O7: =IF(Apixaban!$B$2=1,EXP(LN(or_apx_ich)*D7)*(1-EXP(-r_ich*dt))/(1-(1-EXP(-r_ich*dt))+EXP(LN(or_apx_ich)*D7)*(1-EXP(-r_ich*dt))),(1-EXP(-r_ich*dt))) -> 0.00084351325 | P7: =IF(Apixaban!$B$2=1,EXP(LN(or_apx_mb)*D7)*(1-EXP(-r_mb*dt))/(1-(1-EXP(-r_mb*dt))+EXP(LN(or_apx_mb)*D7)*(1-EXP(-r_mb*dt))),(1-EXP(-r_mb*dt))) -> 0.0066944691 | Q7: =IF(Apixaban!$B$2=1,EXP(LN(or_apx_mi)*D7)*(1-EXP(-r_mi*dt))/(1-(1-EXP(-r_mi*dt))+EXP(LN(or_apx_mi)*D7)*(1-EXP(-r_mi*dt))),(1-EXP(-r_mi*dt))) -> 0.0013232192 | R7: =(1-EXP(-r_tia*dt)) -> 0.0020060282 | S7: =(1-EXP(-r_minor*dt)) -> 0.043793769 | T7: =M7*N7 -> 0.0031263388 | U7: =M7*O7 -> 0.00082045386 | V7: =M7*P7 -> 0.0065114603 | W7: =M7*Q7 -> 0.0012870459 | X7: =M7*R7 -> 0.0019511887 | Y7: =M7*S7 -> 0.042596565 | Z7: =T7*f_stroke_fatal -> 0.00074094229 | AA7: =T7*(1-f_stroke_fatal)*f_stroke_major -> 0.00079433703 | AB7: =T7*(1-f_stroke_fatal)*(1-f_stroke_major) -> 0.0015910595 | AC7: =U7*(1-f_bleed_fatal) -> 0.00075153574 | AD7: =V7*(1-f_bleed_fatal) -> 0.0059644976 | AE7: =W7*f_mi_fatal -> 0.00015573255 | AF7: =W7-AE7 -> 0.0011313133 | AG7: =M7-T7-U7-V7-AE7 -> 0.9620487 | AH7: =Z7*c_stroke_fatal+AA7*c_stroke_major+AB7*c_stroke_minor+U7*c_ich+V7*c_major_bleed+AE7*c_mi_fatal+AF7*c_mi_nonfatal+X7*c_tia+Y7*c_minor_bleed -> 210.02608 | AI7: =dt*(AF7*dec_mi+AD7*dec_major_bleed+Y7*dec_minor_bleed+X7*dec_tia) -> 0.00036121893 | AJ7: =G7*L7+Z7+U7-AC7+V7-AD7+AE7 -> 0.0097067367 | AK7: =1-EXP(LN(1-E7)*hr_death_prior_stroke*dt) -> 0.019110191 | AL7: =H7*(1-AK7) -> 0.0023266456 | AM7: =(1-EXP(-r_stroke*F7*rr_stroke_prior*rr_asa_stroke*dt)) -> 0.014412823 | AN7: =(1-EXP(-r_ich*rr_asa_ich*dt)) -> 0.0010235777 | AO7: =(1-EXP(-r_mb*rr_asa_mb*dt)) -> 0.0095180967 | AP7: =(1-EXP(-r_mi*rr_asa_mi*dt)) -> 0.0021341352 | AQ7: =(1-EXP(-r_tia*rr_asa_tia*dt)) -> 0.0031276457 | AR7: =(1-EXP(-r_minor*rr_asa_minor*dt)) -> 0.027818195 | AS7: =AL7*AM7 -> 3.3533531e-05 | AT7: =AL7*AN7 -> 2.3815025e-06 | AU7: =AL7*AO7 -> 2.2145238e-05 | AV7: =AL7*AP7 -> 4.9653762e-06 | AW7: =AL7*AQ7 -> 7.276923e-06 | AX7: =AL7*AR7 -> 6.4723081e-05 | AY7: =AS7*f_stroke_fatal_recur -> 1.2477491e-05 | AZ7: =AS7*(1-f_stroke_fatal_recur)*f_stroke_major -> 7.0116611e-06 | BA7: =AS7*(1-f_stroke_fatal_recur)*(1-f_stroke_major) -> 1.4044378e-05 | BB7: =AT7*(1-f_bleed_fatal) -> 2.1814563e-06 | BC7: =AU7*(1-f_bleed_fatal) -> 2.0285038e-05 | BD7: =AV7*f_mi_fatal -> 6.0081052e-07 | BE7: =AV7-BD7 -> 4.3645657e-06 | BF7: =AL7-AS7-AT7-AU7-BD7 -> 0.0022679845 | BG7: =AY7*c_stroke_fatal+AZ7*c_stroke_major+BA7*c_stroke_minor+AT7*c_ich+AU7*c_major_bleed+BD7*c_mi_fatal+BE7*c_mi_nonfatal+AW7*c_tia+AX7*c_minor_bleed -> 1.46952 | BH7: =dt*(BE7*dec_mi+BC7*dec_major_bleed+AX7*dec_minor_bleed+AW7*dec_tia) -> 1.0006793e-06 | BI7: =H7*AK7+AY7+AT7-BB7+AU7-BC7+BD7 -> 6.0467433e-05 | BJ7: =1-EXP(LN(1-E7)*hr_death_prior_stroke*dt) -> 0.019110191 | BK7: =I7*(1-BJ7) -> 0.00078636159 | BL7: =(1-EXP(-r_stroke*F7*rr_stroke_prior*rr_asa_stroke*dt)) -> 0.014412823 | BM7: =(1-EXP(-r_ich*rr_asa_ich*dt)) -> 0.0010235777 | BN7: =(1-EXP(-r_mb*rr_asa_mb*dt)) -> 0.0095180967 | BO7: =(1-EXP(-r_mi*rr_asa_mi*dt)) -> 0.0021341352 | BP7: =(1-EXP(-r_tia*rr_asa_tia*dt)) -> 0.0031276457 | BQ7: =(1-EXP(-r_minor*rr_asa_minor*dt)) -> 0.027818195 | BR7: =BK7*BL7 -> 1.133369e-05 | BS7: =BK7*BM7 -> 8.0490217e-07 | BT7: =BK7*BN7 -> 7.4846657e-06 | BU7: =BK7*BO7 -> 1.6782019e-06 | BV7: =BK7*BP7 -> 2.4594604e-06 | BW7: =BK7*BQ7 -> 2.187516e-05 | BX7: =BR7*f_stroke_fatal_recur -> 4.2171528e-06 | BY7: =BR7*(1-f_stroke_fatal_recur)*f_stroke_major -> 2.369807e-06 | BZ7: =BR7*(1-f_stroke_fatal_recur)*(1-f_stroke_major) -> 4.7467305e-06 | CA7: =BS7*(1-f_bleed_fatal) -> 7.3729039e-07 | CB7: =BT7*(1-f_bleed_fatal) -> 6.8559538e-06 | CC7: =BU7*f_mi_fatal -> 2.0306243e-07 | CD7: =BU7-CC7 -> 1.4751395e-06 | CE7: =BK7-BR7-BS7-BT7-CC7 -> 0.00076653527 | CF7: =BX7*c_stroke_fatal+BY7*c_stroke_major+BZ7*c_stroke_minor+BS7*c_ich+BT7*c_major_bleed+CC7*c_mi_fatal+CD7*c_mi_nonfatal+BV7*c_tia+BW7*c_minor_bleed -> 0.49666957 | CG7: =dt*(CD7*dec_mi+CB7*dec_major_bleed+BW7*dec_minor_bleed+BV7*dec_tia) -> 3.3821042e-07 | CH7: =I7*BJ7+BX7+BS7-CA7+BT7-CB7+CC7 -> 2.0436833e-05 | CI7: =1-EXP(LN(1-E7)*dt) -> 0.0083541048 | CJ7: =J7*(1-CI7) -> 0.0060301047 | CK7: =(1-EXP(-r_stroke*F7*rr_asa_stroke*dt)) -> 0.0065772277 | CL7: =(1-EXP(-r_ich*rr_asa_ich*dt)) -> 0.0010235777 | CM7: =(1-EXP(-r_mb*rr_asa_mb*dt)) -> 0.0095180967 | CN7: =(1-EXP(-r_mi*rr_asa_mi*dt)) -> 0.0021341352 | CO7: =(1-EXP(-r_tia*rr_asa_tia*dt)) -> 0.0031276457 | CP7: =(1-EXP(-r_minor*rr_asa_minor*dt)) -> 0.027818195 | CQ7: =CJ7*CK7 -> 3.9661371e-05 | CR7: =CJ7*CL7 -> 6.1722805e-06 | CS7: =CJ7*CM7 -> 5.739512e-05 | CT7: =CJ7*CN7 -> 1.2869058e-05 | CU7: =CJ7*CO7 -> 1.8860031e-05 | CV7: =CJ7*CP7 -> 0.00016774663 | CW7: =CQ7*f_stroke_fatal -> 9.399745e-06 | CX7: =CQ7*(1-f_stroke_fatal)*f_stroke_major -> 1.0077122e-05 | CY7: =CQ7*(1-f_stroke_fatal)*(1-f_stroke_major) -> 2.0184505e-05 | CZ7: =CR7*(1-f_bleed_fatal) -> 5.653809e-06 | DA7: =CS7*(1-f_bleed_fatal) -> 5.2573929e-05 | DB7: =CT7*f_mi_fatal -> 1.5571561e-06 | DC7: =CT7-DB7 -> 1.1311902e-05 | DD7: =CJ7-CQ7-CR7-CS7-DB7 -> 0.0059253187 | DE7: =CW7*c_stroke_fatal+CX7*c_stroke_major+CY7*c_stroke_minor+CR7*c_ich+CS7*c_major_bleed+DB7*c_mi_fatal+DC7*c_mi_nonfatal+CU7*c_tia+CV7*c_minor_bleed -> 2.2773971 | DF7: =dt*(DC7*dec_mi+DA7*dec_major_bleed+CV7*dec_minor_bleed+CU7*dec_tia) -> 2.5935197e-06 | DG7: =J7*CI7+CW7+CR7-CZ7+CS7-DA7+DB7 -> 6.7097082e-05 | DH7: =AG7 -> 0.9620487 | DI7: =AB7+AC7+BF7+BA7+BB7+BC7+CY7+CZ7 -> 0.0046729289 | DJ7: =AA7+AZ7+BY7+CX7+CE7+BZ7+CA7+CB7 -> 0.0015926709 | DK7: =AD7+DD7+DA7 -> 0.01194239 | DL7: =K7+AJ7+BI7+CH7+DG7 -> 0.019743309 | DM7: =SUM(DH7:DL7) -> 1 | DN7: =dt*(G7*Apixaban!$H$2+(H7+I7+J7)*c_aspirin) -> 73.246602 | DO7: =dt*(H7*c_lt_minor_stroke+I7*c_lt_major_stroke) -> 11.646143 | DP7: =AH7+BG7+CF7+DE7 -> 214.26966 | DQ7: =DN7+DO7+DP7 -> 299.16241 | DR7: =dt*(G7*(u_af-dec_per_year_over_70*MAX(B7-ref_age,0))+H7*(u_minor_stroke-dec_per_year_over_70*MAX(B7-ref_age,0))+I7*(u_major_stroke-dec_per_year_over_70*MAX(B7-ref_age,0))+J7*(u_af-dec_per_year_over_70*MAX(B7-ref_age,0)))-AI7-BH7-CG7-DF7 -> 0.19998321 | DS7: =dt*(G7+H7+I7+J7) -> 0.24752786 | DT7: =DQ7*C7 -> 298.05095 | DU7: =DN7*C7 -> 72.974474 | DV7: =DP7*C7 -> 213.4736 | DW7: =DO7*C7 -> 11.602874 | DX7: =DR7*C7 -> 0.19924022 | DY7: =DS7*C7 -> 0.24660823 | DZ7: =T7+AS7+BR7+CQ7 -> 0.0032108674 | EA7: =U7+AT7+BS7+CR7 -> 0.00082981255 | EB7: =V7+AU7+BT7+CS7 -> 0.0065984853 | EC7: =G7*dt*C7 -> 0.24430319
A8: 2 | B8: =start_age+A8*dt -> 70.5 | C8: =(1+disc_rate)^-(A8*dt) -> 0.99258333 | D8: =IF(A8*dt>=wane_start,(1-wane_decay)^(A8*dt-wane_start),1) -> 1 | E8: =MIN(p_nonvasc_death*MIN(EXP(gomp_int+gomp_slope*INT(B8)),1)/qx_ref,0.999) -> 0.033 | F8: =rr_stroke_per_decade^((B8-ref_age)/10) -> 1.0204802 | G8: =DH7 -> 0.9620487 | H8: =DI7 -> 0.0046729289 | I8: =DJ7 -> 0.0015926709 | J8: =DK7 -> 0.01194239 | K8: =DL7 -> 0.019743309 | L8: =1-EXP(LN(1-E8)*dt) -> 0.0083541048 | M8: =G8*(1-L8) -> 0.95401165 | N8: =IF(Apixaban!$B$2=1,EXP(LN(or_apx_stroke)*D8)*(1-EXP(-r_stroke*F8*dt))/(1-(1-EXP(-r_stroke*F8*dt))+EXP(LN(or_apx_stroke)*D8)*(1-EXP(-r_stroke*F8*dt))),(1-EXP(-r_stroke*F8*dt))) -> 0.0032469143 | O8: =IF(Apixaban!$B$2=1,EXP(LN(or_apx_ich)*D8)*(1-EXP(-r_ich*dt))/(1-(1-EXP(-r_ich*dt))+EXP(LN(or_apx_ich)*D8)*(1-EXP(-r_ich*dt))),(1-EXP(-r_ich*dt))) -> 0.00084351325 | P8: =IF(Apixaban!$B$2=1,EXP(LN(or_apx_mb)*D8)*(1-EXP(-r_mb*dt))/(1-(1-EXP(-r_mb*dt))+EXP(LN(or_apx_mb)*D8)*(1-EXP(-r_mb*dt))),(1-EXP(-r_mb*dt))) -> 0.0066944691 | Q8: =IF(Apixaban!$B$2=1,EXP(LN(or_apx_mi)*D8)*(1-EXP(-r_mi*dt))/(1-(1-EXP(-r_mi*dt))+EXP(LN(or_apx_mi)*D8)*(1-EXP(-r_mi*dt))),(1-EXP(-r_mi*dt))) -> 0.0013232192 | R8: =(1-EXP(-r_tia*dt)) -> 0.0020060282 | S8: =(1-EXP(-r_minor*dt)) -> 0.043793769 | T8: =M8*N8 -> 0.0030975941 | U8: =M8*O8 -> 0.00080472146 | V8: =M8*P8 -> 0.0063866015 | W8: =M8*Q8 -> 0.0012623665 | X8: =M8*R8 -> 0.0019137742 | Y8: =M8*S8 -> 0.041779766 | Z8: =T8*f_stroke_fatal -> 0.0007341298 | AA8: =T8*(1-f_stroke_fatal)*f_stroke_major -> 0.00078703361 | AB8: =T8*(1-f_stroke_fatal)*(1-f_stroke_major) -> 0.0015764307 | AC8: =U8*(1-f_bleed_fatal) -> 0.00073712486 | AD8: =V8*(1-f_bleed_fatal) -> 0.0058501269 | AE8: =W8*f_mi_fatal -> 0.00015274634 | AF8: =W8-AE8 -> 0.0011096201 | AG8: =M8-T8-U8-V8-AE8 -> 0.94356998 | AH8: =Z8*c_stroke_fatal+AA8*c_stroke_major+AB8*c_stroke_minor+U8*c_ich+V8*c_major_bleed+AE8*c_mi_fatal+AF8*c_mi_nonfatal+X8*c_tia+Y8*c_minor_bleed -> 207.15167 | AI8: =dt*(AF8*dec_mi+AD8*dec_major_bleed+Y8*dec_minor_bleed+X8*dec_tia) -> 0.00035429247 | AJ8: =G8*L8+Z8+U8-AC8+V8-AD8+AE8 -> 0.0095280029 | AK8: =1-EXP(LN(1-E8)*hr_death_prior_stroke*dt) -> 0.019110191 | AL8: =H8*(1-AK8) -> 0.0045836283 | AM8: =(1-EXP(-r_stroke*F8*rr_stroke_prior*rr_asa_stroke*dt)) -> 0.014558589 | AN8: =(1-EXP(-r_ich*rr_asa_ich*dt)) -> 0.0010235777 | AO8: =(1-EXP(-r_mb*rr_asa_mb*dt)) -> 0.0095180967 | AP8: =(1-EXP(-r_mi*rr_asa_mi*dt)) -> 0.0021341352 | AQ8: =(1-EXP(-r_tia*rr_asa_tia*dt)) -> 0.0031276457 | AR8: =(1-EXP(-r_minor*rr_asa_minor*dt)) -> 0.027818195 | AS8: =AL8*AM8 -> 6.6731162e-05 | AT8: =AL8*AN8 -> 4.6916997e-06 | AU8: =AL8*AO8 -> 4.3627418e-05 | AV8: =AL8*AP8 -> 9.7820824e-06 | AW8: =AL8*AQ8 -> 1.4335965e-05 | AX8: =AL8*AR8 -> 0.00012750827 | AY8: =AS8*f_stroke_fatal_recur -> 2.4829998e-05 | AZ8: =AS8*(1-f_stroke_fatal_recur)*f_stroke_major -> 1.3953088e-05 | BA8: =AS8*(1-f_stroke_fatal_recur)*(1-f_stroke_major) -> 2.7948076e-05 | BB8: =AT8*(1-f_bleed_fatal) -> 4.2975969e-06 | BC8: =AU8*(1-f_bleed_fatal) -> 3.9962715e-05 | BD8: =AV8*f_mi_fatal -> 1.183632e-06 | BE8: =AV8-BD8 -> 8.5984504e-06 | BF8: =AL8-AS8-AT8-AU8-BD8 -> 0.0044673944 | BG8: =AY8*c_stroke_fatal+AZ8*c_stroke_major+BA8*c_stroke_minor+AT8*c_ich+AU8*c_major_bleed+BD8*c_mi_fatal+BE8*c_mi_nonfatal+AW8*c_tia+AX8*c_minor_bleed -> 2.9180776 | BH8: =dt*(BE8*dec_mi+BC8*dec_major_bleed+AX8*dec_minor_bleed+AW8*dec_tia) -> 1.971397e-06 | BI8: =H8*AK8+AY8+AT8-BB8+AU8-BC8+BD8 -> 0.000119373 | BJ8: =1-EXP(LN(1-E8)*hr_death_prior_stroke*dt) -> 0.019110191 | BK8: =I8*(1-BJ8) -> 0.0015622346 | BL8: =(1-EXP(-r_stroke*F8*rr_stroke_prior*rr_asa_stroke*dt)) -> 0.014558589 | BM8: =(1-EXP(-r_ich*rr_asa_ich*dt)) -> 0.0010235777 | BN8: =(1-EXP(-r_mb*rr_asa_mb*dt)) -> 0.0095180967 | BO8: =(1-EXP(-r_mi*rr_asa_mi*dt)) -> 0.0021341352 | BP8: =(1-EXP(-r_tia*rr_asa_tia*dt)) -> 0.0031276457 | BQ8: =(1-EXP(-r_minor*rr_asa_minor*dt)) -> 0.027818195 | BR8: =BK8*BL8 -> 2.2743932e-05 | BS8: =BK8*BM8 -> 1.5990685e-06 | BT8: =BK8*BN8 -> 1.48695e-05 | BU8: =BK8*BO8 -> 3.3340198e-06 | BV8: =BK8*BP8 -> 4.8861163e-06 | BW8: =BK8*BQ8 -> 4.3458547e-05 | BX8: =BR8*f_stroke_fatal_recur -> 8.4627896e-06 | BY8: =BR8*(1-f_stroke_fatal_recur)*f_stroke_major -> 4.7556204e-06 | BZ8: =BR8*(1-f_stroke_fatal_recur)*(1-f_stroke_major) -> 9.5255219e-06 | CA8: =BS8*(1-f_bleed_fatal) -> 1.4647467e-06 | CB8: =BT8*(1-f_bleed_fatal) -> 1.3620462e-05 | CC8: =BU8*f_mi_fatal -> 4.034164e-07 | CD8: =BU8-CC8 -> 2.9306034e-06 | CE8: =BK8-BR8-BS8-BT8-CC8 -> 0.0015226187 | CF8: =BX8*c_stroke_fatal+BY8*c_stroke_major+BZ8*c_stroke_minor+BS8*c_ich+BT8*c_major_bleed+CC8*c_mi_fatal+CD8*c_mi_nonfatal+BV8*c_tia+BW8*c_minor_bleed -> 0.99456621 | CG8: =dt*(CD8*dec_mi+CB8*dec_major_bleed+BW8*dec_minor_bleed+BV8*dec_tia) -> 6.7190976e-07 | CH8: =I8*BJ8+BX8+BS8-CA8+BT8-CB8+CC8 -> 4.068581e-05 | CI8: =1-EXP(LN(1-E8)*dt) -> 0.0083541048 | CJ8: =J8*(1-CI8) -> 0.011842622 | CK8: =(1-EXP(-r_stroke*F8*rr_asa_stroke*dt)) -> 0.0066440145 | CL8: =(1-EXP(-r_ich*rr_asa_ich*dt)) -> 0.0010235777 | CM8: =(1-EXP(-r_mb*rr_asa_mb*dt)) -> 0.0095180967 | CN8: =(1-EXP(-r_mi*rr_asa_mi*dt)) -> 0.0021341352 | CO8: =(1-EXP(-r_tia*rr_asa_tia*dt)) -> 0.0031276457 | CP8: =(1-EXP(-r_minor*rr_asa_minor*dt)) -> 0.027818195 | CQ8: =CJ8*CK8 -> 7.8682555e-05 | CR8: =CJ8*CL8 -> 1.2121844e-05 | CS8: =CJ8*CM8 -> 0.00011271922 | CT8: =CJ8*CN8 -> 2.5273757e-05 | CU8: =CJ8*CO8 -> 3.7039526e-05 | CV8: =CJ8*CP8 -> 0.00032944038 | CW8: =CQ8*f_stroke_fatal -> 1.8647765e-05 | CX8: =CQ8*(1-f_stroke_fatal)*f_stroke_major -> 1.9991585e-05 | CY8: =CQ8*(1-f_stroke_fatal)*(1-f_stroke_major) -> 4.0043204e-05 | CZ8: =CR8*(1-f_bleed_fatal) -> 1.1103609e-05 | DA8: =CS8*(1-f_bleed_fatal) -> 0.00010325081 | DB8: =CT8*f_mi_fatal -> 3.0581246e-06 | DC8: =CT8-DB8 -> 2.2215632e-05 | DD8: =CJ8-CQ8-CR8-CS8-DB8 -> 0.011636041 | DE8: =CW8*c_stroke_fatal+CX8*c_stroke_major+CY8*c_stroke_minor+CR8*c_ich+CS8*c_major_bleed+DB8*c_mi_fatal+DC8*c_mi_nonfatal+CU8*c_tia+CV8*c_minor_bleed -> 4.5018408 | DF8: =dt*(DC8*dec_mi+DA8*dec_major_bleed+CV8*dec_minor_bleed+CU8*dec_tia) -> 5.0934562e-06 | DG8: =J8*CI8+CW8+CR8-CZ8+CS8-DA8+DB8 -> 0.00013196052 | DH8: =AG8 -> 0.94356998 | DI8: =AB8+AC8+BF8+BA8+BB8+BC8+CY8+CZ8 -> 0.0069043052 | DJ8: =AA8+AZ8+BY8+CX8+CE8+BZ8+CA8+CB8 -> 0.0023729633 | DK8: =AD8+DD8+DA8 -> 0.017589418 | DL8: =K8+AJ8+BI8+CH8+DG8 -> 0.029563331 | DM8: =SUM(DH8:DL8) -> 1 | DN8: =dt*(G8*Apixaban!$H$2+(H8+I8+J8)*c_aspirin) -> 71.931198 | DO8: =dt*(H8*c_lt_minor_stroke+I8*c_lt_major_stroke) -> 23.030484 | DP8: =AH8+BG8+CF8+DE8 -> 215.56616 | DQ8: =DN8+DO8+DP8 -> 310.52784 | DR8: =dt*(G8*(u_af-dec_per_year_over_70*MAX(B8-ref_age,0))+H8*(u_minor_stroke-dec_per_year_over_70*MAX(B8-ref_age,0))+I8*(u_major_stroke-dec_per_year_over_70*MAX(B8-ref_age,0))+J8*(u_af-dec_per_year_over_70*MAX(B8-ref_age,0)))-AI8-BH8-CG8-DF8 -> 0.19784424 | DS8: =dt*(G8+H8+I8+J8) -> 0.24506417 | DT8: =DQ8*C8 -> 308.22476 | DU8: =DN8*C8 -> 71.397709 | DV8: =DP8*C8 -> 213.96738 | DW8: =DO8*C8 -> 22.859674 | DX8: =DR8*C8 -> 0.19637689 | DY8: =DS8*C8 -> 0.24324661 | DZ8: =T8+AS8+BR8+CQ8 -> 0.0032657517 | EA8: =U8+AT8+BS8+CR8 -> 0.00082313408 | EB8: =V8+AU8+BT8+CS8 -> 0.0065578176 | EC8: =G8*dt*C8 -> 0.23872838
A9: 3 | B9: =start_age+A9*dt -> 70.75 | C9: =(1+disc_rate)^-(A9*dt) -> 0.98889565 | D9: =IF(A9*dt>=wane_start,(1-wane_decay)^(A9*dt-wane_start),1) -> 1 | E9: =MIN(p_nonvasc_death*MIN(EXP(gomp_int+gomp_slope*INT(B9)),1)/qx_ref,0.999) -> 0.033 | F9: =rr_stroke_per_decade^((B9-ref_age)/10) -> 1.030877 | G9: =DH8 -> 0.94356998 | H9: =DI8 -> 0.0069043052 | I9: =DJ8 -> 0.0023729633 | J9: =DK8 -> 0.017589418 | K9: =DL8 -> 0.029563331 | L9: =1-EXP(LN(1-E9)*dt) -> 0.0083541048 | M9: =G9*(1-L9) -> 0.9356873 | N9: =IF(Apixaban!$B$2=1,EXP(LN(or_apx_stroke)*D9)*(1-EXP(-r_stroke*F9*dt))/(1-(1-EXP(-r_stroke*F9*dt))+EXP(LN(or_apx_stroke)*D9)*(1-EXP(-r_stroke*F9*dt))),(1-EXP(-r_stroke*F9*dt))) -> 0.0032799545 | O9: =IF(Apixaban!$B$2=1,EXP(LN(or_apx_ich)*D9)*(1-EXP(-r_ich*dt))/(1-(1-EXP(-r_ich*dt))+EXP(LN(or_apx_ich)*D9)*(1-EXP(-r_ich*dt))),(1-EXP(-r_ich*dt))) -> 0.00084351325 | P9: =IF(Apixaban!$B$2=1,EXP(LN(or_apx_mb)*D9)*(1-EXP(-r_mb*dt))/(1-(1-EXP(-r_mb*dt))+EXP(LN(or_apx_mb)*D9)*(1-EXP(-r_mb*dt))),(1-EXP(-r_mb*dt))) -> 0.0066944691 | Q9: =IF(Apixaban!$B$2=1,EXP(LN(or_apx_mi)*D9)*(1-EXP(-r_mi*dt))/(1-(1-EXP(-r_mi*dt))+EXP(LN(or_apx_mi)*D9)*(1-EXP(-r_mi*dt))),(1-EXP(-r_mi*dt))) -> 0.0013232192 | R9: =(1-EXP(-r_tia*dt)) -> 0.0020060282 | S9: =(1-EXP(-r_minor*dt)) -> 0.043793769 | T9: =M9*N9 -> 0.0030690118 | U9: =M9*O9 -> 0.00078926463 | V9: =M9*P9 -> 0.0062639297 | W9: =M9*Q9 -> 0.0012381194 | X9: =M9*R9 -> 0.0018770151 | Y9: =M9*S9 -> 0.040977274 | Z9: =T9*f_stroke_fatal -> 0.0007273558 | AA9: =T9*(1-f_stroke_fatal)*f_stroke_major -> 0.00077977145 | AB9: =T9*(1-f_stroke_fatal)*(1-f_stroke_major) -> 0.0015618846 | AC9: =U9*(1-f_bleed_fatal) -> 0.00072296641 | AD9: =V9*(1-f_bleed_fatal) -> 0.0057377596 | AE9: =W9*f_mi_fatal -> 0.00014981244 | AF9: =W9-AE9 -> 0.0010883069 | AG9: =M9-T9-U9-V9-AE9 -> 0.92541528 | AH9: =Z9*c_stroke_fatal+AA9*c_stroke_major+AB9*c_stroke_minor+U9*c_ich+V9*c_major_bleed+AE9*c_mi_fatal+AF9*c_mi_nonfatal+X9*c_tia+Y9*c_minor_bleed -> 204.31502 | AI9: =dt*(AF9*dec_mi+AD9*dec_major_bleed+Y9*dec_minor_bleed+X9*dec_tia) -> 0.00034748734 | AJ9: =G9*L9+Z9+U9-AC9+V9-AD9+AE9 -> 0.0093523191 | AK9: =1-EXP(LN(1-E9)*hr_death_prior_stroke*dt) -> 0.019110191 | AL9: =H9*(1-AK9) -> 0.0067723626 | AM9: =(1-EXP(-r_stroke*F9*rr_stroke_prior*rr_asa_stroke*dt)) -> 0.014705819 | AN9: =(1-EXP(-r_ich*rr_asa_ich*dt)) -> 0.0010235777 | AO9: =(1-EXP(-r_mb*rr_asa_mb*dt)) -> 0.0095180967 | AP9: =(1-EXP(-r_mi*rr_asa_mi*dt)) -> 0.0021341352 | AQ9: =(1-EXP(-r_tia*rr_asa_tia*dt)) -> 0.0031276457 | AR9: =(1-EXP(-r_minor*rr_asa_minor*dt)) -> 0.027818195 | AS9: =AL9*AM9 -> 9.9593136e-05 | AT9: =AL9*AN9 -> 6.9320392e-06 | AU9: =AL9*AO9 -> 6.4460002e-05 | AV9: =AL9*AP9 -> 1.4453137e-05 | AW9: =AL9*AQ9 -> 2.118155e-05 | AX9: =AL9*AR9 -> 0.0001883949 | AY9: =AS9*f_stroke_fatal_recur -> 3.705761e-05 | AZ9: =AS9*(1-f_stroke_fatal_recur)*f_stroke_major -> 2.082433e-05 | BA9: =AS9*(1-f_stroke_fatal_recur)*(1-f_stroke_major) -> 4.1711196e-05 | BB9: =AT9*(1-f_bleed_fatal) -> 6.3497479e-06 | BC9: =AU9*(1-f_bleed_fatal) -> 5.9045362e-05 | BD9: =AV9*f_mi_fatal -> 1.7488296e-06 | BE9: =AV9-BD9 -> 1.2704308e-05 | BF9: =AL9-AS9-AT9-AU9-BD9 -> 0.0065996286 | BG9: =AY9*c_stroke_fatal+AZ9*c_stroke_major+BA9*c_stroke_minor+AT9*c_ich+AU9*c_major_bleed+BD9*c_mi_fatal+BE9*c_mi_nonfatal+AW9*c_tia+AX9*c_minor_bleed -> 4.3458718 | BH9: =dt*(BE9*dec_mi+BC9*dec_major_bleed+AX9*dec_minor_bleed+AW9*dec_tia) -> 2.9127613e-06 | BI9: =H9*AK9+AY9+AT9-BB9+AU9-BC9+BD9 -> 0.00017674596 | BJ9: =1-EXP(LN(1-E9)*hr_death_prior_stroke*dt) -> 0.019110191 | BK9: =I9*(1-BJ9) -> 0.0023276155 | BL9: =(1-EXP(-r_stroke*F9*rr_stroke_prior*rr_asa_stroke*dt)) -> 0.014705819 | BM9: =(1-EXP(-r_ich*rr_asa_ich*dt)) -> 0.0010235777 | BN9: =(1-EXP(-r_mb*rr_asa_mb*dt)) -> 0.0095180967 | BO9: =(1-EXP(-r_mi*rr_asa_mi*dt)) -> 0.0021341352 | BP9: =(1-EXP(-r_tia*rr_asa_tia*dt)) -> 0.0031276457 | BQ9: =(1-EXP(-r_minor*rr_asa_minor*dt)) -> 0.027818195 | BR9: =BK9*BL9 -> 3.4229492e-05 | BS9: =BK9*BM9 -> 2.3824953e-06 | BT9: =BK9*BN9 -> 2.215447e-05 | BU9: =BK9*BO9 -> 4.9674462e-06 | BV9: =BK9*BP9 -> 7.2799567e-06 | BW9: =BK9*BQ9 -> 6.4750063e-05 | BX9: =BR9*f_stroke_fatal_recur -> 1.2736452e-05 | BY9: =BR9*(1-f_stroke_fatal_recur)*f_stroke_major -> 7.1571824e-06 | BZ9: =BR9*(1-f_stroke_fatal_recur)*(1-f_stroke_major) -> 1.4335858e-05 | CA9: =BS9*(1-f_bleed_fatal) -> 2.1823657e-06 | CB9: =BT9*(1-f_bleed_fatal) -> 2.0293494e-05 | CC9: =BU9*f_mi_fatal -> 6.0106099e-07 | CD9: =BU9-CC9 -> 4.3663852e-06 | CE9: =BK9-BR9-BS9-BT9-CC9 -> 0.002268248 | CF9: =BX9*c_stroke_fatal+BY9*c_stroke_major+BZ9*c_stroke_minor+BS9*c_ich+BT9*c_major_bleed+CC9*c_mi_fatal+CD9*c_mi_nonfatal+BV9*c_tia+BW9*c_minor_bleed -> 1.493647 | CG9: =dt*(CD9*dec_mi+CB9*dec_major_bleed+BW9*dec_minor_bleed+BV9*dec_tia) -> 1.0010965e-06 | CH9: =I9*BJ9+BX9+BS9-CA9+BT9-CB9+CC9 -> 6.0746399e-05 | CI9: =1-EXP(LN(1-E9)*dt) -> 0.0083541048 | CJ9: =J9*(1-CI9) -> 0.017442474 | CK9: =(1-EXP(-r_stroke*F9*rr_asa_stroke*dt)) -> 0.0067114773 | CL9: =(1-EXP(-r_ich*rr_asa_ich*dt)) -> 0.0010235777 | CM9: =(1-EXP(-r_mb*rr_asa_mb*dt)) -> 0.0095180967 | CN9: =(1-EXP(-r_mi*rr_asa_mi*dt)) -> 0.0021341352 | CO9: =(1-EXP(-r_tia*rr_asa_tia*dt)) -> 0.0031276457 | CP9: =(1-EXP(-r_minor*rr_asa_minor*dt)) -> 0.027818195 | CQ9: =CJ9*CK9 -> 0.00011706477 | CR9: =CJ9*CL9 -> 1.7853728e-05 | CS9: =CJ9*CM9 -> 0.00016601916 | CT9: =CJ9*CN9 -> 3.7224598e-05 | CU9: =CJ9*CO9 -> 5.4553879e-05 | CV9: =CJ9*CP9 -> 0.00048521816 | CW9: =CQ9*f_stroke_fatal -> 2.7744351e-05 | CX9: =CQ9*(1-f_stroke_fatal)*f_stroke_major -> 2.97437e-05 | CY9: =CQ9*(1-f_stroke_fatal)*(1-f_stroke_major) -> 5.957672e-05 | CZ9: =CR9*(1-f_bleed_fatal) -> 1.6354014e-05 | DA9: =CS9*(1-f_bleed_fatal) -> 0.00015207355 | DB9: =CT9*f_mi_fatal -> 4.5041764e-06 | DC9: =CT9-DB9 -> 3.2720422e-05 | DD9: =CJ9-CQ9-CR9-CS9-DB9 -> 0.017137033 | DE9: =CW9*c_stroke_fatal+CX9*c_stroke_major+CY9*c_stroke_minor+CR9*c_ich+CS9*c_major_bleed+DB9*c_mi_fatal+DC9*c_mi_nonfatal+CU9*c_tia+CV9*c_minor_bleed -> 6.6740391 | DF9: =dt*(DC9*dec_mi+DA9*dec_major_bleed+CV9*dec_minor_bleed+CU9*dec_tia) -> 7.5019262e-06 | DG9: =J9*CI9+CW9+CR9-CZ9+CS9-DA9+DB9 -> 0.00019463769 | DH9: =AG9 -> 0.92541528 | DI9: =AB9+AC9+BF9+BA9+BB9+BC9+CY9+CZ9 -> 0.0090675166 | DJ9: =AA9+AZ9+BY9+CX9+CE9+BZ9+CA9+CB9 -> 0.0031425564 | DK9: =AD9+DD9+DA9 -> 0.023026866 | DL9: =K9+AJ9+BI9+CH9+DG9 -> 0.03934778 | DM9: =SUM(DH9:DL9) -> 1 | DN9: =dt*(G9*Apixaban!$H$2+(H9+I9+J9)*c_aspirin) -> 70.63749 | DO9: =dt*(H9*c_lt_minor_stroke+I9*c_lt_major_stroke) -> 34.156897 | DP9: =AH9+BG9+CF9+DE9 -> 216.82858 | DQ9: =DN9+DO9+DP9 -> 321.62297 | DR9: =dt*(G9*(u_af-dec_per_year_over_70*MAX(B9-ref_age,0))+H9*(u_minor_stroke-dec_per_year_over_70*MAX(B9-ref_age,0))+I9*(u_major_stroke-dec_per_year_over_70*MAX(B9-ref_age,0))+J9*(u_af-dec_per_year_over_70*MAX(B9-ref_age,0)))-AI9-BH9-CG9-DF9 -> 0.19571498 | DS9: =dt*(G9+H9+I9+J9) -> 0.24260917 | DT9: =DQ9*C9 -> 318.05155 | DU9: =DN9*C9 -> 69.853106 | DV9: =DP9*C9 -> 214.42084 | DW9: =DO9*C9 -> 33.777607 | DX9: =DR9*C9 -> 0.19354169 | DY9: =DS9*C9 -> 0.23991515 | DZ9: =T9+AS9+BR9+CQ9 -> 0.0033198992 | EA9: =U9+AT9+BS9+CR9 -> 0.0008164329 | EB9: =V9+AU9+BT9+CS9 -> 0.0065165633 | EC9: =G9*dt*C9 -> 0.23327306
A10: 4 | B10: =start_age+A10*dt -> 71 | C10: =(1+disc_rate)^-(A10*dt) -> 0.98522167 | D10: =IF(A10*dt>=wane_start,(1-wane_decay)^(A10*dt-wane_start),1) -> 1 | E10: =MIN(p_nonvasc_death*MIN(EXP(gomp_int+gomp_slope*INT(B10)),1)/qx_ref,0.999) -> 0.036640021 | F10: =rr_stroke_per_decade^((B10-ref_age)/10) -> 1.0413797 | G10: =DH9 -> 0.92541528 | H10: =DI9 -> 0.0090675166 | I10: =DJ9 -> 0.0031425564 | J10: =DK9 -> 0.023026866 | K10: =DL9 -> 0.03934778 | L10: =1-EXP(LN(1-E10)*dt) -> 0.0092886235 | M10: =G10*(1-L10) -> 0.91681945 | N10: =IF(Apixaban!$B$2=1,EXP(LN(or_apx_stroke)*D10)*(1-EXP(-r_stroke*F10*dt))/(1-(1-EXP(-r_stroke*F10*dt))+EXP(LN(or_apx_stroke)*D10)*(1-EXP(-r_stroke*F10*dt))),(1-EXP(-r_stroke*F10*dt))) -> 0.0033133306 | O10: =IF(Apixaban!$B$2=1,EXP(LN(or_apx_ich)*D10)*(1-EXP(-r_ich*dt))/(1-(1-EXP(-r_ich*dt))+EXP(LN(or_apx_ich)*D10)*(1-EXP(-r_ich*dt))),(1-EXP(-r_ich*dt))) -> 0.00084351325 | P10: =IF(Apixaban!$B$2=1,EXP(LN(or_apx_mb)*D10)*(1-EXP(-r_mb*dt))/(1-(1-EXP(-r_mb*dt))+EXP(LN(or_apx_mb)*D10)*(1-EXP(-r_mb*dt))),(1-EXP(-r_mb*dt))) -> 0.0066944691 | Q10: =IF(Apixaban!$B$2=1,EXP(LN(or_apx_mi)*D10)*(1-EXP(-r_mi*dt))/(1-(1-EXP(-r_mi*dt))+EXP(LN(or_apx_mi)*D10)*(1-EXP(-r_mi*dt))),(1-EXP(-r_mi*dt))) -> 0.0013232192 | R10: =(1-EXP(-r_tia*dt)) -> 0.0020060282 | S10: =(1-EXP(-r_minor*dt)) -> 0.043793769 | T10: =M10*N10 -> 0.0030377259 | U10: =M10*O10 -> 0.00077334935 | V10: =M10*P10 -> 0.0061376194 | W10: =M10*Q10 -> 0.0012131531 | X10: =M10*R10 -> 0.0018391656 | Y10: =M10*S10 -> 0.040150979 | Z10: =T10*f_stroke_fatal -> 0.00071994104 | AA10: =T10*(1-f_stroke_fatal)*f_stroke_major -> 0.00077182236 | AB10: =T10*(1-f_stroke_fatal)*(1-f_stroke_major) -> 0.0015459625 | AC10: =U10*(1-f_bleed_fatal) -> 0.00070838801 | AD10: =V10*(1-f_bleed_fatal) -> 0.0056220594 | AE10: =W10*f_mi_fatal -> 0.00014679152 | AF10: =W10-AE10 -> 0.0010663615 | AG10: =M10-T10-U10-V10-AE10 -> 0.90672396 | AH10: =Z10*c_stroke_fatal+AA10*c_stroke_major+AB10*c_stroke_minor+U10*c_ich+V10*c_major_bleed+AE10*c_mi_fatal+AF10*c_mi_nonfatal+X10*c_tia+Y10*c_minor_bleed -> 201.32566 | AI10: =dt*(AF10*dec_mi+AD10*dec_major_bleed+Y10*dec_minor_bleed+X10*dec_tia) -> 0.00034048036 | AJ10: =G10*L10+Z10+U10-AC10+V10-AD10+AE10 -> 0.010043088 | AK10: =1-EXP(LN(1-E10)*hr_death_prior_stroke*dt) -> 0.021234968 | AL10: =H10*(1-AK10) -> 0.0088749682 | AM10: =(1-EXP(-r_stroke*F10*rr_stroke_prior*rr_asa_stroke*dt)) -> 0.014854526 | AN10: =(1-EXP(-r_ich*rr_asa_ich*dt)) -> 0.0010235777 | AO10: =(1-EXP(-r_mb*rr_asa_mb*dt)) -> 0.0095180967 | AP10: =(1-EXP(-r_mi*rr_asa_mi*dt)) -> 0.0021341352 | AQ10: =(1-EXP(-r_tia*rr_asa_tia*dt)) -> 0.0031276457 | AR10: =(1-EXP(-r_minor*rr_asa_minor*dt)) -> 0.027818195 | AS10: =AL10*AM10 -> 0.00013183344 | AT10: =AL10*AN10 -> 9.0842193e-06 | AU10: =AL10*AO10 -> 8.4472805e-05 | AV10: =AL10*AP10 -> 1.8940382e-05 | AW10: =AL10*AQ10 -> 2.7757756e-05 | AX10: =AL10*AR10 -> 0.0002468856 | AY10: =AS10*f_stroke_fatal_recur -> 4.9053906e-05 | AZ10: =AS10*(1-f_stroke_fatal_recur)*f_stroke_major -> 2.7565586e-05 | BA10: =AS10*(1-f_stroke_fatal_recur)*(1-f_stroke_major) -> 5.5213951e-05 | BB10: =AT10*(1-f_bleed_fatal) -> 8.3211449e-06 | BC10: =AU10*(1-f_bleed_fatal) -> 7.737709e-05 | BD10: =AV10*f_mi_fatal -> 2.2917862e-06 | BE10: =AV10-BD10 -> 1.6648595e-05 | BF10: =AL10-AS10-AT10-AU10-BD10 -> 0.0086472859 | BG10: =AY10*c_stroke_fatal+AZ10*c_stroke_major+BA10*c_stroke_minor+AT10*c_ich+AU10*c_major_bleed+BD10*c_mi_fatal+BE10*c_mi_nonfatal+AW10*c_tia+AX10*c_minor_bleed -> 5.7406333 | BH10: =dt*(BE10*dec_mi+BC10*dec_major_bleed+AX10*dec_minor_bleed+AW10*dec_tia) -> 3.8170821e-06 | BI10: =H10*AK10+AY10+AT10-BB10+AU10-BC10+BD10 -> 0.0002517529 | BJ10: =1-EXP(LN(1-E10)*hr_death_prior_stroke*dt) -> 0.021234968 | BK10: =I10*(1-BJ10) -> 0.0030758243 | BL10: =(1-EXP(-r_stroke*F10*rr_stroke_prior*rr_asa_stroke*dt)) -> 0.014854526 | BM10: =(1-EXP(-r_ich*rr_asa_ich*dt)) -> 0.0010235777 | BN10: =(1-EXP(-r_mb*rr_asa_mb*dt)) -> 0.0095180967 | BO10: =(1-EXP(-r_mi*rr_asa_mi*dt)) -> 0.0021341352 | BP10: =(1-EXP(-r_tia*rr_asa_tia*dt)) -> 0.0031276457 | BQ10: =(1-EXP(-r_minor*rr_asa_minor*dt)) -> 0.027818195 | BR10: =BK10*BL10 -> 4.5689912e-05 | BS10: =BK10*BM10 -> 3.1483451e-06 | BT10: =BK10*BN10 -> 2.9275993e-05 | BU10: =BK10*BO10 -> 6.5642249e-06 | BV10: =BK10*BP10 -> 9.6200886e-06 | BW10: =BK10*BQ10 -> 8.5563881e-05 | BX10: =BR10*f_stroke_fatal_recur -> 1.7000759e-05 | BY10: =BR10*(1-f_stroke_fatal_recur)*f_stroke_major -> 9.5534878e-06 | BZ10: =BR10*(1-f_stroke_fatal_recur)*(1-f_stroke_major) -> 1.9135665e-05 | CA10: =BS10*(1-f_bleed_fatal) -> 2.8838841e-06 | CB10: =BT10*(1-f_bleed_fatal) -> 2.681681e-05 | CC10: =BU10*f_mi_fatal -> 7.9427121e-07 | CD10: =BU10-CC10 -> 5.7699536e-06 | CE10: =BK10-BR10-BS10-BT10-CC10 -> 0.0029969158 | CF10: =BX10*c_stroke_fatal+BY10*c_stroke_major+BZ10*c_stroke_minor+BS10*c_ich+BT10*c_major_bleed+CC10*c_mi_fatal+CD10*c_mi_nonfatal+BV10*c_tia+BW10*c_minor_bleed -> 1.9895485 | CG10: =dt*(CD10*dec_mi+CB10*dec_major_bleed+BW10*dec_minor_bleed+BV10*dec_tia) -> 1.3228976e-06 | CH10: =I10*BJ10+BX10+BS10-CA10+BT10-CB10+CC10 -> 8.7250758e-05 | CI10: =1-EXP(LN(1-E10)*dt) -> 0.0092886235 | CJ10: =J10*(1-CI10) -> 0.022812978 | CK10: =(1-EXP(-r_stroke*F10*rr_asa_stroke*dt)) -> 0.0067796227 | CL10: =(1-EXP(-r_ich*rr_asa_ich*dt)) -> 0.0010235777 | CM10: =(1-EXP(-r_mb*rr_asa_mb*dt)) -> 0.0095180967 | CN10: =(1-EXP(-r_mi*rr_asa_mi*dt)) -> 0.0021341352 | CO10: =(1-EXP(-r_tia*rr_asa_tia*dt)) -> 0.0031276457 | CP10: =(1-EXP(-r_minor*rr_asa_minor*dt)) -> 0.027818195 | CQ10: =CJ10*CK10 -> 0.00015466338 | CR10: =CJ10*CL10 -> 2.3350855e-05 | CS10: =CJ10*CM10 -> 0.00021713613 | CT10: =CJ10*CN10 -> 4.8685978e-05 | CU10: =CJ10*CO10 -> 7.1350911e-05 | CV10: =CJ10*CP10 -> 0.00063461587 | CW10: =CQ10*f_stroke_fatal -> 3.6655222e-05 | CX10: =CQ10*(1-f_stroke_fatal)*f_stroke_major -> 3.9296717e-05 | CY10: =CQ10*(1-f_stroke_fatal)*(1-f_stroke_major) -> 7.8711443e-05 | CZ10: =CR10*(1-f_bleed_fatal) -> 2.1389383e-05 | DA10: =CS10*(1-f_bleed_fatal) -> 0.0001988967 | DB10: =CT10*f_mi_fatal -> 5.8910034e-06 | DC10: =CT10-DB10 -> 4.2794975e-05 | DD10: =CJ10-CQ10-CR10-CS10-DB10 -> 0.022411937 | DE10: =CW10*c_stroke_fatal+CX10*c_stroke_major+CY10*c_stroke_minor+CR10*c_ich+CS10*c_major_bleed+DB10*c_mi_fatal+DC10*c_mi_nonfatal+CU10*c_tia+CV10*c_minor_bleed -> 8.7864014 | DF10: =dt*(DC10*dec_mi+DA10*dec_major_bleed+CV10*dec_minor_bleed+CU10*dec_tia) -> 9.8117545e-06 | DG10: =J10*CI10+CW10+CR10-CZ10+CS10-DA10+DB10 -> 0.00027663502 | DH10: =AG10 -> 0.90672396 | DI10: =AB10+AC10+BF10+BA10+BB10+BC10+CY10+CZ10 -> 0.011142649 | DJ10: =AA10+AZ10+BY10+CX10+CE10+BZ10+CA10+CB10 -> 0.0038939903 | DK10: =AD10+DD10+DA10 -> 0.028232893 | DL10: =K10+AJ10+BI10+CH10+DG10 -> 0.050006507 | DM10: =SUM(DH10:DL10) -> 1 | DN10: =dt*(G10*Apixaban!$H$2+(H10+I10+J10)*c_aspirin) -> 69.365132 | DO10: =dt*(H10*c_lt_minor_stroke+I10*c_lt_major_stroke) -> 45.029186 | DP10: =AH10+BG10+CF10+DE10 -> 217.84224 | DQ10: =DN10+DO10+DP10 -> 332.23656 | DR10: =dt*(G10*(u_af-dec_per_year_over_70*MAX(B10-ref_age,0))+H10*(u_minor_stroke-dec_per_year_over_70*MAX(B10-ref_age,0))+I10*(u_major_stroke-dec_per_year_over_70*MAX(B10-ref_age,0))+J10*(u_af-dec_per_year_over_70*MAX(B10-ref_age,0)))-AI10-BH10-CG10-DF10 -> 0.19359592 | DS10: =dt*(G10+H10+I10+J10) -> 0.24016305 | DT10: =DQ10*C10 -> 327.32666 | DU10: =DN10*C10 -> 68.340032 | DV10: =DP10*C10 -> 214.6229 | DW10: =DO10*C10 -> 44.36373 | DX10: =DR10*C10 -> 0.19073489 | DY10: =DS10*C10 -> 0.23661385 | DZ10: =T10+AS10+BR10+CQ10 -> 0.0033699126 | EA10: =U10+AT10+BS10+CR10 -> 0.00080893277 | EB10: =V10+AU10+BT10+CS10 -> 0.0064685044 | EC10: =G10*dt*C10 -> 0.2279348
A11: 5 | B11: =start_age+A11*dt -> 71.25 | C11: =(1+disc_rate)^-(A11*dt) -> 0.98156135 | D11: =IF(A11*dt>=wane_start,(1-wane_decay)^(A11*dt-wane_start),1) -> 1 | E11: =MIN(p_nonvasc_death*MIN(EXP(gomp_int+gomp_slope*INT(B11)),1)/qx_ref,0.999) -> 0.036640021 | F11: =rr_stroke_per_decade^((B11-ref_age)/10) -> 1.0519895 | G11: =DH10 -> 0.90672396 | H11: =DI10 -> 0.011142649 | I11: =DJ10 -> 0.0038939903 | J11: =DK10 -> 0.028232893 | K11: =DL10 -> 0.050006507 | L11: =1-EXP(LN(1-E11)*dt) -> 0.0092886235 | M11: =G11*(1-L11) -> 0.89830174 | N11: =IF(Apixaban!$B$2=1,EXP(LN(or_apx_stroke)*D11)*(1-EXP(-r_stroke*F11*dt))/(1-(1-EXP(-r_stroke*F11*dt))+EXP(LN(or_apx_stroke)*D11)*(1-EXP(-r_stroke*F11*dt))),(1-EXP(-r_stroke*F11*dt))) -> 0.0033470458 | O11: =IF(Apixaban!$B$2=1,EXP(LN(or_apx_ich)*D11)*(1-EXP(-r_ich*dt))/(1-(1-EXP(-r_ich*dt))+EXP(LN(or_apx_ich)*D11)*(1-EXP(-r_ich*dt))),(1-EXP(-r_ich*dt))) -> 0.00084351325 | P11: =IF(Apixaban!$B$2=1,EXP(LN(or_apx_mb)*D11)*(1-EXP(-r_mb*dt))/(1-(1-EXP(-r_mb*dt))+EXP(LN(or_apx_mb)*D11)*(1-EXP(-r_mb*dt))),(1-EXP(-r_mb*dt))) -> 0.0066944691 | Q11: =IF(Apixaban!$B$2=1,EXP(LN(or_apx_mi)*D11)*(1-EXP(-r_mi*dt))/(1-(1-EXP(-r_mi*dt))+EXP(LN(or_apx_mi)*D11)*(1-EXP(-r_mi*dt))),(1-EXP(-r_mi*dt))) -> 0.0013232192 | R11: =(1-EXP(-r_tia*dt)) -> 0.0020060282 | S11: =(1-EXP(-r_minor*dt)) -> 0.043793769 | T11: =M11*N11 -> 0.0030066571 | U11: =M11*O11 -> 0.00075772942 | V11: =M11*P11 -> 0.0060136532 | W11: =M11*Q11 -> 0.0011886501 | X11: =M11*R11 -> 0.0018020186 | Y11: =M11*S11 -> 0.039340019 | Z11: =T11*f_stroke_fatal -> 0.00071257772 | AA11: =T11*(1-f_stroke_fatal)*f_stroke_major -> 0.00076392842 | AB11: =T11*(1-f_stroke_fatal)*(1-f_stroke_major) -> 0.0015301509 | AC11: =U11*(1-f_bleed_fatal) -> 0.00069408015 | AD11: =V11*(1-f_bleed_fatal) -> 0.0055085064 | AE11: =W11*f_mi_fatal -> 0.00014382666 | AF11: =W11-AE11 -> 0.0010448234 | AG11: =M11-T11-U11-V11-AE11 -> 0.88837988 | AH11: =Z11*c_stroke_fatal+AA11*c_stroke_major+AB11*c_stroke_minor+U11*c_ich+V11*c_major_bleed+AE11*c_mi_fatal+AF11*c_mi_nonfatal+X11*c_tia+Y11*c_minor_bleed -> 198.37834 | AI11: =dt*(AF11*dec_mi+AD11*dec_major_bleed+Y11*dec_minor_bleed+X11*dec_tia) -> 0.00033360342 | AJ11: =G11*L11+Z11+U11-AC11+V11-AD11+AE11 -> 0.009847418 | AK11: =1-EXP(LN(1-E11)*hr_death_prior_stroke*dt) -> 0.021234968 | AL11: =H11*(1-AK11) -> 0.010906036 | AM11: =(1-EXP(-r_stroke*F11*rr_stroke_prior*rr_asa_stroke*dt)) -> 0.015004725 | AN11: =(1-EXP(-r_ich*rr_asa_ich*dt)) -> 0.0010235777 | AO11: =(1-EXP(-r_mb*rr_asa_mb*dt)) -> 0.0095180967 | AP11: =(1-EXP(-r_mi*rr_asa_mi*dt)) -> 0.0021341352 | AQ11: =(1-EXP(-r_tia*rr_asa_tia*dt)) -> 0.0031276457 | AR11: =(1-EXP(-r_minor*rr_asa_minor*dt)) -> 0.027818195 | AS11: =AL11*AM11 -> 0.00016364207 | AT11: =AL11*AN11 -> 1.1163175e-05 | AU11: =AL11*AO11 -> 0.0001038047 | AV11: =AL11*AP11 -> 2.3274954e-05 | AW11: =AL11*AQ11 -> 3.4110215e-05 | AX11: =AL11*AR11 -> 0.00030338623 | AY11: =AS11*f_stroke_fatal_recur -> 6.0889577e-05 | AZ11: =AS11*(1-f_stroke_fatal_recur)*f_stroke_major -> 3.4216579e-05 | BA11: =AS11*(1-f_stroke_fatal_recur)*(1-f_stroke_major) -> 6.8535911e-05 | BB11: =AT11*(1-f_bleed_fatal) -> 1.0225468e-05 | BC11: =AU11*(1-f_bleed_fatal) -> 9.5085107e-05 | BD11: =AV11*f_mi_fatal -> 2.8162694e-06 | BE11: =AV11-BD11 -> 2.0458685e-05 | BF11: =AL11-AS11-AT11-AU11-BD11 -> 0.010624609 | BG11: =AY11*c_stroke_fatal+AZ11*c_stroke_major+BA11*c_stroke_minor+AT11*c_ich+AU11*c_major_bleed+BD11*c_mi_fatal+BE11*c_mi_nonfatal+AW11*c_tia+AX11*c_minor_bleed -> 7.1108774 | BH11: =dt*(BE11*dec_mi+BC11*dec_major_bleed+AX11*dec_minor_bleed+AW11*dec_tia) -> 4.6906346e-06 | BI11: =H11*AK11+AY11+AT11-BB11+AU11-BC11+BD11 -> 0.00030997695 | BJ11: =1-EXP(LN(1-E11)*hr_death_prior_stroke*dt) -> 0.021234968 | BK11: =I11*(1-BJ11) -> 0.0038113016 | BL11: =(1-EXP(-r_stroke*F11*rr_stroke_prior*rr_asa_stroke*dt)) -> 0.015004725 | BM11: =(1-EXP(-r_ich*rr_asa_ich*dt)) -> 0.0010235777 | BN11: =(1-EXP(-r_mb*rr_asa_mb*dt)) -> 0.0095180967 | BO11: =(1-EXP(-r_mi*rr_asa_mi*dt)) -> 0.0021341352 | BP11: =(1-EXP(-r_tia*rr_asa_tia*dt)) -> 0.0031276457 | BQ11: =(1-EXP(-r_minor*rr_asa_minor*dt)) -> 0.027818195 | BR11: =BK11*BL11 -> 5.7187533e-05 | BS11: =BK11*BM11 -> 3.9011632e-06 | BT11: =BK11*BN11 -> 3.6276337e-05 | BU11: =BK11*BO11 -> 8.1338327e-06 | BV11: =BK11*BP11 -> 1.1920401e-05 | BW11: =BK11*BQ11 -> 0.00010602353 | BX11: =BR11*f_stroke_fatal_recur -> 2.1278909e-05 | BY11: =BR11*(1-f_stroke_fatal_recur)*f_stroke_major -> 1.1957572e-05 | BZ11: =BR11*(1-f_stroke_fatal_recur)*(1-f_stroke_major) -> 2.3951052e-05 | CA11: =BS11*(1-f_bleed_fatal) -> 3.5734655e-06 | CB11: =BT11*(1-f_bleed_fatal) -> 3.3229125e-05 | CC11: =BU11*f_mi_fatal -> 9.8419375e-07 | CD11: =BU11-CC11 -> 7.1496389e-06 | CE11: =BK11-BR11-BS11-BT11-CC11 -> 0.0037129523 | CF11: =BX11*c_stroke_fatal+BY11*c_stroke_major+BZ11*c_stroke_minor+BS11*c_ich+BT11*c_major_bleed+CC11*c_mi_fatal+CD11*c_mi_nonfatal+BV11*c_tia+BW11*c_minor_bleed -> 2.4850183 | CG11: =dt*(CD11*dec_mi+CB11*dec_major_bleed+BW11*dec_minor_bleed+BV11*dec_tia) -> 1.6392229e-06 | CH11: =I11*BJ11+BX11+BS11-CA11+BT11-CB11+CC11 -> 0.00010832677 | CI11: =1-EXP(LN(1-E11)*dt) -> 0.0092886235 | CJ11: =J11*(1-CI11) -> 0.027970648 | CK11: =(1-EXP(-r_stroke*F11*rr_asa_stroke*dt)) -> 0.0068484576 | CL11: =(1-EXP(-r_ich*rr_asa_ich*dt)) -> 0.0010235777 | CM11: =(1-EXP(-r_mb*rr_asa_mb*dt)) -> 0.0095180967 | CN11: =(1-EXP(-r_mi*rr_asa_mi*dt)) -> 0.0021341352 | CO11: =(1-EXP(-r_tia*rr_asa_tia*dt)) -> 0.0031276457 | CP11: =(1-EXP(-r_minor*rr_asa_minor*dt)) -> 0.027818195 | CQ11: =CJ11*CK11 -> 0.0001915558 | CR11: =CJ11*CL11 -> 2.8630131e-05 | CS11: =CJ11*CM11 -> 0.00026622733 | CT11: =CJ11*CN11 -> 5.9693143e-05 | CU11: =CJ11*CO11 -> 8.7482275e-05 | CV11: =CJ11*CP11 -> 0.00077809294 | CW11: =CQ11*f_stroke_fatal -> 4.5398724e-05 | CX11: =CQ11*(1-f_stroke_fatal)*f_stroke_major -> 4.8670305e-05 | CY11: =CQ11*(1-f_stroke_fatal)*(1-f_stroke_major) -> 9.7486767e-05 | CZ11: =CR11*(1-f_bleed_fatal) -> 2.62252e-05 | DA11: =CS11*(1-f_bleed_fatal) -> 0.00024386424 | DB11: =CT11*f_mi_fatal -> 7.2228703e-06 | DC11: =CT11-DB11 -> 5.2470273e-05 | DD11: =CJ11-CQ11-CR11-CS11-DB11 -> 0.027477012 | DE11: =CW11*c_stroke_fatal+CX11*c_stroke_major+CY11*c_stroke_minor+CR11*c_ich+CS11*c_major_bleed+DB11*c_mi_fatal+DC11*c_mi_nonfatal+CU11*c_tia+CV11*c_minor_bleed -> 10.844012 | DF11: =dt*(DC11*dec_mi+DA11*dec_major_bleed+CV11*dec_minor_bleed+CU11*dec_tia) -> 1.2030044e-05 | DG11: =J11*CI11+CW11+CR11-CZ11+CS11-DA11+DB11 -> 0.00033963433 | DH11: =AG11 -> 0.88837988 | DI11: =AB11+AC11+BF11+BA11+BB11+BC11+CY11+CZ11 -> 0.013146399 | DJ11: =AA11+AZ11+BY11+CX11+CE11+BZ11+CA11+CB11 -> 0.0046324788 | DK11: =AD11+DD11+DA11 -> 0.033229382 | DL11: =K11+AJ11+BI11+CH11+DG11 -> 0.060611863 | DM11: =SUM(DH11:DL11) -> 1 | DN11: =dt*(G11*Apixaban!$H$2+(H11+I11+J11)*c_aspirin) -> 68.049456 | DO11: =dt*(H11*c_lt_minor_stroke+I11*c_lt_major_stroke) -> 55.544814 | DP11: =AH11+BG11+CF11+DE11 -> 218.81825 | DQ11: =DN11+DO11+DP11 -> 342.41252 | DR11: =dt*(G11*(u_af-dec_per_year_over_70*MAX(B11-ref_age,0))+H11*(u_minor_stroke-dec_per_year_over_70*MAX(B11-ref_age,0))+I11*(u_major_stroke-dec_per_year_over_70*MAX(B11-ref_age,0))+J11*(u_af-dec_per_year_over_70*MAX(B11-ref_age,0)))-AI11-BH11-CG11-DF11 -> 0.19130374 | DS11: =dt*(G11+H11+I11+J11) -> 0.23749837 | DT11: =DQ11*C11 -> 336.09889 | DU11: =DN11*C11 -> 66.794715 | DV11: =DP11*C11 -> 214.78354 | DW11: =DO11*C11 -> 54.520642 | DX11: =DR11*C11 -> 0.18777635 | DY11: =DS11*C11 -> 0.23311922 | DZ11: =T11+AS11+BR11+CQ11 -> 0.0034190425 | EA11: =U11+AT11+BS11+CR11 -> 0.00080142389 | EB11: =V11+AU11+BT11+CS11 -> 0.0064199616 | EC11: =G11*dt*C11 -> 0.2225013
A12: 6 | B12: =start_age+A12*dt -> 71.5 | C12: =(1+disc_rate)^-(A12*dt) -> 0.97791461 | D12: =IF(A12*dt>=wane_start,(1-wane_decay)^(A12*dt-wane_start),1) -> 1 | E12: =MIN(p_nonvasc_death*MIN(EXP(gomp_int+gomp_slope*INT(B12)),1)/qx_ref,0.999) -> 0.036640021 | F12: =rr_stroke_per_decade^((B12-ref_age)/10) -> 1.0627074 | G12: =DH11 -> 0.88837988 | H12: =DI11 -> 0.013146399 | I12: =DJ11 -> 0.0046324788 | J12: =DK11 -> 0.033229382 | K12: =DL11 -> 0.060611863 | L12: =1-EXP(LN(1-E12)*dt) -> 0.0092886235 | M12: =G12*(1-L12) -> 0.88012805 | N12: =IF(Apixaban!$B$2=1,EXP(LN(or_apx_stroke)*D12)*(1-EXP(-r_stroke*F12*dt))/(1-(1-EXP(-r_stroke*F12*dt))+EXP(LN(or_apx_stroke)*D12)*(1-EXP(-r_stroke*F12*dt))),(1-EXP(-r_stroke*F12*dt))) -> 0.0033811036 | O12: =IF(Apixaban!$B$2=1,EXP(LN(or_apx_ich)*D12)*(1-EXP(-r_ich*dt))/(1-(1-EXP(-r_ich*dt))+EXP(LN(or_apx_ich)*D12)*(1-EXP(-r_ich*dt))),(1-EXP(-r_ich*dt))) -> 0.00084351325 | P12: =IF(Apixaban!$B$2=1,EXP(LN(or_apx_mb)*D12)*(1-EXP(-r_mb*dt))/(1-(1-EXP(-r_mb*dt))+EXP(LN(or_apx_mb)*D12)*(1-EXP(-r_mb*dt))),(1-EXP(-r_mb*dt))) -> 0.0066944691 | Q12: =IF(Apixaban!$B$2=1,EXP(LN(or_apx_mi)*D12)*(1-EXP(-r_mi*dt))/(1-(1-EXP(-r_mi*dt))+EXP(LN(or_apx_mi)*D12)*(1-EXP(-r_mi*dt))),(1-EXP(-r_mi*dt))) -> 0.0013232192 | R12: =(1-EXP(-r_tia*dt)) -> 0.0020060282 | S12: =(1-EXP(-r_minor*dt)) -> 0.043793769 | T12: =M12*N12 -> 0.0029758042 | U12: =M12*O12 -> 0.00074239967 | V12: =M12*P12 -> 0.00589199 | W12: =M12*Q12 -> 0.0011646023 | X12: =M12*R12 -> 0.0017655616 | Y12: =M12*S12 -> 0.038544125 | Z12: =T12*f_stroke_fatal -> 0.00070526559 | AA12: =T12*(1-f_stroke_fatal)*f_stroke_major -> 0.00075608935 | AB12: =T12*(1-f_stroke_fatal)*(1-f_stroke_major) -> 0.0015144492 | AC12: =U12*(1-f_bleed_fatal) -> 0.0006800381 | AD12: =V12*(1-f_bleed_fatal) -> 0.0053970629 | AE12: =W12*f_mi_fatal -> 0.00014091688 | AF12: =W12-AE12 -> 0.0010236854 | AG12: =M12-T12-U12-V12-AE12 -> 0.87037694 | AH12: =Z12*c_stroke_fatal+AA12*c_stroke_major+AB12*c_stroke_minor+U12*c_ich+V12*c_major_bleed+AE12*c_mi_fatal+AF12*c_mi_nonfatal+X12*c_tia+Y12*c_minor_bleed -> 195.47243 | AI12: =dt*(AF12*dec_mi+AD12*dec_major_bleed+Y12*dec_minor_bleed+X12*dec_tia) -> 0.00032685423 | AJ12: =G12*L12+Z12+U12-AC12+V12-AD12+AE12 -> 0.0096552974 | AK12: =1-EXP(LN(1-E12)*hr_death_prior_stroke*dt) -> 0.021234968 | AL12: =H12*(1-AK12) -> 0.012867236 | AM12: =(1-EXP(-r_stroke*F12*rr_stroke_prior*rr_asa_stroke*dt)) -> 0.015156432 | AN12: =(1-EXP(-r_ich*rr_asa_ich*dt)) -> 0.0010235777 | AO12: =(1-EXP(-r_mb*rr_asa_mb*dt)) -> 0.0095180967 | AP12: =(1-EXP(-r_mi*rr_asa_mi*dt)) -> 0.0021341352 | AQ12: =(1-EXP(-r_tia*rr_asa_tia*dt)) -> 0.0031276457 | AR12: =(1-EXP(-r_minor*rr_asa_minor*dt)) -> 0.027818195 | AS12: =AL12*AM12 -> 0.00019502138 | AT12: =AL12*AN12 -> 1.3170615e-05 | AU12: =AL12*AO12 -> 0.00012247159 | AV12: =AL12*AP12 -> 2.746042e-05 | AW12: =AL12*AQ12 -> 4.0244153e-05 | AX12: =AL12*AR12 -> 0.00035794327 | AY12: =AS12*f_stroke_fatal_recur -> 7.2565504e-05 | AZ12: =AS12*(1-f_stroke_fatal_recur)*f_stroke_major -> 4.0777806e-05 | BA12: =AS12*(1-f_stroke_fatal_recur)*(1-f_stroke_major) -> 8.1678067e-05 | BB12: =AT12*(1-f_bleed_fatal) -> 1.2064283e-05 | BC12: =AU12*(1-f_bleed_fatal) -> 0.00011218398 | BD12: =AV12*f_mi_fatal -> 3.3227108e-06 | BE12: =AV12-BD12 -> 2.4137709e-05 | BF12: =AL12-AS12-AT12-AU12-BD12 -> 0.012533249 | BG12: =AY12*c_stroke_fatal+AZ12*c_stroke_major+BA12*c_stroke_minor+AT12*c_ich+AU12*c_major_bleed+BD12*c_mi_fatal+BE12*c_mi_nonfatal+AW12*c_tia+AX12*c_minor_bleed -> 8.4569107 | BH12: =dt*(BE12*dec_mi+BC12*dec_major_bleed+AX12*dec_minor_bleed+AW12*dec_tia) -> 5.5341375e-06 | BI12: =H12*AK12+AY12+AT12-BB12+AU12-BC12+BD12 -> 0.00036644552 | BJ12: =1-EXP(LN(1-E12)*hr_death_prior_stroke*dt) -> 0.021234968 | BK12: =I12*(1-BJ12) -> 0.0045341083 | BL12: =(1-EXP(-r_stroke*F12*rr_stroke_prior*rr_asa_stroke*dt)) -> 0.015156432 | BM12: =(1-EXP(-r_ich*rr_asa_ich*dt)) -> 0.0010235777 | BN12: =(1-EXP(-r_mb*rr_asa_mb*dt)) -> 0.0095180967 | BO12: =(1-EXP(-r_mi*rr_asa_mi*dt)) -> 0.0021341352 | BP12: =(1-EXP(-r_tia*rr_asa_tia*dt)) -> 0.0031276457 | BQ12: =(1-EXP(-r_minor*rr_asa_minor*dt)) -> 0.027818195 | BR12: =BK12*BL12 -> 6.8720903e-05 | BS12: =BK12*BM12 -> 4.6410121e-06 | BT12: =BK12*BN12 -> 4.3156081e-05 | BU12: =BK12*BO12 -> 9.6764e-06 | BV12: =BK12*BP12 -> 1.4181084e-05 | BW12: =BK12*BQ12 -> 0.00012613071 | BX12: =BR12*f_stroke_fatal_recur -> 2.5570361e-05 | BY12: =BR12*(1-f_stroke_fatal_recur)*f_stroke_major -> 1.436913e-05 | BZ12: =BR12*(1-f_stroke_fatal_recur)*(1-f_stroke_major) -> 2.8781412e-05 | CA12: =BS12*(1-f_bleed_fatal) -> 4.251167e-06 | CB12: =BT12*(1-f_bleed_fatal) -> 3.9530971e-05 | CC12: =BU12*f_mi_fatal -> 1.1708444e-06 | CD12: =BU12-CC12 -> 8.5055556e-06 | CE12: =BK12-BR12-BS12-BT12-CC12 -> 0.0044164195 | CF12: =BX12*c_stroke_fatal+BY12*c_stroke_major+BZ12*c_stroke_minor+BS12*c_ich+BT12*c_major_bleed+CC12*c_mi_fatal+CD12*c_mi_nonfatal+BV12*c_tia+BW12*c_minor_bleed -> 2.9800145 | CG12: =dt*(CD12*dec_mi+CB12*dec_major_bleed+BW12*dec_minor_bleed+BV12*dec_tia) -> 1.9500987e-06 | CH12: =I12*BJ12+BX12+BS12-CA12+BT12-CB12+CC12 -> 0.0001291267 | CI12: =1-EXP(LN(1-E12)*dt) -> 0.0092886235 | CJ12: =J12*(1-CI12) -> 0.032920727 | CK12: =(1-EXP(-r_stroke*F12*rr_asa_stroke*dt)) -> 0.006917989 | CL12: =(1-EXP(-r_ich*rr_asa_ich*dt)) -> 0.0010235777 | CM12: =(1-EXP(-r_mb*rr_asa_mb*dt)) -> 0.0095180967 | CN12: =(1-EXP(-r_mi*rr_asa_mi*dt)) -> 0.0021341352 | CO12: =(1-EXP(-r_tia*rr_asa_tia*dt)) -> 0.0031276457 | CP12: =(1-EXP(-r_minor*rr_asa_minor*dt)) -> 0.027818195 | CQ12: =CJ12*CK12 -> 0.00022774523 | CR12: =CJ12*CL12 -> 3.3696921e-05 | CS12: =CJ12*CM12 -> 0.00031334267 | CT12: =CJ12*CN12 -> 7.0257281e-05 | CU12: =CJ12*CO12 -> 0.00010296437 | CV12: =CJ12*CP12 -> 0.00091579521 | CW12: =CQ12*f_stroke_fatal -> 5.3975619e-05 | CX12: =CQ12*(1-f_stroke_fatal)*f_stroke_major -> 5.786528e-05 | CY12: =CQ12*(1-f_stroke_fatal)*(1-f_stroke_major) -> 0.00011590433 | CZ12: =CR12*(1-f_bleed_fatal) -> 3.086638e-05 | DA12: =CS12*(1-f_bleed_fatal) -> 0.00028702188 | DB12: =CT12*f_mi_fatal -> 8.5011311e-06 | DC12: =CT12-DB12 -> 6.175615e-05 | DD12: =CJ12-CQ12-CR12-CS12-DB12 -> 0.032337441 | DE12: =CW12*c_stroke_fatal+CX12*c_stroke_major+CY12*c_stroke_minor+CR12*c_ich+CS12*c_major_bleed+DB12*c_mi_fatal+DC12*c_mi_nonfatal+CU12*c_tia+CV12*c_minor_bleed -> 12.847694 | DF12: =dt*(DC12*dec_mi+DA12*dec_major_bleed+CV12*dec_minor_bleed+CU12*dec_tia) -> 1.415905e-05 | DG12: =J12*CI12+CW12+CR12-CZ12+CS12-DA12+DB12 -> 0.0004002833 | DH12: =AG12 -> 0.87037694 | DI12: =AB12+AC12+BF12+BA12+BB12+BC12+CY12+CZ12 -> 0.015080434 | DJ12: =AA12+AZ12+BY12+CX12+CE12+BZ12+CA12+CB12 -> 0.0053580846 | DK12: =AD12+DD12+DA12 -> 0.038021526 | DL12: =K12+AJ12+BI12+CH12+DG12 -> 0.071163016 | DM12: =SUM(DH12:DL12) -> 1 | DN12: =dt*(G12*Apixaban!$H$2+(H12+I12+J12)*c_aspirin) -> 66.75681 | DO12: =dt*(H12*c_lt_minor_stroke+I12*c_lt_major_stroke) -> 65.782952 | DP12: =AH12+BG12+CF12+DE12 -> 219.75705 | DQ12: =DN12+DO12+DP12 -> 352.29681 | DR12: =dt*(G12*(u_af-dec_per_year_over_70*MAX(B12-ref_age,0))+H12*(u_minor_stroke-dec_per_year_over_70*MAX(B12-ref_age,0))+I12*(u_major_stroke-dec_per_year_over_70*MAX(B12-ref_age,0))+J12*(u_af-dec_per_year_over_70*MAX(B12-ref_age,0)))-AI12-BH12-CG12-DF12 -> 0.18902536 | DS12: =dt*(G12+H12+I12+J12) -> 0.23484703 | DT12: =DQ12*C12 -> 344.5162 | DU12: =DN12*C12 -> 65.28246 | DV12: =DP12*C12 -> 214.90363 | DW12: =DO12*C12 -> 64.33011 | DX12: =DR12*C12 -> 0.18485066 | DY12: =DS12*C12 -> 0.22966035 | DZ12: =T12+AS12+BR12+CQ12 -> 0.0034672917 | EA12: =U12+AT12+BS12+CR12 -> 0.00079390822 | EB12: =V12+AU12+BT12+CS12 -> 0.0063709604 | EC12: =G12*dt*C12 -> 0.21718992
A13: 7 | B13: =start_age+A13*dt -> 71.75 | C13: =(1+disc_rate)^-(A13*dt) -> 0.97428143 | D13: =IF(A13*dt>=wane_start,(1-wane_decay)^(A13*dt-wane_start),1) -> 1 | E13: =MIN(p_nonvasc_death*MIN(EXP(gomp_int+gomp_slope*INT(B13)),1)/qx_ref,0.999) -> 0.036640021 | F13: =rr_stroke_per_decade^((B13-ref_age)/10) -> 1.0735344 | G13: =DH12 -> 0.87037694 | H13: =DI12 -> 0.015080434 | I13: =DJ12 -> 0.0053580846 | J13: =DK12 -> 0.038021526 | K13: =DL12 -> 0.071163016 | L13: =1-EXP(LN(1-E13)*dt) -> 0.0092886235 | M13: =G13*(1-L13) -> 0.86229234 | N13: =IF(Apixaban!$B$2=1,EXP(LN(or_apx_stroke)*D13)*(1-EXP(-r_stroke*F13*dt))/(1-(1-EXP(-r_stroke*F13*dt))+EXP(LN(or_apx_stroke)*D13)*(1-EXP(-r_stroke*F13*dt))),(1-EXP(-r_stroke*F13*dt))) -> 0.0034155076 | O13: =IF(Apixaban!$B$2=1,EXP(LN(or_apx_ich)*D13)*(1-EXP(-r_ich*dt))/(1-(1-EXP(-r_ich*dt))+EXP(LN(or_apx_ich)*D13)*(1-EXP(-r_ich*dt))),(1-EXP(-r_ich*dt))) -> 0.00084351325 | P13: =IF(Apixaban!$B$2=1,EXP(LN(or_apx_mb)*D13)*(1-EXP(-r_mb*dt))/(1-(1-EXP(-r_mb*dt))+EXP(LN(or_apx_mb)*D13)*(1-EXP(-r_mb*dt))),(1-EXP(-r_mb*dt))) -> 0.0066944691 | Q13: =IF(Apixaban!$B$2=1,EXP(LN(or_apx_mi)*D13)*(1-EXP(-r_mi*dt))/(1-(1-EXP(-r_mi*dt))+EXP(LN(or_apx_mi)*D13)*(1-EXP(-r_mi*dt))),(1-EXP(-r_mi*dt))) -> 0.0013232192 | R13: =(1-EXP(-r_tia*dt)) -> 0.0020060282 | S13: =(1-EXP(-r_minor*dt)) -> 0.043793769 | T13: =M13*N13 -> 0.0029451661 | U13: =M13*O13 -> 0.00072735501 | V13: =M13*P13 -> 0.0057725894 | W13: =M13*Q13 -> 0.0011410017 | X13: =M13*R13 -> 0.0017297827 | Y13: =M13*S13 -> 0.037763031 | Z13: =T13*f_stroke_fatal -> 0.00069800436 | AA13: =T13*(1-f_stroke_fatal)*f_stroke_major -> 0.00074830485 | AB13: =T13*(1-f_stroke_fatal)*(1-f_stroke_major) -> 0.0014988569 | AC13: =U13*(1-f_bleed_fatal) -> 0.00066625719 | AD13: =V13*(1-f_bleed_fatal) -> 0.0052876919 | AE13: =W13*f_mi_fatal -> 0.00013806121 | AF13: =W13-AE13 -> 0.0010029405 | AG13: =M13-T13-U13-V13-AE13 -> 0.85270916 | AH13: =Z13*c_stroke_fatal+AA13*c_stroke_major+AB13*c_stroke_minor+U13*c_ich+V13*c_major_bleed+AE13*c_mi_fatal+AF13*c_mi_nonfatal+X13*c_tia+Y13*c_minor_bleed -> 192.6073 | AI13: =dt*(AF13*dec_mi+AD13*dec_major_bleed+Y13*dec_minor_bleed+X13*dec_tia) -> 0.00032023056 | AJ13: =G13*L13+Z13+U13-AC13+V13-AD13+AE13 -> 0.0094666646 | AK13: =1-EXP(LN(1-E13)*hr_death_prior_stroke*dt) -> 0.021234968 | AL13: =H13*(1-AK13) -> 0.014760201 | AM13: =(1-EXP(-r_stroke*F13*rr_stroke_prior*rr_asa_stroke*dt)) -> 0.01530966 | AN13: =(1-EXP(-r_ich*rr_asa_ich*dt)) -> 0.0010235777 | AO13: =(1-EXP(-r_mb*rr_asa_mb*dt)) -> 0.0095180967 | AP13: =(1-EXP(-r_mi*rr_asa_mi*dt)) -> 0.0021341352 | AQ13: =(1-EXP(-r_tia*rr_asa_tia*dt)) -> 0.0031276457 | AR13: =(1-EXP(-r_minor*rr_asa_minor*dt)) -> 0.027818195 | AS13: =AL13*AM13 -> 0.00022597366 | AT13: =AL13*AN13 -> 1.5108212e-05 | AU13: =AL13*AO13 -> 0.00014048902 | AV13: =AL13*AP13 -> 3.1500264e-05 | AW13: =AL13*AQ13 -> 4.6164679e-05 | AX13: =AL13*AR13 -> 0.00041060215 | AY13: =AS13*f_stroke_fatal_recur -> 8.4082539e-05 | AZ13: =AS13*(1-f_stroke_fatal_recur)*f_stroke_major -> 4.7249743e-05 | BA13: =AS13*(1-f_stroke_fatal_recur)*(1-f_stroke_major) -> 9.4641378e-05 | BB13: =AT13*(1-f_bleed_fatal) -> 1.3839123e-05 | BC13: =AU13*(1-f_bleed_fatal) -> 0.00012868794 | BD13: =AV13*f_mi_fatal -> 3.811532e-06 | BE13: =AV13-BD13 -> 2.7688732e-05 | BF13: =AL13-AS13-AT13-AU13-BD13 -> 0.014374819 | BG13: =AY13*c_stroke_fatal+AZ13*c_stroke_major+BA13*c_stroke_minor+AT13*c_ich+AU13*c_major_bleed+BD13*c_mi_fatal+BE13*c_mi_nonfatal+AW13*c_tia+AX13*c_minor_bleed -> 9.7790321 | BH13: =dt*(BE13*dec_mi+BC13*dec_major_bleed+AX13*dec_minor_bleed+AW13*dec_tia) -> 6.3482931e-06 | BI13: =H13*AK13+AY13+AT13-BB13+AU13-BC13+BD13 -> 0.00042119676 | BJ13: =1-EXP(LN(1-E13)*hr_death_prior_stroke*dt) -> 0.021234968 | BK13: =I13*(1-BJ13) -> 0.0052443058 | BL13: =(1-EXP(-r_stroke*F13*rr_stroke_prior*rr_asa_stroke*dt)) -> 0.01530966 | BM13: =(1-EXP(-r_ich*rr_asa_ich*dt)) -> 0.0010235777 | BN13: =(1-EXP(-r_mb*rr_asa_mb*dt)) -> 0.0095180967 | BO13: =(1-EXP(-r_mi*rr_asa_mi*dt)) -> 0.0021341352 | BP13: =(1-EXP(-r_tia*rr_asa_tia*dt)) -> 0.0031276457 | BQ13: =(1-EXP(-r_minor*rr_asa_minor*dt)) -> 0.027818195 | BR13: =BK13*BL13 -> 8.0288539e-05 | BS13: =BK13*BM13 -> 5.3679544e-06 | BT13: =BK13*BN13 -> 4.991581e-05 | BU13: =BK13*BO13 -> 1.1192057e-05 | BV13: =BK13*BP13 -> 1.640233e-05 | BW13: =BK13*BQ13 -> 0.00014588712 | BX13: =BR13*f_stroke_fatal_recur -> 2.9874563e-05 | BY13: =BR13*(1-f_stroke_fatal_recur)*f_stroke_major -> 1.6787854e-05 | BZ13: =BR13*(1-f_stroke_fatal_recur)*(1-f_stroke_major) -> 3.3626122e-05 | CA13: =BS13*(1-f_bleed_fatal) -> 4.9170462e-06 | CB13: =BT13*(1-f_bleed_fatal) -> 4.5722882e-05 | CC13: =BU13*f_mi_fatal -> 1.354239e-06 | CD13: =BU13-CC13 -> 9.8378185e-06 | CE13: =BK13-BR13-BS13-BT13-CC13 -> 0.0051073793 | CF13: =BX13*c_stroke_fatal+BY13*c_stroke_major+BZ13*c_stroke_minor+BS13*c_ich+BT13*c_major_bleed+CC13*c_mi_fatal+CD13*c_mi_nonfatal+BV13*c_tia+BW13*c_minor_bleed -> 3.4744943 | CG13: =dt*(CD13*dec_mi+CB13*dec_major_bleed+BW13*dec_minor_bleed+BV13*dec_tia) -> 2.2555513e-06 | CH13: =I13*BJ13+BX13+BS13-CA13+BT13-CB13+CC13 -> 0.00014965139 | CI13: =1-EXP(LN(1-E13)*dt) -> 0.0092886235 | CJ13: =J13*(1-CI13) -> 0.037668358 | CK13: =(1-EXP(-r_stroke*F13*rr_asa_stroke*dt)) -> 0.0069882239 | CL13: =(1-EXP(-r_ich*rr_asa_ich*dt)) -> 0.0010235777 | CM13: =(1-EXP(-r_mb*rr_asa_mb*dt)) -> 0.0095180967 | CN13: =(1-EXP(-r_mi*rr_asa_mi*dt)) -> 0.0021341352 | CO13: =(1-EXP(-r_tia*rr_asa_tia*dt)) -> 0.0031276457 | CP13: =(1-EXP(-r_minor*rr_asa_minor*dt)) -> 0.027818195 | CQ13: =CJ13*CK13 -> 0.00026323492 | CR13: =CJ13*CL13 -> 3.8556491e-05 | CS13: =CJ13*CM13 -> 0.00035853108 | CT13: =CJ13*CN13 -> 8.0389368e-05 | CU13: =CJ13*CO13 -> 0.00011781328 | CV13: =CJ13*CP13 -> 0.0010478657 | CW13: =CQ13*f_stroke_fatal -> 6.2386676e-05 | CX13: =CQ13*(1-f_stroke_fatal)*f_stroke_major -> 6.6882465e-05 | CY13: =CQ13*(1-f_stroke_fatal)*(1-f_stroke_major) -> 0.00013396578 | CZ13: =CR13*(1-f_bleed_fatal) -> 3.5317746e-05 | DA13: =CS13*(1-f_bleed_fatal) -> 0.00032841447 | DB13: =CT13*f_mi_fatal -> 9.7271135e-06 | DC13: =CT13-DB13 -> 7.0662255e-05 | DD13: =CJ13-CQ13-CR13-CS13-DB13 -> 0.036998309 | DE13: =CW13*c_stroke_fatal+CX13*c_stroke_major+CY13*c_stroke_minor+CR13*c_ich+CS13*c_major_bleed+DB13*c_mi_fatal+DC13*c_mi_nonfatal+CU13*c_tia+CV13*c_minor_bleed -> 14.798262 | DF13: =dt*(DC13*dec_mi+DA13*dec_major_bleed+CV13*dec_minor_bleed+CU13*dec_tia) -> 1.6200984e-05 | DG13: =J13*CI13+CW13+CR13-CZ13+CS13-DA13+DB13 -> 0.00045863678 | DH13: =AG13 -> 0.85270916 | DI13: =AB13+AC13+BF13+BA13+BB13+BC13+CY13+CZ13 -> 0.016946385 | DJ13: =AA13+AZ13+BY13+CX13+CE13+BZ13+CA13+CB13 -> 0.0060708702 | DK13: =AD13+DD13+DA13 -> 0.042614415 | DL13: =K13+AJ13+BI13+CH13+DG13 -> 0.081659165 | DM13: =SUM(DH13:DL13) -> 1 | DN13: =dt*(G13*Apixaban!$H$2+(H13+I13+J13)*c_aspirin) -> 65.486807 | DO13: =dt*(H13*c_lt_minor_stroke+I13*c_lt_major_stroke) -> 75.74852 | DP13: =AH13+BG13+CF13+DE13 -> 220.65909 | DQ13: =DN13+DO13+DP13 -> 361.89442 | DR13: =dt*(G13*(u_af-dec_per_year_over_70*MAX(B13-ref_age,0))+H13*(u_minor_stroke-dec_per_year_over_70*MAX(B13-ref_age,0))+I13*(u_major_stroke-dec_per_year_over_70*MAX(B13-ref_age,0))+J13*(u_af-dec_per_year_over_70*MAX(B13-ref_age,0)))-AI13-BH13-CG13-DF13 -> 0.18676091 | DS13: =dt*(G13+H13+I13+J13) -> 0.23220925 | DT13: =DQ13*C13 -> 352.58701 | DU13: =DN13*C13 -> 63.80258 | DV13: =DP13*C13 -> 214.98405 | DW13: =DO13*C13 -> 73.800377 | DX13: =DR13*C13 -> 0.18195769 | DY13: =DS13*C13 -> 0.22623716 | DZ13: =T13+AS13+BR13+CQ13 -> 0.0035146632 | EA13: =U13+AT13+BS13+CR13 -> 0.00078638767 | EB13: =V13+AU13+BT13+CS13 -> 0.0063215253 | EC13: =G13*dt*C13 -> 0.21199802
A14: 8 | B14: =start_age+A14*dt -> 72 | C14: =(1+disc_rate)^-(A14*dt) -> 0.97066175 | D14: =IF(A14*dt>=wane_start,(1-wane_decay)^(A14*dt-wane_start),1) -> 1 | E14: =MIN(p_nonvasc_death*MIN(EXP(gomp_int+gomp_slope*INT(B14)),1)/qx_ref,0.999) -> 0.040681549 | F14: =rr_stroke_per_decade^((B14-ref_age)/10) -> 1.0844718 | G14: =DH13 -> 0.85270916 | H14: =DI13 -> 0.016946385 | I14: =DJ13 -> 0.0060708702 | J14: =DK13 -> 0.042614415 | K14: =DL13 -> 0.081659165 | L14: =1-EXP(LN(1-E14)*dt) -> 0.010329331 | M14: =G14*(1-L14) -> 0.84390125 | N14: =IF(Apixaban!$B$2=1,EXP(LN(or_apx_stroke)*D14)*(1-EXP(-r_stroke*F14*dt))/(1-(1-EXP(-r_stroke*F14*dt))+EXP(LN(or_apx_stroke)*D14)*(1-EXP(-r_stroke*F14*dt))),(1-EXP(-r_stroke*F14*dt))) -> 0.0034502612 | O14: =IF(Apixaban!$B$2=1,EXP(LN(or_apx_ich)*D14)*(1-EXP(-r_ich*dt))/(1-(1-EXP(-r_ich*dt))+EXP(LN(or_apx_ich)*D14)*(1-EXP(-r_ich*dt))),(1-EXP(-r_ich*dt))) -> 0.00084351325 | P14: =IF(Apixaban!$B$2=1,EXP(LN(or_apx_mb)*D14)*(1-EXP(-r_mb*dt))/(1-(1-EXP(-r_mb*dt))+EXP(LN(or_apx_mb)*D14)*(1-EXP(-r_mb*dt))),(1-EXP(-r_mb*dt))) -> 0.0066944691 | Q14: =IF(Apixaban!$B$2=1,EXP(LN(or_apx_mi)*D14)*(1-EXP(-r_mi*dt))/(1-(1-EXP(-r_mi*dt))+EXP(LN(or_apx_mi)*D14)*(1-EXP(-r_mi*dt))),(1-EXP(-r_mi*dt))) -> 0.0013232192 | R14: =(1-EXP(-r_tia*dt)) -> 0.0020060282 | S14: =(1-EXP(-r_minor*dt)) -> 0.043793769 | T14: =M14*N14 -> 0.0029116798 | U14: =M14*O14 -> 0.00071184189 | V14: =M14*P14 -> 0.0056494708 | W14: =M14*Q14 -> 0.0011166663 | X14: =M14*R14 -> 0.0016928897 | Y14: =M14*S14 -> 0.036957616 | Z14: =T14*f_stroke_fatal -> 0.00069006811 | AA14: =T14*(1-f_stroke_fatal)*f_stroke_major -> 0.00073979669 | AB14: =T14*(1-f_stroke_fatal)*(1-f_stroke_major) -> 0.001481815 | AC14: =U14*(1-f_bleed_fatal) -> 0.00065204717 | AD14: =V14*(1-f_bleed_fatal) -> 0.0051749153 | AE14: =W14*f_mi_fatal -> 0.00013511662 | AF14: =W14-AE14 -> 0.00098154968 | AG14: =M14-T14-U14-V14-AE14 -> 0.83449314 | AH14: =Z14*c_stroke_fatal+AA14*c_stroke_major+AB14*c_stroke_minor+U14*c_ich+V14*c_major_bleed+AE14*c_mi_fatal+AF14*c_mi_nonfatal+X14*c_tia+Y14*c_minor_bleed -> 189.58297 | AI14: =dt*(AF14*dec_mi+AD14*dec_major_bleed+Y14*dec_minor_bleed+X14*dec_tia) -> 0.00031340064 | AJ14: =G14*L14+Z14+U14-AC14+V14-AD14+AE14 -> 0.01016745 | AK14: =1-EXP(LN(1-E14)*hr_death_prior_stroke*dt) -> 0.023598117 | AL14: =H14*(1-AK14) -> 0.016546482 | AM14: =(1-EXP(-r_stroke*F14*rr_stroke_prior*rr_asa_stroke*dt)) -> 0.015464425 | AN14: =(1-EXP(-r_ich*rr_asa_ich*dt)) -> 0.0010235777 | AO14: =(1-EXP(-r_mb*rr_asa_mb*dt)) -> 0.0095180967 | AP14: =(1-EXP(-r_mi*rr_asa_mi*dt)) -> 0.0021341352 | AQ14: =(1-EXP(-r_tia*rr_asa_tia*dt)) -> 0.0031276457 | AR14: =(1-EXP(-r_minor*rr_asa_minor*dt)) -> 0.027818195 | AS14: =AL14*AM14 -> 0.00025588183 | AT14: =AL14*AN14 -> 1.693661e-05 | AU14: =AL14*AO14 -> 0.00015749102 | AV14: =AL14*AP14 -> 3.5312429e-05 | AW14: =AL14*AQ14 -> 5.1751532e-05 | AX14: =AL14*AR14 -> 0.00046029326 | AY14: =AS14*f_stroke_fatal_recur -> 9.5211071e-05 | AZ14: =AS14*(1-f_stroke_fatal_recur)*f_stroke_major -> 5.3503364e-05 | BA14: =AS14*(1-f_stroke_fatal_recur)*(1-f_stroke_major) -> 0.0001071674 | BB14: =AT14*(1-f_bleed_fatal) -> 1.5513934e-05 | BC14: =AU14*(1-f_bleed_fatal) -> 0.00014426177 | BD14: =AV14*f_mi_fatal -> 4.2728039e-06 | BE14: =AV14-BD14 -> 3.1039625e-05 | BF14: =AL14-AS14-AT14-AU14-BD14 -> 0.0161119 | BG14: =AY14*c_stroke_fatal+AZ14*c_stroke_major+BA14*c_stroke_minor+AT14*c_ich+AU14*c_major_bleed+BD14*c_mi_fatal+BE14*c_mi_nonfatal+AW14*c_tia+AX14*c_minor_bleed -> 11.050787 | BH14: =dt*(BE14*dec_mi+BC14*dec_major_bleed+AX14*dec_minor_bleed+AW14*dec_tia) -> 7.1165641e-06 | BI14: =H14*AK14+AY14+AT14-BB14+AU14-BC14+BD14 -> 0.00051403856 | BJ14: =1-EXP(LN(1-E14)*hr_death_prior_stroke*dt) -> 0.023598117 | BK14: =I14*(1-BJ14) -> 0.0059276091 | BL14: =(1-EXP(-r_stroke*F14*rr_stroke_prior*rr_asa_stroke*dt)) -> 0.015464425 | BM14: =(1-EXP(-r_ich*rr_asa_ich*dt)) -> 0.0010235777 | BN14: =(1-EXP(-r_mb*rr_asa_mb*dt)) -> 0.0095180967 | BO14: =(1-EXP(-r_mi*rr_asa_mi*dt)) -> 0.0021341352 | BP14: =(1-EXP(-r_tia*rr_asa_tia*dt)) -> 0.0031276457 | BQ14: =(1-EXP(-r_minor*rr_asa_minor*dt)) -> 0.027818195 | BR14: =BK14*BL14 -> 9.1667068e-05 | BS14: =BK14*BM14 -> 6.0673684e-06 | BT14: =BK14*BN14 -> 5.6419557e-05 | BU14: =BK14*BO14 -> 1.2650319e-05 | BV14: =BK14*BP14 -> 1.8539461e-05 | BW14: =BK14*BQ14 -> 0.00016489539 | BX14: =BR14*f_stroke_fatal_recur -> 3.4108399e-05 | BY14: =BR14*(1-f_stroke_fatal_recur)*f_stroke_major -> 1.9167037e-05 | BZ14: =BR14*(1-f_stroke_fatal_recur)*(1-f_stroke_major) -> 3.8391632e-05 | CA14: =BS14*(1-f_bleed_fatal) -> 5.5577095e-06 | CB14: =BT14*(1-f_bleed_fatal) -> 5.1680314e-05 | CC14: =BU14*f_mi_fatal -> 1.5306886e-06 | CD14: =BU14-CC14 -> 1.111963e-05 | CE14: =BK14-BR14-BS14-BT14-CC14 -> 0.0057719245 | CF14: =BX14*c_stroke_fatal+BY14*c_stroke_major+BZ14*c_stroke_minor+BS14*c_ich+BT14*c_major_bleed+CC14*c_mi_fatal+CD14*c_mi_nonfatal+BV14*c_tia+BW14*c_minor_bleed -> 3.9588323 | CG14: =dt*(CD14*dec_mi+CB14*dec_major_bleed+BW14*dec_minor_bleed+BV14*dec_tia) -> 2.5494368e-06 | CH14: =I14*BJ14+BX14+BS14-CA14+BT14-CB14+CC14 -> 0.00018414909 | CI14: =1-EXP(LN(1-E14)*dt) -> 0.010329331 | CJ14: =J14*(1-CI14) -> 0.042174237 | CK14: =(1-EXP(-r_stroke*F14*rr_asa_stroke*dt)) -> 0.0070591692 | CL14: =(1-EXP(-r_ich*rr_asa_ich*dt)) -> 0.0010235777 | CM14: =(1-EXP(-r_mb*rr_asa_mb*dt)) -> 0.0095180967 | CN14: =(1-EXP(-r_mi*rr_asa_mi*dt)) -> 0.0021341352 | CO14: =(1-EXP(-r_tia*rr_asa_tia*dt)) -> 0.0031276457 | CP14: =(1-EXP(-r_minor*rr_asa_minor*dt)) -> 0.027818195 | CQ14: =CJ14*CK14 -> 0.00029771507 | CR14: =CJ14*CL14 -> 4.3168607e-05 | CS14: =CJ14*CM14 -> 0.00040141846 | CT14: =CJ14*CN14 -> 9.0005522e-05 | CU14: =CJ14*CO14 -> 0.00013190607 | CV14: =CJ14*CP14 -> 0.0011732111 | CW14: =CQ14*f_stroke_fatal -> 7.0558473e-05 | CX14: =CQ14*(1-f_stroke_fatal)*f_stroke_major -> 7.5643148e-05 | CY14: =CQ14*(1-f_stroke_fatal)*(1-f_stroke_major) -> 0.00015151345 | CZ14: =CR14*(1-f_bleed_fatal) -> 3.9542444e-05 | DA14: =CS14*(1-f_bleed_fatal) -> 0.00036769931 | DB14: =CT14*f_mi_fatal -> 1.0890668e-05 | DC14: =CT14-DB14 -> 7.9114853e-05 | DD14: =CJ14-CQ14-CR14-CS14-DB14 -> 0.041421044 | DE14: =CW14*c_stroke_fatal+CX14*c_stroke_major+CY14*c_stroke_minor+CR14*c_ich+CS14*c_major_bleed+DB14*c_mi_fatal+DC14*c_mi_nonfatal+CU14*c_tia+CV14*c_minor_bleed -> 16.678976 | DF14: =dt*(DC14*dec_mi+DA14*dec_major_bleed+CV14*dec_minor_bleed+CU14*dec_tia) -> 1.8138941e-05 | DG14: =J14*CI14+CW14+CR14-CZ14+CS14-DA14+DB14 -> 0.00055897284 | DH14: =AG14 -> 0.83449314 | DI14: =AB14+AC14+BF14+BA14+BB14+BC14+CY14+CZ14 -> 0.018703761 | DJ14: =AA14+AZ14+BY14+CX14+CE14+BZ14+CA14+CB14 -> 0.0067556643 | DK14: =AD14+DD14+DA14 -> 0.046963658 | DL14: =K14+AJ14+BI14+CH14+DG14 -> 0.093083776 | DM14: =SUM(DH14:DL14) -> 1 | DN14: =dt*(G14*Apixaban!$H$2+(H14+I14+J14)*c_aspirin) -> 64.239068 | DO14: =dt*(H14*c_lt_minor_stroke+I14*c_lt_major_stroke) -> 85.446338 | DP14: =AH14+BG14+CF14+DE14 -> 221.27157 | DQ14: =DN14+DO14+DP14 -> 370.95697 | DR14: =dt*(G14*(u_af-dec_per_year_over_70*MAX(B14-ref_age,0))+H14*(u_minor_stroke-dec_per_year_over_70*MAX(B14-ref_age,0))+I14*(u_major_stroke-dec_per_year_over_70*MAX(B14-ref_age,0))+J14*(u_af-dec_per_year_over_70*MAX(B14-ref_age,0)))-AI14-BH14-CG14-DF14 -> 0.1845109 | DS14: =dt*(G14+H14+I14+J14) -> 0.22958521 | DT14: =DQ14*C14 -> 360.07374 | DU14: =DN14*C14 -> 62.354406 | DV14: =DP14*C14 -> 214.77984 | DW14: =DO14*C14 -> 82.939492 | DX14: =DR14*C14 -> 0.17909767 | DY14: =DS14*C14 -> 0.22284958 | DZ14: =T14+AS14+BR14+CQ14 -> 0.0035569438 | EA14: =U14+AT14+BS14+CR14 -> 0.00077801447 | EB14: =V14+AU14+BT14+CS14 -> 0.0062647999 | EC14: =G14*dt*C14 -> 0.20692304
A15: 9 | B15: =start_age+A15*dt -> 72.25 | C15: =(1+disc_rate)^-(A15*dt) -> 0.96705551 | D15: =IF(A15*dt>=wane_start,(1-wane_decay)^(A15*dt-wane_start),1) -> 1 | E15: =MIN(p_nonvasc_death*MIN(EXP(gomp_int+gomp_slope*INT(B15)),1)/qx_ref,0.999) -> 0.040681549 | F15: =rr_stroke_per_decade^((B15-ref_age)/10) -> 1.0955206 | G15: =DH14 -> 0.83449314 | H15: =DI14 -> 0.018703761 | I15: =DJ14 -> 0.0067556643 | J15: =DK14 -> 0.046963658 | K15: =DL14 -> 0.093083776 | L15: =1-EXP(LN(1-E15)*dt) -> 0.010329331 | M15: =G15*(1-L15) -> 0.82587338 | N15: =IF(Apixaban!$B$2=1,EXP(LN(or_apx_stroke)*D15)*(1-EXP(-r_stroke*F15*dt))/(1-(1-EXP(-r_stroke*F15*dt))+EXP(LN(or_apx_stroke)*D15)*(1-EXP(-r_stroke*F15*dt))),(1-EXP(-r_stroke*F15*dt))) -> 0.003485368 | O15: =IF(Apixaban!$B$2=1,EXP(LN(or_apx_ich)*D15)*(1-EXP(-r_ich*dt))/(1-(1-EXP(-r_ich*dt))+EXP(LN(or_apx_ich)*D15)*(1-EXP(-r_ich*dt))),(1-EXP(-r_ich*dt))) -> 0.00084351325 | P15: =IF(Apixaban!$B$2=1,EXP(LN(or_apx_mb)*D15)*(1-EXP(-r_mb*dt))/(1-(1-EXP(-r_mb*dt))+EXP(LN(or_apx_mb)*D15)*(1-EXP(-r_mb*dt))),(1-EXP(-r_mb*dt))) -> 0.0066944691 | Q15: =IF(Apixaban!$B$2=1,EXP(LN(or_apx_mi)*D15)*(1-EXP(-r_mi*dt))/(1-(1-EXP(-r_mi*dt))+EXP(LN(or_apx_mi)*D15)*(1-EXP(-r_mi*dt))),(1-EXP(-r_mi*dt))) -> 0.0013232192 | R15: =(1-EXP(-r_tia*dt)) -> 0.0020060282 | S15: =(1-EXP(-r_minor*dt)) -> 0.043793769 | T15: =M15*N15 -> 0.0028784727 | U15: =M15*O15 -> 0.00069663514 | V15: =M15*P15 -> 0.0055287838 | W15: =M15*Q15 -> 0.0010928115 | X15: =M15*R15 -> 0.0016567253 | Y15: =M15*S15 -> 0.036168108 | Z15: =T15*f_stroke_fatal -> 0.00068219803 | AA15: =T15*(1-f_stroke_fatal)*f_stroke_major -> 0.00073135946 | AB15: =T15*(1-f_stroke_fatal)*(1-f_stroke_major) -> 0.0014649152 | AC15: =U15*(1-f_bleed_fatal) -> 0.00063811779 | AD15: =V15*(1-f_bleed_fatal) -> 0.005064366 | AE15: =W15*f_mi_fatal -> 0.00013223019 | AF15: =W15-AE15 -> 0.00096058129 | AG15: =M15-T15-U15-V15-AE15 -> 0.81663726 | AH15: =Z15*c_stroke_fatal+AA15*c_stroke_major+AB15*c_stroke_minor+U15*c_ich+V15*c_major_bleed+AE15*c_mi_fatal+AF15*c_mi_nonfatal+X15*c_tia+Y15*c_minor_bleed -> 186.60425 | AI15: =dt*(AF15*dec_mi+AD15*dec_major_bleed+Y15*dec_minor_bleed+X15*dec_tia) -> 0.00030670561 | AJ15: =G15*L15+Z15+U15-AC15+V15-AD15+AE15 -> 0.009957119 | AK15: =1-EXP(LN(1-E15)*hr_death_prior_stroke*dt) -> 0.023598117 | AL15: =H15*(1-AK15) -> 0.018262387 | AM15: =(1-EXP(-r_stroke*F15*rr_stroke_prior*rr_asa_stroke*dt)) -> 0.015620743 | AN15: =(1-EXP(-r_ich*rr_asa_ich*dt)) -> 0.0010235777 | AO15: =(1-EXP(-r_mb*rr_asa_mb*dt)) -> 0.0095180967 | AP15: =(1-EXP(-r_mi*rr_asa_mi*dt)) -> 0.0021341352 | AQ15: =(1-EXP(-r_tia*rr_asa_tia*dt)) -> 0.0031276457 | AR15: =(1-EXP(-r_minor*rr_asa_minor*dt)) -> 0.027818195 | AS15: =AL15*AM15 -> 0.00028527205 | AT15: =AL15*AN15 -> 1.8692972e-05 | AU15: =AL15*AO15 -> 0.00017382317 | AV15: =AL15*AP15 -> 3.8974403e-05 | AW15: =AL15*AQ15 -> 5.7118276e-05 | AX15: =AL15*AR15 -> 0.00050802665 | AY15: =AS15*f_stroke_fatal_recur -> 0.00010614688 | AZ15: =AS15*(1-f_stroke_fatal_recur)*f_stroke_major -> 5.9648683e-05 | BA15: =AS15*(1-f_stroke_fatal_recur)*(1-f_stroke_major) -> 0.00011947649 | BB15: =AT15*(1-f_bleed_fatal) -> 1.7122762e-05 | BC15: =AU15*(1-f_bleed_fatal) -> 0.00015922202 | BD15: =AV15*f_mi_fatal -> 4.7159028e-06 | BE15: =AV15-BD15 -> 3.42585e-05 | BF15: =AL15-AS15-AT15-AU15-BD15 -> 0.017779883 | BG15: =AY15*c_stroke_fatal+AZ15*c_stroke_major+BA15*c_stroke_minor+AT15*c_ich+AU15*c_major_bleed+BD15*c_mi_fatal+BE15*c_mi_nonfatal+AW15*c_tia+AX15*c_minor_bleed -> 12.295207 | BH15: =dt*(BE15*dec_mi+BC15*dec_major_bleed+AX15*dec_minor_bleed+AW15*dec_tia) -> 7.8545669e-06 | BI15: =H15*AK15+AY15+AT15-BB15+AU15-BC15+BD15 -> 0.00056840766 | BJ15: =1-EXP(LN(1-E15)*hr_death_prior_stroke*dt) -> 0.023598117 | BK15: =I15*(1-BJ15) -> 0.0065962434 | BL15: =(1-EXP(-r_stroke*F15*rr_stroke_prior*rr_asa_stroke*dt)) -> 0.015620743 | BM15: =(1-EXP(-r_ich*rr_asa_ich*dt)) -> 0.0010235777 | BN15: =(1-EXP(-r_mb*rr_asa_mb*dt)) -> 0.0095180967 | BO15: =(1-EXP(-r_mi*rr_asa_mi*dt)) -> 0.0021341352 | BP15: =(1-EXP(-r_tia*rr_asa_tia*dt)) -> 0.0031276457 | BQ15: =(1-EXP(-r_minor*rr_asa_minor*dt)) -> 0.027818195 | BR15: =BK15*BL15 -> 0.00010303822 | BS15: =BK15*BM15 -> 6.7517675e-06 | BT15: =BK15*BN15 -> 6.2783683e-05 | BU15: =BK15*BO15 -> 1.4077275e-05 | BV15: =BK15*BP15 -> 2.0630712e-05 | BW15: =BK15*BQ15 -> 0.00018349559 | BX15: =BR15*f_stroke_fatal_recur -> 3.8339491e-05 | BY15: =BR15*(1-f_stroke_fatal_recur)*f_stroke_major -> 2.1544677e-05 | BZ15: =BR15*(1-f_stroke_fatal_recur)*(1-f_stroke_major) -> 4.3154052e-05 | CA15: =BS15*(1-f_bleed_fatal) -> 6.184619e-06 | CB15: =BT15*(1-f_bleed_fatal) -> 5.7509853e-05 | CC15: =BU15*f_mi_fatal -> 1.7033503e-06 | CD15: =BU15-CC15 -> 1.2373925e-05 | CE15: =BK15-BR15-BS15-BT15-CC15 -> 0.0064219664 | CF15: =BX15*c_stroke_fatal+BY15*c_stroke_major+BZ15*c_stroke_minor+BS15*c_ich+BT15*c_major_bleed+CC15*c_mi_fatal+CD15*c_mi_nonfatal+BV15*c_tia+BW15*c_minor_bleed -> 4.4409405 | CG15: =dt*(CD15*dec_mi+CB15*dec_major_bleed+BW15*dec_minor_bleed+BV15*dec_tia) -> 2.8370133e-06 | CH15: =I15*BJ15+BX15+BS15-CA15+BT15-CB15+CC15 -> 0.00020530477 | CI15: =1-EXP(LN(1-E15)*dt) -> 0.010329331 | CJ15: =J15*(1-CI15) -> 0.046478555 | CK15: =(1-EXP(-r_stroke*F15*rr_asa_stroke*dt)) -> 0.0071308323 | CL15: =(1-EXP(-r_ich*rr_asa_ich*dt)) -> 0.0010235777 | CM15: =(1-EXP(-r_mb*rr_asa_mb*dt)) -> 0.0095180967 | CN15: =(1-EXP(-r_mi*rr_asa_mi*dt)) -> 0.0021341352 | CO15: =(1-EXP(-r_tia*rr_asa_tia*dt)) -> 0.0031276457 | CP15: =(1-EXP(-r_minor*rr_asa_minor*dt)) -> 0.027818195 | CQ15: =CJ15*CK15 -> 0.00033143078 | CR15: =CJ15*CL15 -> 4.7574412e-05 | CS15: =CJ15*CM15 -> 0.00044238739 | CT15: =CJ15*CN15 -> 9.9191519e-05 | CU15: =CJ15*CO15 -> 0.00014536845 | CV15: =CJ15*CP15 -> 0.0012929495 | CW15: =CQ15*f_stroke_fatal -> 7.8549095e-05 | CX15: =CQ15*(1-f_stroke_fatal)*f_stroke_major -> 8.4209602e-05 | CY15: =CQ15*(1-f_stroke_fatal)*(1-f_stroke_major) -> 0.00016867209 | CZ15: =CR15*(1-f_bleed_fatal) -> 4.3578161e-05 | DA15: =CS15*(1-f_bleed_fatal) -> 0.00040522684 | DB15: =CT15*f_mi_fatal -> 1.2002174e-05 | DC15: =CT15-DB15 -> 8.7189345e-05 | DD15: =CJ15-CQ15-CR15-CS15-DB15 -> 0.045645161 | DE15: =CW15*c_stroke_fatal+CX15*c_stroke_major+CY15*c_stroke_minor+CR15*c_ich+CS15*c_major_bleed+DB15*c_mi_fatal+DC15*c_mi_nonfatal+CU15*c_tia+CV15*c_minor_bleed -> 18.504303 | DF15: =dt*(DC15*dec_mi+DA15*dec_major_bleed+CV15*dec_minor_bleed+CU15*dec_tia) -> 1.9990208e-05 | DG15: =J15*CI15+CW15+CR15-CZ15+CS15-DA15+DB15 -> 0.00061681122 | DH15: =AG15 -> 0.81663726 | DI15: =AB15+AC15+BF15+BA15+BB15+BC15+CY15+CZ15 -> 0.020390988 | DJ15: =AA15+AZ15+BY15+CX15+CE15+BZ15+CA15+CB15 -> 0.0074255773 | DK15: =AD15+DD15+DA15 -> 0.051114753 | DL15: =K15+AJ15+BI15+CH15+DG15 -> 0.10443142 | DM15: =SUM(DH15:DL15) -> 1 | DN15: =dt*(G15*Apixaban!$H$2+(H15+I15+J15)*c_aspirin) -> 62.946727 | DO15: =dt*(H15*c_lt_minor_stroke+I15*c_lt_major_stroke) -> 94.667894 | DP15: =AH15+BG15+CF15+DE15 -> 221.8447 | DQ15: =DN15+DO15+DP15 -> 379.45932 | DR15: =dt*(G15*(u_af-dec_per_year_over_70*MAX(B15-ref_age,0))+H15*(u_minor_stroke-dec_per_year_over_70*MAX(B15-ref_age,0))+I15*(u_major_stroke-dec_per_year_over_70*MAX(B15-ref_age,0))+J15*(u_af-dec_per_year_over_70*MAX(B15-ref_age,0)))-AI15-BH15-CG15-DF15 -> 0.18207836 | DS15: =dt*(G15+H15+I15+J15) -> 0.22672906 | DT15: =DQ15*C15 -> 366.95823 | DU15: =DN15*C15 -> 60.87298 | DV15: =DP15*C15 -> 214.53614 | DW15: =DO15*C15 -> 91.549108 | DX15: =DR15*C15 -> 0.17607988 | DY15: =DS15*C15 -> 0.21925958 | DZ15: =T15+AS15+BR15+CQ15 -> 0.0035982137 | EA15: =U15+AT15+BS15+CR15 -> 0.00076965429 | EB15: =V15+AU15+BT15+CS15 -> 0.0062077781 | EC15: =G15*dt*C15 -> 0.2017503
A16: 10 | B16: =start_age+A16*dt -> 72.5 | C16: =(1+disc_rate)^-(A16*dt) -> 0.96346267 | D16: =IF(A16*dt>=wane_start,(1-wane_decay)^(A16*dt-wane_start),1) -> 1 | E16: =MIN(p_nonvasc_death*MIN(EXP(gomp_int+gomp_slope*INT(B16)),1)/qx_ref,0.999) -> 0.040681549 | F16: =rr_stroke_per_decade^((B16-ref_age)/10) -> 1.1066819 | G16: =DH15 -> 0.81663726 | H16: =DI15 -> 0.020390988 | I16: =DJ15 -> 0.0074255773 | J16: =DK15 -> 0.051114753 | K16: =DL15 -> 0.10443142 | L16: =1-EXP(LN(1-E16)*dt) -> 0.010329331 | M16: =G16*(1-L16) -> 0.80820195 | N16: =IF(Apixaban!$B$2=1,EXP(LN(or_apx_stroke)*D16)*(1-EXP(-r_stroke*F16*dt))/(1-(1-EXP(-r_stroke*F16*dt))+EXP(LN(or_apx_stroke)*D16)*(1-EXP(-r_stroke*F16*dt))),(1-EXP(-r_stroke*F16*dt))) -> 0.0035208316 | O16: =IF(Apixaban!$B$2=1,EXP(LN(or_apx_ich)*D16)*(1-EXP(-r_ich*dt))/(1-(1-EXP(-r_ich*dt))+EXP(LN(or_apx_ich)*D16)*(1-EXP(-r_ich*dt))),(1-EXP(-r_ich*dt))) -> 0.00084351325 | P16: =IF(Apixaban!$B$2=1,EXP(LN(or_apx_mb)*D16)*(1-EXP(-r_mb*dt))/(1-(1-EXP(-r_mb*dt))+EXP(LN(or_apx_mb)*D16)*(1-EXP(-r_mb*dt))),(1-EXP(-r_mb*dt))) -> 0.0066944691 | Q16: =IF(Apixaban!$B$2=1,EXP(LN(or_apx_mi)*D16)*(1-EXP(-r_mi*dt))/(1-(1-EXP(-r_mi*dt))+EXP(LN(or_apx_mi)*D16)*(1-EXP(-r_mi*dt))),(1-EXP(-r_mi*dt))) -> 0.0013232192 | R16: =(1-EXP(-r_tia*dt)) -> 0.0020060282 | S16: =(1-EXP(-r_minor*dt)) -> 0.043793769 | T16: =M16*N16 -> 0.0028455429 | U16: =M16*O16 -> 0.00068172905 | V16: =M16*P16 -> 0.0054104829 | W16: =M16*Q16 -> 0.0010694283 | X16: =M16*R16 -> 0.0016212759 | Y16: =M16*S16 -> 0.035394209 | Z16: =T16*f_stroke_fatal -> 0.00067439367 | AA16: =T16*(1-f_stroke_fatal)*f_stroke_major -> 0.0007229927 | AB16: =T16*(1-f_stroke_fatal)*(1-f_stroke_major) -> 0.0014481566 | AC16: =U16*(1-f_bleed_fatal) -> 0.00062446381 | AD16: =V16*(1-f_bleed_fatal) -> 0.0049560024 | AE16: =W16*f_mi_fatal -> 0.00012940082 | AF16: =W16-AE16 -> 0.00094002747 | AG16: =M16-T16-U16-V16-AE16 -> 0.79913479 | AH16: =Z16*c_stroke_fatal+AA16*c_stroke_major+AB16*c_stroke_minor+U16*c_ich+V16*c_major_bleed+AE16*c_mi_fatal+AF16*c_mi_nonfatal+X16*c_tia+Y16*c_minor_bleed -> 183.67041 | AI16: =dt*(AF16*dec_mi+AD16*dec_major_bleed+Y16*dec_minor_bleed+X16*dec_tia) -> 0.00030014295 | AJ16: =G16*L16+Z16+U16-AC16+V16-AD16+AE16 -> 0.0097508567 | AK16: =1-EXP(LN(1-E16)*hr_death_prior_stroke*dt) -> 0.023598117 | AL16: =H16*(1-AK16) -> 0.019909799 | AM16: =(1-EXP(-r_stroke*F16*rr_stroke_prior*rr_asa_stroke*dt)) -> 0.015778627 | AN16: =(1-EXP(-r_ich*rr_asa_ich*dt)) -> 0.0010235777 | AO16: =(1-EXP(-r_mb*rr_asa_mb*dt)) -> 0.0095180967 | AP16: =(1-EXP(-r_mi*rr_asa_mi*dt)) -> 0.0021341352 | AQ16: =(1-EXP(-r_tia*rr_asa_tia*dt)) -> 0.0031276457 | AR16: =(1-EXP(-r_minor*rr_asa_minor*dt)) -> 0.027818195 | AS16: =AL16*AM16 -> 0.0003141493 | AT16: =AL16*AN16 -> 2.0379226e-05 | AU16: =AL16*AO16 -> 0.00018950339 | AV16: =AL16*AP16 -> 4.2490202e-05 | AW16: =AL16*AQ16 -> 6.2270796e-05 | AX16: =AL16*AR16 -> 0.00055385467 | AY16: =AS16*f_stroke_fatal_recur -> 0.00011689181 | AZ16: =AS16*(1-f_stroke_fatal_recur)*f_stroke_major -> 6.5686742e-05 | BA16: =AS16*(1-f_stroke_fatal_recur)*(1-f_stroke_major) -> 0.00013157074 | BB16: =AT16*(1-f_bleed_fatal) -> 1.8667371e-05 | BC16: =AU16*(1-f_bleed_fatal) -> 0.00017358511 | BD16: =AV16*f_mi_fatal -> 5.1413144e-06 | BE16: =AV16-BD16 -> 3.7348887e-05 | BF16: =AL16-AS16-AT16-AU16-BD16 -> 0.019380626 | BG16: =AY16*c_stroke_fatal+AZ16*c_stroke_major+BA16*c_stroke_minor+AT16*c_ich+AU16*c_major_bleed+BD16*c_mi_fatal+BE16*c_mi_nonfatal+AW16*c_tia+AX16*c_minor_bleed -> 13.512716 | BH16: =dt*(BE16*dec_mi+BC16*dec_major_bleed+AX16*dec_minor_bleed+AW16*dec_tia) -> 8.5631108e-06 | BI16: =H16*AK16+AY16+AT16-BB16+AU16-BC16+BD16 -> 0.00062085217 | BJ16: =1-EXP(LN(1-E16)*hr_death_prior_stroke*dt) -> 0.023598117 | BK16: =I16*(1-BJ16) -> 0.0072503477 | BL16: =(1-EXP(-r_stroke*F16*rr_stroke_prior*rr_asa_stroke*dt)) -> 0.015778627 | BM16: =(1-EXP(-r_ich*rr_asa_ich*dt)) -> 0.0010235777 | BN16: =(1-EXP(-r_mb*rr_asa_mb*dt)) -> 0.0095180967 | BO16: =(1-EXP(-r_mi*rr_asa_mi*dt)) -> 0.0021341352 | BP16: =(1-EXP(-r_tia*rr_asa_tia*dt)) -> 0.0031276457 | BQ16: =(1-EXP(-r_minor*rr_asa_minor*dt)) -> 0.027818195 | BR16: =BK16*BL16 -> 0.00011440053 | BS16: =BK16*BM16 -> 7.421294e-06 | BT16: =BK16*BN16 -> 6.9009511e-05 | BU16: =BK16*BO16 -> 1.5473222e-05 | BV16: =BK16*BP16 -> 2.2676518e-05 | BW16: =BK16*BQ16 -> 0.00020169159 | BX16: =BR16*f_stroke_fatal_recur -> 4.2567295e-05 | BY16: =BR16*(1-f_stroke_fatal_recur)*f_stroke_major -> 2.3920469e-05 | BZ16: =BR16*(1-f_stroke_fatal_recur)*(1-f_stroke_major) -> 4.7912771e-05 | CA16: =BS16*(1-f_bleed_fatal) -> 6.7979053e-06 | CB16: =BT16*(1-f_bleed_fatal) -> 6.3212712e-05 | CC16: =BU16*f_mi_fatal -> 1.8722599e-06 | CD16: =BU16-CC16 -> 1.3600962e-05 | CE16: =BK16-BR16-BS16-BT16-CC16 -> 0.0070576441 | CF16: =BX16*c_stroke_fatal+BY16*c_stroke_major+BZ16*c_stroke_minor+BS16*c_ich+BT16*c_major_bleed+CC16*c_mi_fatal+CD16*c_mi_nonfatal+BV16*c_tia+BW16*c_minor_bleed -> 4.9207875 | CG16: =dt*(CD16*dec_mi+CB16*dec_major_bleed+BW16*dec_minor_bleed+BV16*dec_tia) -> 3.1183404e-06 | CH16: =I16*BJ16+BX16+BS16-CA16+BT16-CB16+CC16 -> 0.00022608938 | CI16: =1-EXP(LN(1-E16)*dt) -> 0.010329331 | CJ16: =J16*(1-CI16) -> 0.050586772 | CK16: =(1-EXP(-r_stroke*F16*rr_asa_stroke*dt)) -> 0.0072032202 | CL16: =(1-EXP(-r_ich*rr_asa_ich*dt)) -> 0.0010235777 | CM16: =(1-EXP(-r_mb*rr_asa_mb*dt)) -> 0.0095180967 | CN16: =(1-EXP(-r_mi*rr_asa_mi*dt)) -> 0.0021341352 | CO16: =(1-EXP(-r_tia*rr_asa_tia*dt)) -> 0.0031276457 | CP16: =(1-EXP(-r_minor*rr_asa_minor*dt)) -> 0.027818195 | CQ16: =CJ16*CK16 -> 0.00036438766 | CR16: =CJ16*CL16 -> 5.1779491e-05 | CS16: =CJ16*CM16 -> 0.00048148979 | CT16: =CJ16*CN16 -> 0.00010795901 | CU16: =CJ16*CO16 -> 0.0001582175 | CV16: =CJ16*CP16 -> 0.0014072327 | CW16: =CQ16*f_stroke_fatal -> 8.6359875e-05 | CX16: =CQ16*(1-f_stroke_fatal)*f_stroke_major -> 9.2583252e-05 | CY16: =CQ16*(1-f_stroke_fatal)*(1-f_stroke_major) -> 0.00018544453 | CZ16: =CR16*(1-f_bleed_fatal) -> 4.7430014e-05 | DA16: =CS16*(1-f_bleed_fatal) -> 0.00044104465 | DB16: =CT16*f_mi_fatal -> 1.306304e-05 | DC16: =CT16-DB16 -> 9.4895969e-05 | DD16: =CJ16-CQ16-CR16-CS16-DB16 -> 0.049676052 | DE16: =CW16*c_stroke_fatal+CX16*c_stroke_major+CY16*c_stroke_minor+CR16*c_ich+CS16*c_major_bleed+DB16*c_mi_fatal+DC16*c_mi_nonfatal+CU16*c_tia+CV16*c_minor_bleed -> 20.275187 | DF16: =dt*(DC16*dec_mi+DA16*dec_major_bleed+CV16*dec_minor_bleed+CU16*dec_tia) -> 2.1757133e-05 | DG16: =J16*CI16+CW16+CR16-CZ16+CS16-DA16+DB16 -> 0.00067219873 | DH16: =AG16 -> 0.79913479 | DI16: =AB16+AC16+BF16+BA16+BB16+BC16+CY16+CZ16 -> 0.022009944 | DJ16: =AA16+AZ16+BY16+CX16+CE16+BZ16+CA16+CB16 -> 0.0080807506 | DK16: =AD16+DD16+DA16 -> 0.055073099 | DL16: =K16+AJ16+BI16+CH16+DG16 -> 0.11570142 | DM16: =SUM(DH16:DL16) -> 1 | DN16: =dt*(G16*Apixaban!$H$2+(H16+I16+J16)*c_aspirin) -> 61.678484 | DO16: =dt*(H16*c_lt_minor_stroke+I16*c_lt_major_stroke) -> 103.60266 | DP16: =AH16+BG16+CF16+DE16 -> 222.3791 | DQ16: =DN16+DO16+DP16 -> 387.66024 | DR16: =dt*(G16*(u_af-dec_per_year_over_70*MAX(B16-ref_age,0))+H16*(u_minor_stroke-dec_per_year_over_70*MAX(B16-ref_age,0))+I16*(u_major_stroke-dec_per_year_over_70*MAX(B16-ref_age,0))+J16*(u_af-dec_per_year_over_70*MAX(B16-ref_age,0)))-AI16-BH16-CG16-DF16 -> 0.17966463 | DS16: =dt*(G16+H16+I16+J16) -> 0.22389215 | DT16: =DQ16*C16 -> 373.49617 | DU16: =DN16*C16 -> 59.424917 | DV16: =DP16*C16 -> 214.25396 | DW16: =DO16*C16 -> 99.817295 | DX16: =DR16*C16 -> 0.17310016 | DY16: =DS16*C16 -> 0.21571173 | DZ16: =T16+AS16+BR16+CQ16 -> 0.0036384804 | EA16: =U16+AT16+BS16+CR16 -> 0.00076130906 | EB16: =V16+AU16+BT16+CS16 -> 0.0061504856 | EC16: =G16*dt*C16 -> 0.19669988
A17: 11 | B17: =start_age+A17*dt -> 72.75 | C17: =(1+disc_rate)^-(A17*dt) -> 0.95988318 | D17: =IF(A17*dt>=wane_start,(1-wane_decay)^(A17*dt-wane_start),1) -> 1 | E17: =MIN(p_nonvasc_death*MIN(EXP(gomp_int+gomp_slope*INT(B17)),1)/qx_ref,0.999) -> 0.040681549 | F17: =rr_stroke_per_decade^((B17-ref_age)/10) -> 1.117957 | G17: =DH16 -> 0.79913479 | H17: =DI16 -> 0.022009944 | I17: =DJ16 -> 0.0080807506 | J17: =DK16 -> 0.055073099 | K17: =DL16 -> 0.11570142 | L17: =1-EXP(LN(1-E17)*dt) -> 0.010329331 | M17: =G17*(1-L17) -> 0.79088026 | N17: =IF(Apixaban!$B$2=1,EXP(LN(or_apx_stroke)*D17)*(1-EXP(-r_stroke*F17*dt))/(1-(1-EXP(-r_stroke*F17*dt))+EXP(LN(or_apx_stroke)*D17)*(1-EXP(-r_stroke*F17*dt))),(1-EXP(-r_stroke*F17*dt))) -> 0.0035566555 | O17: =IF(Apixaban!$B$2=1,EXP(LN(or_apx_ich)*D17)*(1-EXP(-r_ich*dt))/(1-(1-EXP(-r_ich*dt))+EXP(LN(or_apx_ich)*D17)*(1-EXP(-r_ich*dt))),(1-EXP(-r_ich*dt))) -> 0.00084351325 | P17: =IF(Apixaban!$B$2=1,EXP(LN(or_apx_mb)*D17)*(1-EXP(-r_mb*dt))/(1-(1-EXP(-r_mb*dt))+EXP(LN(or_apx_mb)*D17)*(1-EXP(-r_mb*dt))),(1-EXP(-r_mb*dt))) -> 0.0066944691 | Q17: =IF(Apixaban!$B$2=1,EXP(LN(or_apx_mi)*D17)*(1-EXP(-r_mi*dt))/(1-(1-EXP(-r_mi*dt))+EXP(LN(or_apx_mi)*D17)*(1-EXP(-r_mi*dt))),(1-EXP(-r_mi*dt))) -> 0.0013232192 | R17: =(1-EXP(-r_tia*dt)) -> 0.0020060282 | S17: =(1-EXP(-r_minor*dt)) -> 0.043793769 | T17: =M17*N17 -> 0.0028128886 | U17: =M17*O17 -> 0.00066711798 | V17: =M17*P17 -> 0.0052945235 | W17: =M17*Q17 -> 0.0010465079 | X17: =M17*R17 -> 0.0015865281 | Y17: =M17*S17 -> 0.034635628 | Z17: =T17*f_stroke_fatal -> 0.0006666546 | AA17: =T17*(1-f_stroke_fatal)*f_stroke_major -> 0.00071469593 | AB17: =T17*(1-f_stroke_fatal)*(1-f_stroke_major) -> 0.0014315381 | AC17: =U17*(1-f_bleed_fatal) -> 0.00061108007 | AD17: =V17*(1-f_bleed_fatal) -> 0.0048497835 | AE17: =W17*f_mi_fatal -> 0.00012662746 | AF17: =W17-AE17 -> 0.00091988046 | AG17: =M17-T17-U17-V17-AE17 -> 0.78197911 | AH17: =Z17*c_stroke_fatal+AA17*c_stroke_major+AB17*c_stroke_minor+U17*c_ich+V17*c_major_bleed+AE17*c_mi_fatal+AF17*c_mi_nonfatal+X17*c_tia+Y17*c_minor_bleed -> 180.78073 | AI17: =dt*(AF17*dec_mi+AD17*dec_major_bleed+Y17*dec_minor_bleed+X17*dec_tia) -> 0.00029371017 | AJ17: =G17*L17+Z17+U17-AC17+V17-AD17+AE17 -> 0.0095485875 | AK17: =1-EXP(LN(1-E17)*hr_death_prior_stroke*dt) -> 0.023598117 | AL17: =H17*(1-AK17) -> 0.021490551 | AM17: =(1-EXP(-r_stroke*F17*rr_stroke_prior*rr_asa_stroke*dt)) -> 0.015938095 | AN17: =(1-EXP(-r_ich*rr_asa_ich*dt)) -> 0.0010235777 | AO17: =(1-EXP(-r_mb*rr_asa_mb*dt)) -> 0.0095180967 | AP17: =(1-EXP(-r_mi*rr_asa_mi*dt)) -> 0.0021341352 | AQ17: =(1-EXP(-r_tia*rr_asa_tia*dt)) -> 0.0031276457 | AR17: =(1-EXP(-r_minor*rr_asa_minor*dt)) -> 0.027818195 | AS17: =AL17*AM17 -> 0.00034251843 | AT17: =AL17*AN17 -> 2.1997248e-05 | AU17: =AL17*AO17 -> 0.00020454914 | AV17: =AL17*AP17 -> 4.586374e-05 | AW17: =AL17*AQ17 -> 6.7214827e-05 | AX17: =AL17*AR17 -> 0.00059782833 | AY17: =AS17*f_stroke_fatal_recur -> 0.00012744768 | AZ17: =AS17*(1-f_stroke_fatal_recur)*f_stroke_major -> 7.1618559e-05 | BA17: =AS17*(1-f_stroke_fatal_recur)*(1-f_stroke_major) -> 0.00014345219 | BB17: =AT17*(1-f_bleed_fatal) -> 2.0149479e-05 | BC17: =AU17*(1-f_bleed_fatal) -> 0.00018736701 | BD17: =AV17*f_mi_fatal -> 5.5495125e-06 | BE17: =AV17-BD17 -> 4.0314227e-05 | BF17: =AL17-AS17-AT17-AU17-BD17 -> 0.020915936 | BG17: =AY17*c_stroke_fatal+AZ17*c_stroke_major+BA17*c_stroke_minor+AT17*c_ich+AU17*c_major_bleed+BD17*c_mi_fatal+BE17*c_mi_nonfatal+AW17*c_tia+AX17*c_minor_bleed -> 14.70373 | BH17: =dt*(BE17*dec_mi+BC17*dec_major_bleed+AX17*dec_minor_bleed+AW17*dec_tia) -> 9.2429847e-06 | BI17: =H17*AK17+AY17+AT17-BB17+AU17-BC17+BD17 -> 0.00067142031 | BJ17: =1-EXP(LN(1-E17)*hr_death_prior_stroke*dt) -> 0.023598117 | BK17: =I17*(1-BJ17) -> 0.0078900601 | BL17: =(1-EXP(-r_stroke*F17*rr_stroke_prior*rr_asa_stroke*dt)) -> 0.015938095 | BM17: =(1-EXP(-r_ich*rr_asa_ich*dt)) -> 0.0010235777 | BN17: =(1-EXP(-r_mb*rr_asa_mb*dt)) -> 0.0095180967 | BO17: =(1-EXP(-r_mi*rr_asa_mi*dt)) -> 0.0021341352 | BP17: =(1-EXP(-r_tia*rr_asa_tia*dt)) -> 0.0031276457 | BQ17: =(1-EXP(-r_minor*rr_asa_minor*dt)) -> 0.027818195 | BR17: =BK17*BL17 -> 0.00012575253 | BS17: =BK17*BM17 -> 8.0760894e-06 | BT17: =BK17*BN17 -> 7.5098356e-05 | BU17: =BK17*BO17 -> 1.6838455e-05 | BV17: =BK17*BP17 -> 2.4677312e-05 | BW17: =BK17*BQ17 -> 0.00021948723 | BX17: =BR17*f_stroke_fatal_recur -> 4.6791258e-05 | BY17: =BR17*(1-f_stroke_fatal_recur)*f_stroke_major -> 2.6294103e-05 | BZ17: =BR17*(1-f_stroke_fatal_recur)*(1-f_stroke_major) -> 5.2667167e-05 | CA17: =BS17*(1-f_bleed_fatal) -> 7.3976979e-06 | CB17: =BT17*(1-f_bleed_fatal) -> 6.8790094e-05 | CC17: =BU17*f_mi_fatal -> 2.037453e-06 | CD17: =BU17-CC17 -> 1.4801002e-05 | CE17: =BK17-BR17-BS17-BT17-CC17 -> 0.0076790957 | CF17: =BX17*c_stroke_fatal+BY17*c_stroke_major+BZ17*c_stroke_minor+BS17*c_ich+BT17*c_major_bleed+CC17*c_mi_fatal+CD17*c_mi_nonfatal+BV17*c_tia+BW17*c_minor_bleed -> 5.3983406 | CG17: =dt*(CD17*dec_mi+CB17*dec_major_bleed+BW17*dec_minor_bleed+BV17*dec_tia) -> 3.3934778e-06 | CH17: =I17*BJ17+BX17+BS17-CA17+BT17-CB17+CC17 -> 0.00024650586 | CI17: =1-EXP(LN(1-E17)*dt) -> 0.010329331 | CJ17: =J17*(1-CI17) -> 0.054504231 | CK17: =(1-EXP(-r_stroke*F17*rr_asa_stroke*dt)) -> 0.0072763402 | CL17: =(1-EXP(-r_ich*rr_asa_ich*dt)) -> 0.0010235777 | CM17: =(1-EXP(-r_mb*rr_asa_mb*dt)) -> 0.0095180967 | CN17: =(1-EXP(-r_mi*rr_asa_mi*dt)) -> 0.0021341352 | CO17: =(1-EXP(-r_tia*rr_asa_tia*dt)) -> 0.0031276457 | CP17: =(1-EXP(-r_minor*rr_asa_minor*dt)) -> 0.027818195 | CQ17: =CJ17*CK17 -> 0.00039659133 | CR17: =CJ17*CL17 -> 5.5789314e-05 | CS17: =CJ17*CM17 -> 0.00051877654 | CT17: =CJ17*CN17 -> 0.0001163194 | CU17: =CJ17*CO17 -> 0.00017046992 | CV17: =CJ17*CP17 -> 0.0015162093 | CW17: =CQ17*f_stroke_fatal -> 9.3992145e-05 | CX17: =CQ17*(1-f_stroke_fatal)*f_stroke_major -> 0.00010076553 | CY17: =CQ17*(1-f_stroke_fatal)*(1-f_stroke_major) -> 0.00020183366 | CZ17: =CR17*(1-f_bleed_fatal) -> 5.1103012e-05 | DA17: =CS17*(1-f_bleed_fatal) -> 0.00047519931 | DB17: =CT17*f_mi_fatal -> 1.4074647e-05 | DC17: =CT17-DB17 -> 0.00010224475 | DD17: =CJ17-CQ17-CR17-CS17-DB17 -> 0.053518999 | DE17: =CW17*c_stroke_fatal+CX17*c_stroke_major+CY17*c_stroke_minor+CR17*c_ich+CS17*c_major_bleed+DB17*c_mi_fatal+DC17*c_mi_nonfatal+CU17*c_tia+CV17*c_minor_bleed -> 21.992555 | DF17: =dt*(DC17*dec_mi+DA17*dec_major_bleed+CV17*dec_minor_bleed+CU17*dec_tia) -> 2.3442013e-05 | DG17: =J17*CI17+CW17+CR17-CZ17+CS17-DA17+DB17 -> 0.00072519858 | DH17: =AG17 -> 0.78197911 | DI17: =AB17+AC17+BF17+BA17+BB17+BC17+CY17+CZ17 -> 0.02356246 | DJ17: =AA17+AZ17+BY17+CX17+CE17+BZ17+CA17+CB17 -> 0.0087213248 | DK17: =AD17+DD17+DA17 -> 0.058843982 | DL17: =K17+AJ17+BI17+CH17+DG17 -> 0.12689313 | DM17: =SUM(DH17:DL17) -> 1 | DN17: =dt*(G17*Apixaban!$H$2+(H17+I17+J17)*c_aspirin) -> 60.433908 | DO17: =dt*(H17*c_lt_minor_stroke+I17*c_lt_major_stroke) -> 112.25663 | DP17: =AH17+BG17+CF17+DE17 -> 222.87536 | DQ17: =DN17+DO17+DP17 -> 395.5659 | DR17: =dt*(G17*(u_af-dec_per_year_over_70*MAX(B17-ref_age,0))+H17*(u_minor_stroke-dec_per_year_over_70*MAX(B17-ref_age,0))+I17*(u_major_stroke-dec_per_year_over_70*MAX(B17-ref_age,0))+J17*(u_af-dec_per_year_over_70*MAX(B17-ref_age,0)))-AI17-BH17-CG17-DF17 -> 0.17726978 | DS17: =dt*(G17+H17+I17+J17) -> 0.22107465 | DT17: =DQ17*C17 -> 379.69706 | DU17: =DN17*C17 -> 58.009492 | DV17: =DP17*C17 -> 213.93431 | DW17: =DO17*C17 -> 107.75326 | DX17: =DR17*C17 -> 0.17015828 | DY17: =DS17*C17 -> 0.21220584 | DZ17: =T17+AS17+BR17+CQ17 -> 0.0036777509 | EA17: =U17+AT17+BS17+CR17 -> 0.00075298063 | EB17: =V17+AU17+BT17+CS17 -> 0.0060929475 | EC17: =G17*dt*C17 -> 0.19176901
A18: 12 | B18: =start_age+A18*dt -> 73 | C18: =(1+disc_rate)^-(A18*dt) -> 0.95631699 | D18: =IF(A18*dt>=wane_start,(1-wane_decay)^(A18*dt-wane_start),1) -> 1 | E18: =MIN(p_nonvasc_death*MIN(EXP(gomp_int+gomp_slope*INT(B18)),1)/qx_ref,0.999) -> 0.045168873 | F18: =rr_stroke_per_decade^((B18-ref_age)/10) -> 1.1293469 | G18: =DH17 -> 0.78197911 | H18: =DI17 -> 0.02356246 | I18: =DJ17 -> 0.0087213248 | J18: =DK17 -> 0.058843982 | K18: =DL17 -> 0.12689313 | L18: =1-EXP(LN(1-E18)*dt) -> 0.011488691 | M18: =G18*(1-L18) -> 0.77299519 | N18: =IF(Apixaban!$B$2=1,EXP(LN(or_apx_stroke)*D18)*(1-EXP(-r_stroke*F18*dt))/(1-(1-EXP(-r_stroke*F18*dt))+EXP(LN(or_apx_stroke)*D18)*(1-EXP(-r_stroke*F18*dt))),(1-EXP(-r_stroke*F18*dt))) -> 0.0035928434 | O18: =IF(Apixaban!$B$2=1,EXP(LN(or_apx_ich)*D18)*(1-EXP(-r_ich*dt))/(1-(1-EXP(-r_ich*dt))+EXP(LN(or_apx_ich)*D18)*(1-EXP(-r_ich*dt))),(1-EXP(-r_ich*dt))) -> 0.00084351325 | P18: =IF(Apixaban!$B$2=1,EXP(LN(or_apx_mb)*D18)*(1-EXP(-r_mb*dt))/(1-(1-EXP(-r_mb*dt))+EXP(LN(or_apx_mb)*D18)*(1-EXP(-r_mb*dt))),(1-EXP(-r_mb*dt))) -> 0.0066944691 | Q18: =IF(Apixaban!$B$2=1,EXP(LN(or_apx_mi)*D18)*(1-EXP(-r_mi*dt))/(1-(1-EXP(-r_mi*dt))+EXP(LN(or_apx_mi)*D18)*(1-EXP(-r_mi*dt))),(1-EXP(-r_mi*dt))) -> 0.0013232192 | R18: =(1-EXP(-r_tia*dt)) -> 0.0020060282 | S18: =(1-EXP(-r_minor*dt)) -> 0.043793769 | T18: =M18*N18 -> 0.0027772507 | U18: =M18*O18 -> 0.00065203168 | V18: =M18*P18 -> 0.0051747924 | W18: =M18*Q18 -> 0.001022842 | X18: =M18*R18 -> 0.0015506501 | Y18: =M18*S18 -> 0.033852373 | Z18: =T18*f_stroke_fatal -> 0.00065820841 | AA18: =T18*(1-f_stroke_fatal)*f_stroke_major -> 0.00070564107 | AB18: =T18*(1-f_stroke_fatal)*(1-f_stroke_major) -> 0.0014134012 | AC18: =U18*(1-f_bleed_fatal) -> 0.00059726102 | AD18: =V18*(1-f_bleed_fatal) -> 0.0047401098 | AE18: =W18*f_mi_fatal -> 0.00012376389 | AF18: =W18-AE18 -> 0.00089907815 | AG18: =M18-T18-U18-V18-AE18 -> 0.76426735 | AH18: =Z18*c_stroke_fatal+AA18*c_stroke_major+AB18*c_stroke_minor+U18*c_ich+V18*c_major_bleed+AE18*c_mi_fatal+AF18*c_mi_nonfatal+X18*c_tia+Y18*c_minor_bleed -> 177.72607 | AI18: =dt*(AF18*dec_mi+AD18*dec_major_bleed+Y18*dec_minor_bleed+X18*dec_tia) -> 0.00028706817 | AJ18: =G18*L18+Z18+U18-AC18+V18-AD18+AE18 -> 0.010255342 | AK18: =1-EXP(LN(1-E18)*hr_death_prior_stroke*dt) -> 0.026226892 | AL18: =H18*(1-AK18) -> 0.02294449 | AM18: =(1-EXP(-r_stroke*F18*rr_stroke_prior*rr_asa_stroke*dt)) -> 0.016099161 | AN18: =(1-EXP(-r_ich*rr_asa_ich*dt)) -> 0.0010235777 | AO18: =(1-EXP(-r_mb*rr_asa_mb*dt)) -> 0.0095180967 | AP18: =(1-EXP(-r_mi*rr_asa_mi*dt)) -> 0.0021341352 | AQ18: =(1-EXP(-r_tia*rr_asa_tia*dt)) -> 0.0031276457 | AR18: =(1-EXP(-r_minor*rr_asa_minor*dt)) -> 0.027818195 | AS18: =AL18*AM18 -> 0.00036938703 | AT18: =AL18*AN18 -> 2.3485467e-05 | AU18: =AL18*AO18 -> 0.00021838787 | AV18: =AL18*AP18 -> 4.8966642e-05 | AW18: =AL18*AQ18 -> 7.1762233e-05 | AX18: =AL18*AR18 -> 0.00063827429 | AY18: =AS18*f_stroke_fatal_recur -> 0.00013744522 | AZ18: =AS18*(1-f_stroke_fatal_recur)*f_stroke_major -> 7.7236622e-05 | BA18: =AS18*(1-f_stroke_fatal_recur)*(1-f_stroke_major) -> 0.00015470519 | BB18: =AT18*(1-f_bleed_fatal) -> 2.1512688e-05 | BC18: =AU18*(1-f_bleed_fatal) -> 0.00020004329 | BD18: =AV18*f_mi_fatal -> 5.9249637e-06 | BE18: =AV18-BD18 -> 4.3041678e-05 | BF18: =AL18-AS18-AT18-AU18-BD18 -> 0.022327304 | BG18: =AY18*c_stroke_fatal+AZ18*c_stroke_major+BA18*c_stroke_minor+AT18*c_ich+AU18*c_major_bleed+BD18*c_mi_fatal+BE18*c_mi_nonfatal+AW18*c_tia+AX18*c_minor_bleed -> 15.825929 | BH18: =dt*(BE18*dec_mi+BC18*dec_major_bleed+AX18*dec_minor_bleed+AW18*dec_tia) -> 9.8683171e-06 | BI18: =H18*AK18+AY18+AT18-BB18+AU18-BC18+BD18 -> 0.00078165763 | BJ18: =1-EXP(LN(1-E18)*hr_death_prior_stroke*dt) -> 0.026226892 | BK18: =I18*(1-BJ18) -> 0.0084925915 | BL18: =(1-EXP(-r_stroke*F18*rr_stroke_prior*rr_asa_stroke*dt)) -> 0.016099161 | BM18: =(1-EXP(-r_ich*rr_asa_ich*dt)) -> 0.0010235777 | BN18: =(1-EXP(-r_mb*rr_asa_mb*dt)) -> 0.0095180967 | BO18: =(1-EXP(-r_mi*rr_asa_mi*dt)) -> 0.0021341352 | BP18: =(1-EXP(-r_tia*rr_asa_tia*dt)) -> 0.0031276457 | BQ18: =(1-EXP(-r_minor*rr_asa_minor*dt)) -> 0.027818195 | BR18: =BK18*BL18 -> 0.0001367236 | BS18: =BK18*BM18 -> 8.6928271e-06 | BT18: =BK18*BN18 -> 8.0833308e-05 | BU18: =BK18*BO18 -> 1.8124338e-05 | BV18: =BK18*BP18 -> 2.6561817e-05 | BW18: =BK18*BQ18 -> 0.00023624857 | BX18: =BR18*f_stroke_fatal_recur -> 5.0873483e-05 | BY18: =BR18*(1-f_stroke_fatal_recur)*f_stroke_major -> 2.8588088e-05 | BZ18: =BR18*(1-f_stroke_fatal_recur)*(1-f_stroke_major) -> 5.7262026e-05 | CA18: =BS18*(1-f_bleed_fatal) -> 7.9626297e-06 | CB18: =BT18*(1-f_bleed_fatal) -> 7.404331e-05 | CC18: =BU18*f_mi_fatal -> 2.1930449e-06 | CD18: =BU18-CC18 -> 1.5931293e-05 | CE18: =BK18-BR18-BS18-BT18-CC18 -> 0.0082641488 | CF18: =BX18*c_stroke_fatal+BY18*c_stroke_major+BZ18*c_stroke_minor+BS18*c_ich+BT18*c_major_bleed+CC18*c_mi_fatal+CD18*c_mi_nonfatal+BV18*c_tia+BW18*c_minor_bleed -> 5.857753 | CG18: =dt*(CD18*dec_mi+CB18*dec_major_bleed+BW18*dec_minor_bleed+BV18*dec_tia) -> 3.6526237e-06 | CH18: =I18*BJ18+BX18+BS18-CA18+BT18-CB18+CC18 -> 0.00028931997 | CI18: =1-EXP(LN(1-E18)*dt) -> 0.011488691 | CJ18: =J18*(1-CI18) -> 0.058167942 | CK18: =(1-EXP(-r_stroke*F18*rr_asa_stroke*dt)) -> 0.0073501997 | CL18: =(1-EXP(-r_ich*rr_asa_ich*dt)) -> 0.0010235777 | CM18: =(1-EXP(-r_mb*rr_asa_mb*dt)) -> 0.0095180967 | CN18: =(1-EXP(-r_mi*rr_asa_mi*dt)) -> 0.0021341352 | CO18: =(1-EXP(-r_tia*rr_asa_tia*dt)) -> 0.0031276457 | CP18: =(1-EXP(-r_minor*rr_asa_minor*dt)) -> 0.027818195 | CQ18: =CJ18*CK18 -> 0.00042754599 | CR18: =CJ18*CL18 -> 5.9539407e-05 | CS18: =CJ18*CM18 -> 0.00055364809 | CT18: =CJ18*CN18 -> 0.00012413825 | CU18: =CJ18*CO18 -> 0.00018192871 | CV18: =CJ18*CP18 -> 0.0016181271 | CW18: =CQ18*f_stroke_fatal -> 0.0001013284 | CX18: =CQ18*(1-f_stroke_fatal)*f_stroke_major -> 0.00010863046 | CY18: =CQ18*(1-f_stroke_fatal)*(1-f_stroke_major) -> 0.00021758713 | CZ18: =CR18*(1-f_bleed_fatal) -> 5.4538096e-05 | DA18: =CS18*(1-f_bleed_fatal) -> 0.00050714165 | DB18: =CT18*f_mi_fatal -> 1.5020728e-05 | DC18: =CT18-DB18 -> 0.00010911752 | DD18: =CJ18-CQ18-CR18-CS18-DB18 -> 0.057112187 | DE18: =CW18*c_stroke_fatal+CX18*c_stroke_major+CY18*c_stroke_minor+CR18*c_ich+CS18*c_major_bleed+DB18*c_mi_fatal+DC18*c_mi_nonfatal+CU18*c_tia+CV18*c_minor_bleed -> 23.629605 | DF18: =dt*(DC18*dec_mi+DA18*dec_major_bleed+CV18*dec_minor_bleed+CU18*dec_tia) -> 2.5017758e-05 | DG18: =J18*CI18+CW18+CR18-CZ18+CS18-DA18+DB18 -> 0.00084389722 | DH18: =AG18 -> 0.76426735 | DI18: =AB18+AC18+BF18+BA18+BB18+BC18+CY18+CZ18 -> 0.024986353 | DJ18: =AA18+AZ18+BY18+CX18+CE18+BZ18+CA18+CB18 -> 0.009323513 | DK18: =AD18+DD18+DA18 -> 0.062359439 | DL18: =K18+AJ18+BI18+CH18+DG18 -> 0.13906334 | DM18: =SUM(DH18:DL18) -> 1 | DN18: =dt*(G18*Apixaban!$H$2+(H18+I18+J18)*c_aspirin) -> 59.212576 | DO18: =dt*(H18*c_lt_minor_stroke+I18*c_lt_major_stroke) -> 120.63569 | DP18: =AH18+BG18+CF18+DE18 -> 223.03936 | DQ18: =DN18+DO18+DP18 -> 402.88762 | DR18: =dt*(G18*(u_af-dec_per_year_over_70*MAX(B18-ref_age,0))+H18*(u_minor_stroke-dec_per_year_over_70*MAX(B18-ref_age,0))+I18*(u_major_stroke-dec_per_year_over_70*MAX(B18-ref_age,0))+J18*(u_af-dec_per_year_over_70*MAX(B18-ref_age,0)))-AI18-BH18-CG18-DF18 -> 0.17489431 | DS18: =dt*(G18+H18+I18+J18) -> 0.21827672 | DT18: =DQ18*C18 -> 385.28828 | DU18: =DN18*C18 -> 56.625992 | DV18: =DP18*C18 -> 213.29633 | DW18: =DO18*C18 -> 115.36596 | DX18: =DR18*C18 -> 0.1672544 | DY18: =DS18*C18 -> 0.20874173 | DZ18: =T18+AS18+BR18+CQ18 -> 0.0037109073 | EA18: =U18+AT18+BS18+CR18 -> 0.00074374939 | EB18: =V18+AU18+BT18+CS18 -> 0.0060276617 | EC18: =G18*dt*C18 -> 0.18695498
... A125: 119 | B125: =start_age+A125*dt -> 99.75 | C125: =(1+disc_rate)^-(A125*dt) -> 0.64214816 | D125: =IF(A125*dt>=wane_start,(1-wane_decay)^(A125*dt-wane_start),1) -> 1 | E125: =MIN(p_nonvasc_death*MIN(EXP(gomp_int+gomp_slope*INT(B125)),1)/qx_ref,0.999) -> 0.68600194 | F125: =rr_stroke_per_decade^((B125-ref_age)/10) -> 3.3409617 | G125: =DH124 -> 4.8355779e-05 | H125: =DI124 -> 2.2168813e-06 | I125: =DJ124 -> 1.0775261e-06 | J125: =DK124 -> 3.1707885e-05 | K125: =DL124 -> 0.99991664 | L125: =1-EXP(LN(1-E125)*dt) -> 0.25143117 | M125: =G125*(1-L125) -> 3.6197629e-05 | N125: =IF(Apixaban!$B$2=1,EXP(LN(or_apx_stroke)*D125)*(1-EXP(-r_stroke*F125*dt))/(1-(1-EXP(-r_stroke*F125*dt))+EXP(LN(or_apx_stroke)*D125)*(1-EXP(-r_stroke*F125*dt))),(1-EXP(-r_stroke*F125*dt))) -> 0.010601232 | O125: =IF(Apixaban!$B$2=1,EXP(LN(or_apx_ich)*D125)*(1-EXP(-r_ich*dt))/(1-(1-EXP(-r_ich*dt))+EXP(LN(or_apx_ich)*D125)*(1-EXP(-r_ich*dt))),(1-EXP(-r_ich*dt))) -> 0.00084351325 | P125: =IF(Apixaban!$B$2=1,EXP(LN(or_apx_mb)*D125)*(1-EXP(-r_mb*dt))/(1-(1-EXP(-r_mb*dt))+EXP(LN(or_apx_mb)*D125)*(1-EXP(-r_mb*dt))),(1-EXP(-r_mb*dt))) -> 0.0066944691 | Q125: =IF(Apixaban!$B$2=1,EXP(LN(or_apx_mi)*D125)*(1-EXP(-r_mi*dt))/(1-(1-EXP(-r_mi*dt))+EXP(LN(or_apx_mi)*D125)*(1-EXP(-r_mi*dt))),(1-EXP(-r_mi*dt))) -> 0.0013232192 | R125: =(1-EXP(-r_tia*dt)) -> 0.0020060282 | S125: =(1-EXP(-r_minor*dt)) -> 0.043793769 | T125: =M125*N125 -> 3.8373948e-07 | U125: =M125*O125 -> 3.053318e-08 | V125: =M125*P125 -> 2.4232391e-07 | W125: =M125*Q125 -> 4.7897397e-08 | X125: =M125*R125 -> 7.2613464e-08 | Y125: =M125*S125 -> 1.5852306e-06 | Z125: =T125*f_stroke_fatal -> 9.0946258e-08 | AA125: =T125*(1-f_stroke_fatal)*f_stroke_major -> 9.7500145e-08 | AB125: =T125*(1-f_stroke_fatal)*(1-f_stroke_major) -> 1.9529308e-07 | AC125: =U125*(1-f_bleed_fatal) -> 2.7968393e-08 | AD125: =V125*(1-f_bleed_fatal) -> 2.219687e-07 | AE125: =W125*f_mi_fatal -> 5.795585e-09 | AF125: =W125-AE125 -> 4.2101812e-08 | AG125: =M125-T125-U125-V125-AE125 -> 3.5535237e-05 | AH125: =Z125*c_stroke_fatal+AA125*c_stroke_major+AB125*c_stroke_minor+U125*c_ich+V125*c_major_bleed+AE125*c_mi_fatal+AF125*c_mi_nonfatal+X125*c_tia+Y125*c_minor_bleed -> 0.017695649 | AI125: =dt*(AF125*dec_mi+AD125*dec_major_bleed+Y125*dec_minor_bleed+X125*dec_tia) -> 1.3442758e-08 | AJ125: =G125*L125+Z125+U125-AC125+V125-AD125+AE125 -> 1.2277812e-05 | AK125: =1-EXP(LN(1-E125)*hr_death_prior_stroke*dt) -> 0.48627227 | AL125: =H125*(1-AK125) -> 1.1388734e-06 | AM125: =(1-EXP(-r_stroke*F125*rr_stroke_prior*rr_asa_stroke*dt)) -> 0.046879455 | AN125: =(1-EXP(-r_ich*rr_asa_ich*dt)) -> 0.0010235777 | AO125: =(1-EXP(-r_mb*rr_asa_mb*dt)) -> 0.0095180967 | AP125: =(1-EXP(-r_mi*rr_asa_mi*dt)) -> 0.0021341352 | AQ125: =(1-EXP(-r_tia*rr_asa_tia*dt)) -> 0.0031276457 | AR125: =(1-EXP(-r_minor*rr_asa_minor*dt)) -> 0.027818195 | AS125: =AL125*AM125 -> 5.3389764e-08 | AT125: =AL125*AN125 -> 1.1657254e-09 | AU125: =AL125*AO125 -> 1.0839907e-08 | AV125: =AL125*AP125 -> 2.4305097e-09 | AW125: =AL125*AQ125 -> 3.5619924e-09 | AX125: =AL125*AR125 -> 3.1681402e-08 | AY125: =AS125*f_stroke_fatal_recur -> 1.9865797e-08 | AZ125: =AS125*(1-f_stroke_fatal_recur)*f_stroke_major -> 1.1163481e-08 | BA125: =AS125*(1-f_stroke_fatal_recur)*(1-f_stroke_major) -> 2.2360486e-08 | BB125: =AT125*(1-f_bleed_fatal) -> 1.0678044e-09 | BC125: =AU125*(1-f_bleed_fatal) -> 9.9293548e-09 | BD125: =AV125*f_mi_fatal -> 2.9409168e-10 | BE125: =AV125-BD125 -> 2.136418e-09 | BF125: =AL125-AS125-AT125-AU125-BD125 -> 1.0731839e-06 | BG125: =AY125*c_stroke_fatal+AZ125*c_stroke_major+BA125*c_stroke_minor+AT125*c_ich+AU125*c_major_bleed+BD125*c_mi_fatal+BE125*c_mi_nonfatal+AW125*c_tia+AX125*c_minor_bleed -> 0.0019942088 | BH125: =dt*(BE125*dec_mi+BC125*dec_major_bleed+AX125*dec_minor_bleed+AW125*dec_tia) -> 4.8982408e-10 | BI125: =H125*AK125+AY125+AT125-BB125+AU125-BC125+BD125 -> 1.0991763e-06 | BJ125: =1-EXP(LN(1-E125)*hr_death_prior_stroke*dt) -> 0.48627227 | BK125: =I125*(1-BJ125) -> 5.5355502e-07 | BL125: =(1-EXP(-r_stroke*F125*rr_stroke_prior*rr_asa_stroke*dt)) -> 0.046879455 | BM125: =(1-EXP(-r_ich*rr_asa_ich*dt)) -> 0.0010235777 | BN125: =(1-EXP(-r_mb*rr_asa_mb*dt)) -> 0.0095180967 | BO125: =(1-EXP(-r_mi*rr_asa_mi*dt)) -> 0.0021341352 | BP125: =(1-EXP(-r_tia*rr_asa_tia*dt)) -> 0.0031276457 | BQ125: =(1-EXP(-r_minor*rr_asa_minor*dt)) -> 0.027818195 | BR125: =BK125*BL125 -> 2.5950358e-08 | BS125: =BK125*BM125 -> 5.6660656e-10 | BT125: =BK125*BN125 -> 5.2687902e-09 | BU125: =BK125*BO125 -> 1.1813612e-09 | BV125: =BK125*BP125 -> 1.731324e-09 | BW125: =BK125*BQ125 -> 1.5398901e-08 | BX125: =BR125*f_stroke_fatal_recur -> 9.6558686e-09 | BY125: =BR125*(1-f_stroke_fatal_recur)*f_stroke_major -> 5.4260649e-09 | BZ125: =BR125*(1-f_stroke_fatal_recur)*(1-f_stroke_major) -> 1.0868424e-08 | CA125: =BS125*(1-f_bleed_fatal) -> 5.1901161e-10 | CB125: =BT125*(1-f_bleed_fatal) -> 4.8262118e-09 | CC125: =BU125*f_mi_fatal -> 1.4294471e-10 | CD125: =BU125-CC125 -> 1.0384165e-09 | CE125: =BK125-BR125-BS125-BT125-CC125 -> 5.2162632e-07 | CF125: =BX125*c_stroke_fatal+BY125*c_stroke_major+BZ125*c_stroke_minor+BS125*c_ich+BT125*c_major_bleed+CC125*c_mi_fatal+CD125*c_mi_nonfatal+BV125*c_tia+BW125*c_minor_bleed -> 0.000969295 | CG125: =dt*(CD125*dec_mi+CB125*dec_major_bleed+BW125*dec_minor_bleed+BV125*dec_tia) -> 2.3808141e-10 | CH125: =I125*BJ125+BX125+BS125-CA125+BT125-CB125+CC125 -> 5.3426004e-07 | CI125: =1-EXP(LN(1-E125)*dt) -> 0.25143117 | CJ125: =J125*(1-CI125) -> 2.3735535e-05 | CK125: =(1-EXP(-r_stroke*F125*rr_asa_stroke*dt)) -> 0.021588066 | CL125: =(1-EXP(-r_ich*rr_asa_ich*dt)) -> 0.0010235777 | CM125: =(1-EXP(-r_mb*rr_asa_mb*dt)) -> 0.0095180967 | CN125: =(1-EXP(-r_mi*rr_asa_mi*dt)) -> 0.0021341352 | CO125: =(1-EXP(-r_tia*rr_asa_tia*dt)) -> 0.0031276457 | CP125: =(1-EXP(-r_minor*rr_asa_minor*dt)) -> 0.027818195 | CQ125: =CJ125*CK125 -> 5.1240429e-07 | CR125: =CJ125*CL125 -> 2.4295164e-08 | CS125: =CJ125*CM125 -> 2.2591712e-07 | CT125: =CJ125*CN125 -> 5.0654839e-08 | CU125: =CJ125*CO125 -> 7.4236342e-08 | CV125: =CJ125*CP125 -> 6.6027974e-07 | CW125: =CQ125*f_stroke_fatal -> 1.2143982e-07 | CX125: =CQ125*(1-f_stroke_fatal)*f_stroke_major -> 1.3019117e-07 | CY125: =CQ125*(1-f_stroke_fatal)*(1-f_stroke_major) -> 2.607733e-07 | CZ125: =CR125*(1-f_bleed_fatal) -> 2.225437e-08 | DA125: =CS125*(1-f_bleed_fatal) -> 2.0694008e-07 | DB125: =CT125*f_mi_fatal -> 6.1292356e-09 | DC125: =CT125-DB125 -> 4.4525604e-08 | DD125: =CJ125-CQ125-CR125-CS125-DB125 -> 2.2966789e-05 | DE125: =CW125*c_stroke_fatal+CX125*c_stroke_major+CY125*c_stroke_minor+CR125*c_ich+CS125*c_major_bleed+DB125*c_mi_fatal+DC125*c_mi_nonfatal+CU125*c_tia+CV125*c_minor_bleed -> 0.02212831 | DF125: =dt*(DC125*dec_mi+DA125*dec_major_bleed+CV125*dec_minor_bleed+CU125*dec_tia) -> 1.0208542e-08 | DG125: =J125*CI125+CW125+CR125-CZ125+CS125-DA125+DB125 -> 8.1209375e-06 | DH125: =AG125 -> 3.5535237e-05 | DI125: =AB125+AC125+BF125+BA125+BB125+BC125+CY125+CZ125 -> 1.6128307e-06 | DJ125: =AA125+AZ125+BY125+CX125+CE125+BZ125+CA125+CB125 -> 7.8212083e-07 | DK125: =AD125+DD125+DA125 -> 2.3395698e-05 | DL125: =K125+AJ125+BI125+CH125+DG125 -> 0.99993867 | DM125: =SUM(DH125:DL125) -> 1 | DN125: =dt*(G125*Apixaban!$H$2+(H125+I125+J125)*c_aspirin) -> 0.0039481922 | DO125: =dt*(H125*c_lt_minor_stroke+I125*c_lt_major_stroke) -> 0.013027756 | DP125: =AH125+BG125+CF125+DE125 -> 0.042787463 | DQ125: =DN125+DO125+DP125 -> 0.059763412 | DR125: =dt*(G125*(u_af-dec_per_year_over_70*MAX(B125-ref_age,0))+H125*(u_minor_stroke-dec_per_year_over_70*MAX(B125-ref_age,0))+I125*(u_major_stroke-dec_per_year_over_70*MAX(B125-ref_age,0))+J125*(u_af-dec_per_year_over_70*MAX(B125-ref_age,0)))-AI125-BH125-CG125-DF125 -> 1.6513982e-05 | DS125: =dt*(G125+H125+I125+J125) -> 2.0839518e-05 | DT125: =DQ125*C125 -> 0.038376965 | DU125: =DN125*C125 -> 0.0025353244 | DV125: =DP125*C125 -> 0.027475891 | DW125: =DO125*C125 -> 0.0083657499 | DX125: =DR125*C125 -> 1.0604423e-05 | DY125: =DS125*C125 -> 1.3382058e-05 | DZ125: =T125+AS125+BR125+CQ125 -> 9.7548389e-07 | EA125: =U125+AT125+BS125+CR125 -> 5.6560676e-08 | EB125: =V125+AU125+BT125+CS125 -> 4.8434972e-07 | EC125: =G125*dt*C125 -> 7.7628937e-06

Sheet Warfarin
A1: Warfarin arm — cohort Markov trace (120 x 3-month cycles)
A2: Arm flag (1 = apixaban, 0 = warfarin) | B2: 0 | D2: Annual cost of the anticoagulant strategy (state 0) | H2: =IF($B$2=1,c_apixaban,c_warfarin+c_inr) -> 384.22883
A3: Columns grouped by state (S0 = AF on anticoagulant, S1 = post minor stroke/ICH, S2 = post major stroke, S3 = post major bleed, S4 = dead). Occupancy columns are start-of-cycle; 'New' columns feed the next row.
A5: Cycle | B5: Age | C5: Discount factor | D5: Apixaban effect multiplier (waning) | E5: Background death (annual) | F5: Stroke age factor | G5: Occupancy S0 | H5: Occupancy S1 | I5: Occupancy S2 | J5: Occupancy S3 | K5: Occupancy S4 | L5: S0: p background death | M5: S0: survivors of background death | N5: S0: p stroke | O5: S0: p ich | P5: S0: p mb | Q5: S0: p mi | R5: S0: p tia | S5: S0: p minor | T5: S0: n stroke | U5: S0: n ich | V5: S0: n mb | W5: S0: n mi | X5: S0: n tia | Y5: S0: n minor | Z5: S0: fatal strokes | AA5: S0: non-fatal major strokes | AB5: S0: non-fatal minor strokes | AC5: S0: non-fatal ICH | AD5: S0: non-fatal major bleeds | AE5: S0: fatal MI | AF5: S0: non-fatal MI | AG5: S0: remain (no state-changing event) | AH5: S0: event costs | AI5: S0: event QALY loss | AJ5: S0: all deaths this cycle | AK5: S1: p background death | AL5: S1: survivors of background death | AM5: S1: p stroke | AN5: S1: p ich | AO5: S1: p mb | AP5: S1: p mi | AQ5: S1: p tia | AR5: S1: p minor | AS5: S1: n stroke | AT5: S1: n ich | AU5: S1: n mb | AV5: S1: n mi | AW5: S1: n tia | AX5: S1: n minor | AY5: S1: fatal strokes | AZ5: S1: non-fatal major strokes | BA5: S1: non-fatal minor strokes | BB5: S1: non-fatal ICH | BC5: S1: non-fatal major bleeds | BD5: S1: fatal MI | BE5: S1: non-fatal MI | BF5: S1: remain (no state-changing event) | BG5: S1: event costs | BH5: S1: event QALY loss | BI5: S1: all deaths this cycle | BJ5: S2: p background death | BK5: S2: survivors of background death | BL5: S2: p stroke | BM5: S2: p ich | BN5: S2: p mb | BO5: S2: p mi | BP5: S2: p tia | BQ5: S2: p minor | BR5: S2: n stroke | BS5: S2: n ich | BT5: S2: n mb | BU5: S2: n mi | BV5: S2: n tia | BW5: S2: n minor | BX5: S2: fatal strokes | BY5: S2: non-fatal major strokes | BZ5: S2: non-fatal minor strokes | CA5: S2: non-fatal ICH | CB5: S2: non-fatal major bleeds | CC5: S2: fatal MI | CD5: S2: non-fatal MI | CE5: S2: remain (no state-changing event) | CF5: S2: event costs | CG5: S2: event QALY loss | CH5: S2: all deaths this cycle | CI5: S3: p background death | CJ5: S3: survivors of background death | CK5: S3: p stroke | CL5: S3: p ich | CM5: S3: p mb | CN5: S3: p mi | CO5: S3: p tia | CP5: S3: p minor | CQ5: S3: n stroke | CR5: S3: n ich | CS5: S3: n mb | CT5: S3: n mi | CU5: S3: n tia | CV5: S3: n minor | CW5: S3: fatal strokes | CX5: S3: non-fatal major strokes | CY5: S3: non-fatal minor strokes | CZ5: S3: non-fatal ICH | DA5: S3: non-fatal major bleeds | DB5: S3: fatal MI | DC5: S3: non-fatal MI | DD5: S3: remain (no state-changing event) | DE5: S3: event costs | DF5: S3: event QALY loss | DG5: S3: all deaths this cycle | DH5: New S0 (next cycle) | DI5: New S1 (next cycle) | DJ5: New S2 (next cycle) | DK5: New S3 (next cycle) | DL5: New S4 (next cycle) | DM5: Mass check (=1) | DN5: Drug cost | DO5: Long-term care cost | DP5: Event cost | DQ5: Total cost (undiscounted) | DR5: QALYs (undiscounted) | DS5: Life-years (undiscounted) | DT5: Total cost (discounted) | DU5: Drug cost (disc.) | DV5: Event cost (disc.) | DW5: Long-term cost (disc.) | DX5: QALYs (discounted) | DY5: Life-years (discounted) | DZ5: Strokes this cycle | EA5: ICH this cycle | EB5: Major bleeds this cycle | EC5: Discounted years on anticoagulant (S0)
A6: 0 | B6: =start_age+A6*dt -> 70 | C6: =(1+disc_rate)^-(A6*dt) -> 1 | D6: =IF(A6*dt>=wane_start,(1-wane_decay)^(A6*dt-wane_start),1) -> 1 | E6: =MIN(p_nonvasc_death*MIN(EXP(gomp_int+gomp_slope*INT(B6)),1)/qx_ref,0.999) -> 0.033 | F6: =rr_stroke_per_decade^((B6-ref_age)/10) -> 1 | G6: 1 | H6: 0 | I6: 0 | J6: 0 | K6: 0 | L6: =1-EXP(LN(1-E6)*dt) -> 0.0083541048 | M6: =G6*(1-L6) -> 0.9916459 | N6: =IF(Warfarin!$B$2=1,EXP(LN(or_apx_stroke)*D6)*(1-EXP(-r_stroke*F6*dt))/(1-(1-EXP(-r_stroke*F6*dt))+EXP(LN(or_apx_stroke)*D6)*(1-EXP(-r_stroke*F6*dt))),(1-EXP(-r_stroke*F6*dt))) -> 0.0040242265 | O6: =IF(Warfarin!$B$2=1,EXP(LN(or_apx_ich)*D6)*(1-EXP(-r_ich*dt))/(1-(1-EXP(-r_ich*dt))+EXP(LN(or_apx_ich)*D6)*(1-EXP(-r_ich*dt))),(1-EXP(-r_ich*dt))) -> 0.0020060282 | P6: =IF(Warfarin!$B$2=1,EXP(LN(or_apx_mb)*D6)*(1-EXP(-r_mb*dt))/(1-(1-EXP(-r_mb*dt))+EXP(LN(or_apx_mb)*D6)*(1-EXP(-r_mb*dt))),(1-EXP(-r_mb*dt))) -> 0.0083541048 | Q6: =IF(Warfarin!$B$2=1,EXP(LN(or_apx_mi)*D6)*(1-EXP(-r_mi*dt))/(1-(1-EXP(-r_mi*dt))+EXP(LN(or_apx_mi)*D6)*(1-EXP(-r_mi*dt))),(1-EXP(-r_mi*dt))) -> 0.0015033869 | R6: =(1-EXP(-r_tia*dt)) -> 0.0020060282 | S6: =(1-EXP(-r_minor*dt)) -> 0.043793769 | T6: =M6*N6 -> 0.0039906077 | U6: =M6*O6 -> 0.0019892696 | V6: =M6*P6 -> 0.0082843137 | W6: =M6*Q6 -> 0.0014908274 | X6: =M6*R6 -> 0.0019892696 | Y6: =M6*S6 -> 0.043427911 | Z6: =T6*f_stroke_fatal -> 0.00094577402 | AA6: =T6*(1-f_stroke_fatal)*f_stroke_major -> 0.0010139296 | AB6: =T6*(1-f_stroke_fatal)*(1-f_stroke_major) -> 0.0020309041 | AC6: =U6*(1-f_bleed_fatal) -> 0.0018221709 | AD6: =V6*(1-f_bleed_fatal) -> 0.0075884314 | AE6: =W6*f_mi_fatal -> 0.00018039012 | AF6: =W6-AE6 -> 0.0013104373 | AG6: =M6-T6-U6-V6-AE6 -> 0.97720131 | AH6: =Z6*c_stroke_fatal+AA6*c_stroke_major+AB6*c_stroke_minor+U6*c_ich+V6*c_major_bleed+AE6*c_mi_fatal+AF6*c_mi_nonfatal+X6*c_tia+Y6*c_minor_bleed -> 282.50964 | AI6: =dt*(AF6*dec_mi+AD6*dec_major_bleed+Y6*dec_minor_bleed+X6*dec_tia) -> 0.00040784949 | AJ6: =G6*L6+Z6+U6-AC6+V6-AD6+AE6 -> 0.01034325 | AK6: =1-EXP(LN(1-E6)*hr_death_prior_stroke*dt) -> 0.019110191 | AL6: =H6*(1-AK6) -> 0 | AM6: =(1-EXP(-r_stroke*F6*rr_stroke_prior*rr_asa_stroke*dt)) -> 0.014268505 | AN6: =(1-EXP(-r_ich*rr_asa_ich*dt)) -> 0.0010235777 | AO6: =(1-EXP(-r_mb*rr_asa_mb*dt)) -> 0.0095180967 | AP6: =(1-EXP(-r_mi*rr_asa_mi*dt)) -> 0.0021341352 | AQ6: =(1-EXP(-r_tia*rr_asa_tia*dt)) -> 0.0031276457 | AR6: =(1-EXP(-r_minor*rr_asa_minor*dt)) -> 0.027818195 | AS6: =AL6*AM6 -> 0 | AT6: =AL6*AN6 -> 0 | AU6: =AL6*AO6 -> 0 | AV6: =AL6*AP6 -> 0 | AW6: =AL6*AQ6 -> 0 | AX6: =AL6*AR6 -> 0 | AY6: =AS6*f_stroke_fatal_recur -> 0 | AZ6: =AS6*(1-f_stroke_fatal_recur)*f_stroke_major -> 0 | BA6: =AS6*(1-f_stroke_fatal_recur)*(1-f_stroke_major) -> 0 | BB6: =AT6*(1-f_bleed_fatal) -> 0 | BC6: =AU6*(1-f_bleed_fatal) -> 0 | BD6: =AV6*f_mi_fatal -> 0 | BE6: =AV6-BD6 -> 0 | BF6: =AL6-AS6-AT6-AU6-BD6 -> 0 | BG6: =AY6*c_stroke_fatal+AZ6*c_stroke_major+BA6*c_stroke_minor+AT6*c_ich+AU6*c_major_bleed+BD6*c_mi_fatal+BE6*c_mi_nonfatal+AW6*c_tia+AX6*c_minor_bleed -> 0 | BH6: =dt*(BE6*dec_mi+BC6*dec_major_bleed+AX6*dec_minor_bleed+AW6*dec_tia) -> 0 | BI6: =H6*AK6+AY6+AT6-BB6+AU6-BC6+BD6 -> 0 | BJ6: =1-EXP(LN(1-E6)*hr_death_prior_stroke*dt) -> 0.019110191 | BK6: =I6*(1-BJ6) -> 0 | BL6: =(1-EXP(-r_stroke*F6*rr_stroke_prior*rr_asa_stroke*dt)) -> 0.014268505 | BM6: =(1-EXP(-r_ich*rr_asa_ich*dt)) -> 0.0010235777 | BN6: =(1-EXP(-r_mb*rr_asa_mb*dt)) -> 0.0095180967 | BO6: =(1-EXP(-r_mi*rr_asa_mi*dt)) -> 0.0021341352 | BP6: =(1-EXP(-r_tia*rr_asa_tia*dt)) -> 0.0031276457 | BQ6: =(1-EXP(-r_minor*rr_asa_minor*dt)) -> 0.027818195 | BR6: =BK6*BL6 -> 0 | BS6: =BK6*BM6 -> 0 | BT6: =BK6*BN6 -> 0 | BU6: =BK6*BO6 -> 0 | BV6: =BK6*BP6 -> 0 | BW6: =BK6*BQ6 -> 0 | BX6: =BR6*f_stroke_fatal_recur -> 0 | BY6: =BR6*(1-f_stroke_fatal_recur)*f_stroke_major -> 0 | BZ6: =BR6*(1-f_stroke_fatal_recur)*(1-f_stroke_major) -> 0 | CA6: =BS6*(1-f_bleed_fatal) -> 0 | CB6: =BT6*(1-f_bleed_fatal) -> 0 | CC6: =BU6*f_mi_fatal -> 0 | CD6: =BU6-CC6 -> 0 | CE6: =BK6-BR6-BS6-BT6-CC6 -> 0 | CF6: =BX6*c_stroke_fatal+BY6*c_stroke_major+BZ6*c_stroke_minor+BS6*c_ich+BT6*c_major_bleed+CC6*c_mi_fatal+CD6*c_mi_nonfatal+BV6*c_tia+BW6*c_minor_bleed -> 0 | CG6: =dt*(CD6*dec_mi+CB6*dec_major_bleed+BW6*dec_minor_bleed+BV6*dec_tia) -> 0 | CH6: =I6*BJ6+BX6+BS6-CA6+BT6-CB6+CC6 -> 0 | CI6: =1-EXP(LN(1-E6)*dt) -> 0.0083541048 | CJ6: =J6*(1-CI6) -> 0 | CK6: =(1-EXP(-r_stroke*F6*rr_asa_stroke*dt)) -> 0.0065111099 | CL6: =(1-EXP(-r_ich*rr_asa_ich*dt)) -> 0.0010235777 | CM6: =(1-EXP(-r_mb*rr_asa_mb*dt)) -> 0.0095180967 | CN6: =(1-EXP(-r_mi*rr_asa_mi*dt)) -> 0.0021341352 | CO6: =(1-EXP(-r_tia*rr_asa_tia*dt)) -> 0.0031276457 | CP6: =(1-EXP(-r_minor*rr_asa_minor*dt)) -> 0.027818195 | CQ6: =CJ6*CK6 -> 0 | CR6: =CJ6*CL6 -> 0 | CS6: =CJ6*CM6 -> 0 | CT6: =CJ6*CN6 -> 0 | CU6: =CJ6*CO6 -> 0 | CV6: =CJ6*CP6 -> 0 | CW6: =CQ6*f_stroke_fatal -> 0 | CX6: =CQ6*(1-f_stroke_fatal)*f_stroke_major -> 0 | CY6: =CQ6*(1-f_stroke_fatal)*(1-f_stroke_major) -> 0 | CZ6: =CR6*(1-f_bleed_fatal) -> 0 | DA6: =CS6*(1-f_bleed_fatal) -> 0 | DB6: =CT6*f_mi_fatal -> 0 | DC6: =CT6-DB6 -> 0 | DD6: =CJ6-CQ6-CR6-CS6-DB6 -> 0 | DE6: =CW6*c_stroke_fatal+CX6*c_stroke_major+CY6*c_stroke_minor+CR6*c_ich+CS6*c_major_bleed+DB6*c_mi_fatal+DC6*c_mi_nonfatal+CU6*c_tia+CV6*c_minor_bleed -> 0 | DF6: =dt*(DC6*dec_mi+DA6*dec_major_bleed+CV6*dec_minor_bleed+CU6*dec_tia) -> 0 | DG6: =J6*CI6+CW6+CR6-CZ6+CS6-DA6+DB6 -> 0 | DH6: =AG6 -> 0.97720131 | DI6: =AB6+AC6+BF6+BA6+BB6+BC6+CY6+CZ6 -> 0.003853075 | DJ6: =AA6+AZ6+BY6+CX6+CE6+BZ6+CA6+CB6 -> 0.0010139296 | DK6: =AD6+DD6+DA6 -> 0.0075884314 | DL6: =K6+AJ6+BI6+CH6+DG6 -> 0.01034325 | DM6: =SUM(DH6:DL6) -> 1 | DN6: =dt*(G6*Warfarin!$H$2+(H6+I6+J6)*c_aspirin) -> 96.057208 | DO6: =dt*(H6*c_lt_minor_stroke+I6*c_lt_major_stroke) -> 0 | DP6: =AH6+BG6+CF6+DE6 -> 282.50964 | DQ6: =DN6+DO6+DP6 -> 378.56685 | DR6: =dt*(G6*(u_af-dec_per_year_over_70*MAX(B6-ref_age,0))+H6*(u_minor_stroke-dec_per_year_over_70*MAX(B6-ref_age,0))+I6*(u_major_stroke-dec_per_year_over_70*MAX(B6-ref_age,0))+J6*(u_af-dec_per_year_over_70*MAX(B6-ref_age,0)))-AI6-BH6-CG6-DF6 -> 0.20209215 | DS6: =dt*(G6+H6+I6+J6) -> 0.25 | DT6: =DQ6*C6 -> 378.56685 | DU6: =DN6*C6 -> 96.057208 | DV6: =DP6*C6 -> 282.50964 | DW6: =DO6*C6 -> 0 | DX6: =DR6*C6 -> 0.20209215 | DY6: =DS6*C6 -> 0.25 | DZ6: =T6+AS6+BR6+CQ6 -> 0.0039906077 | EA6: =U6+AT6+BS6+CR6 -> 0.0019892696 | EB6: =V6+AU6+BT6+CS6 -> 0.0082843137 | EC6: =G6*dt*C6 -> 0.25
A7: 1 | B7: =start_age+A7*dt -> 70.25 | C7: =(1+disc_rate)^-(A7*dt) -> 0.99628477 | D7: =IF(A7*dt>=wane_start,(1-wane_decay)^(A7*dt-wane_start),1) -> 1 | E7: =MIN(p_nonvasc_death*MIN(EXP(gomp_int+gomp_slope*INT(B7)),1)/qx_ref,0.999) -> 0.033 | F7: =rr_stroke_per_decade^((B7-ref_age)/10) -> 1.0101882 | G7: =DH6 -> 0.97720131 | H7: =DI6 -> 0.003853075 | I7: =DJ6 -> 0.0010139296 | J7: =DK6 -> 0.0075884314 | K7: =DL6 -> 0.01034325 | L7: =1-EXP(LN(1-E7)*dt) -> 0.0083541048 | M7: =G7*(1-L7) -> 0.96903767 | N7: =IF(Warfarin!$B$2=1,EXP(LN(or_apx_stroke)*D7)*(1-EXP(-r_stroke*F7*dt))/(1-(1-EXP(-r_stroke*F7*dt))+EXP(LN(or_apx_stroke)*D7)*(1-EXP(-r_stroke*F7*dt))),(1-EXP(-r_stroke*F7*dt))) -> 0.0040651426 | O7: =IF(Warfarin!$B$2=1,EXP(LN(or_apx_ich)*D7)*(1-EXP(-r_ich*dt))/(1-(1-EXP(-r_ich*dt))+EXP(LN(or_apx_ich)*D7)*(1-EXP(-r_ich*dt))),(1-EXP(-r_ich*dt))) -> 0.0020060282 | P7: =IF(Warfarin!$B$2=1,EXP(LN(or_apx_mb)*D7)*(1-EXP(-r_mb*dt))/(1-(1-EXP(-r_mb*dt))+EXP(LN(or_apx_mb)*D7)*(1-EXP(-r_mb*dt))),(1-EXP(-r_mb*dt))) -> 0.0083541048 | Q7: =IF(Warfarin!$B$2=1,EXP(LN(or_apx_mi)*D7)*(1-EXP(-r_mi*dt))/(1-(1-EXP(-r_mi*dt))+EXP(LN(or_apx_mi)*D7)*(1-EXP(-r_mi*dt))),(1-EXP(-r_mi*dt))) -> 0.0015033869 | R7: =(1-EXP(-r_tia*dt)) -> 0.0020060282 | S7: =(1-EXP(-r_minor*dt)) -> 0.043793769 | T7: =M7*N7 -> 0.0039392763 | U7: =M7*O7 -> 0.0019439169 | V7: =M7*P7 -> 0.0080954422 | W7: =M7*Q7 -> 0.0014568385 | X7: =M7*R7 -> 0.0019439169 | Y7: =M7*S7 -> 0.042437812 | Z7: =T7*f_stroke_fatal -> 0.00093360848 | AA7: =T7*(1-f_stroke_fatal)*f_stroke_major -> 0.0010008874 | AB7: =T7*(1-f_stroke_fatal)*(1-f_stroke_major) -> 0.0020047804 | AC7: =U7*(1-f_bleed_fatal) -> 0.0017806278 | AD7: =V7*(1-f_bleed_fatal) -> 0.0074154251 | AE7: =W7*f_mi_fatal -> 0.00017627746 | AF7: =W7-AE7 -> 0.001280561 | AG7: =M7-T7-U7-V7-AE7 -> 0.95488276 | AH7: =Z7*c_stroke_fatal+AA7*c_stroke_major+AB7*c_stroke_minor+U7*c_ich+V7*c_major_bleed+AE7*c_mi_fatal+AF7*c_mi_nonfatal+X7*c_tia+Y7*c_minor_bleed -> 277.53374 | AI7: =dt*(AF7*dec_mi+AD7*dec_major_bleed+Y7*dec_minor_bleed+X7*dec_tia) -> 0.00039855106 | AJ7: =G7*L7+Z7+U7-AC7+V7-AD7+AE7 -> 0.010116834 | AK7: =1-EXP(LN(1-E7)*hr_death_prior_stroke*dt) -> 0.019110191 | AL7: =H7*(1-AK7) -> 0.003779442 | AM7: =(1-EXP(-r_stroke*F7*rr_stroke_prior*rr_asa_stroke*dt)) -> 0.014412823 | AN7: =(1-EXP(-r_ich*rr_asa_ich*dt)) -> 0.0010235777 | AO7: =(1-EXP(-r_mb*rr_asa_mb*dt)) -> 0.0095180967 | AP7: =(1-EXP(-r_mi*rr_asa_mi*dt)) -> 0.0021341352 | AQ7: =(1-EXP(-r_tia*rr_asa_tia*dt)) -> 0.0031276457 | AR7: =(1-EXP(-r_minor*rr_asa_minor*dt)) -> 0.027818195 | AS7: =AL7*AM7 -> 5.4472428e-05 | AT7: =AL7*AN7 -> 3.8685525e-06 | AU7: =AL7*AO7 -> 3.5973094e-05 | AV7: =AL7*AP7 -> 8.0658401e-06 | AW7: =AL7*AQ7 -> 1.1820755e-05 | AX7: =AL7*AR7 -> 0.00010513725 | AY7: =AS7*f_stroke_fatal_recur -> 2.0268646e-05 | AZ7: =AS7*(1-f_stroke_fatal_recur)*f_stroke_major -> 1.1389859e-05 | BA7: =AS7*(1-f_stroke_fatal_recur)*(1-f_stroke_major) -> 2.2813923e-05 | BB7: =AT7*(1-f_bleed_fatal) -> 3.5435941e-06 | BC7: =AU7*(1-f_bleed_fatal) -> 3.2951355e-05 | BD7: =AV7*f_mi_fatal -> 9.7596665e-07 | BE7: =AV7-BD7 -> 7.0898734e-06 | BF7: =AL7-AS7-AT7-AU7-BD7 -> 0.003684152 | BG7: =AY7*c_stroke_fatal+AZ7*c_stroke_major+BA7*c_stroke_minor+AT7*c_ich+AU7*c_major_bleed+BD7*c_mi_fatal+BE7*c_mi_nonfatal+AW7*c_tia+AX7*c_minor_bleed -> 2.3871128 | BH7: =dt*(BE7*dec_mi+BC7*dec_major_bleed+AX7*dec_minor_bleed+AW7*dec_tia) -> 1.6255202e-06 | BI7: =H7*AK7+AY7+AT7-BB7+AU7-BC7+BD7 -> 9.8224308e-05 | BJ7: =1-EXP(LN(1-E7)*hr_death_prior_stroke*dt) -> 0.019110191 | BK7: =I7*(1-BJ7) -> 0.00099455322 | BL7: =(1-EXP(-r_stroke*F7*rr_stroke_prior*rr_asa_stroke*dt)) -> 0.014412823 | BM7: =(1-EXP(-r_ich*rr_asa_ich*dt)) -> 0.0010235777 | BN7: =(1-EXP(-r_mb*rr_asa_mb*dt)) -> 0.0095180967 | BO7: =(1-EXP(-r_mi*rr_asa_mi*dt)) -> 0.0021341352 | BP7: =(1-EXP(-r_tia*rr_asa_tia*dt)) -> 0.0031276457 | BQ7: =(1-EXP(-r_minor*rr_asa_minor*dt)) -> 0.027818195 | BR7: =BK7*BL7 -> 1.4334319e-05 | BS7: =BK7*BM7 -> 1.0180025e-06 | BT7: =BK7*BN7 -> 9.4662538e-06 | BU7: =BK7*BO7 -> 2.122511e-06 | BV7: =BK7*BP7 -> 3.1106101e-06 | BW7: =BK7*BQ7 -> 2.7666676e-05 | BX7: =BR7*f_stroke_fatal_recur -> 5.3336569e-06 | BY7: =BR7*(1-f_stroke_fatal_recur)*f_stroke_major -> 2.9972206e-06 | BZ7: =BR7*(1-f_stroke_fatal_recur)*(1-f_stroke_major) -> 6.0034419e-06 | CA7: =BS7*(1-f_bleed_fatal) -> 9.3249027e-07 | CB7: =BT7*(1-f_bleed_fatal) -> 8.6710884e-06 | CC7: =BU7*f_mi_fatal -> 2.5682383e-07 | CD7: =BU7-CC7 -> 1.8656872e-06 | CE7: =BK7-BR7-BS7-BT7-CC7 -> 0.00096947782 | CF7: =BX7*c_stroke_fatal+BY7*c_stroke_major+BZ7*c_stroke_minor+BS7*c_ich+BT7*c_major_bleed+CC7*c_mi_fatal+CD7*c_mi_nonfatal+BV7*c_tia+BW7*c_minor_bleed -> 0.62816435 | CG7: =dt*(CD7*dec_mi+CB7*dec_major_bleed+BW7*dec_minor_bleed+BV7*dec_tia) -> 4.2775266e-07 | CH7: =I7*BJ7+BX7+BS7-CA7+BT7-CB7+CC7 -> 2.5847546e-05 | CI7: =1-EXP(LN(1-E7)*dt) -> 0.0083541048 | CJ7: =J7*(1-CI7) -> 0.0075250368 | CK7: =(1-EXP(-r_stroke*F7*rr_asa_stroke*dt)) -> 0.0065772277 | CL7: =(1-EXP(-r_ich*rr_asa_ich*dt)) -> 0.0010235777 | CM7: =(1-EXP(-r_mb*rr_asa_mb*dt)) -> 0.0095180967 | CN7: =(1-EXP(-r_mi*rr_asa_mi*dt)) -> 0.0021341352 | CO7: =(1-EXP(-r_tia*rr_asa_tia*dt)) -> 0.0031276457 | CP7: =(1-EXP(-r_minor*rr_asa_minor*dt)) -> 0.027818195 | CQ7: =CJ7*CK7 -> 4.949388e-05 | CR7: =CJ7*CL7 -> 7.7024597e-06 | CS7: =CJ7*CM7 -> 7.1624028e-05 | CT7: =CJ7*CN7 -> 1.6059446e-05 | CU7: =CJ7*CO7 -> 2.3535649e-05 | CV7: =CJ7*CP7 -> 0.00020933294 | CW7: =CQ7*f_stroke_fatal -> 1.173005e-05 | CX7: =CQ7*(1-f_stroke_fatal)*f_stroke_major -> 1.2575356e-05 | CY7: =CQ7*(1-f_stroke_fatal)*(1-f_stroke_major) -> 2.5188475e-05 | CZ7: =CR7*(1-f_bleed_fatal) -> 7.0554531e-06 | DA7: =CS7*(1-f_bleed_fatal) -> 6.560761e-05 | DB7: =CT7*f_mi_fatal -> 1.9431929e-06 | DC7: =CT7-DB7 -> 1.4116253e-05 | DD7: =CJ7-CQ7-CR7-CS7-DB7 -> 0.0073942732 | DE7: =CW7*c_stroke_fatal+CX7*c_stroke_major+CY7*c_stroke_minor+CR7*c_ich+CS7*c_major_bleed+DB7*c_mi_fatal+DC7*c_mi_nonfatal+CU7*c_tia+CV7*c_minor_bleed -> 2.8419899 | DF7: =dt*(DC7*dec_mi+DA7*dec_major_bleed+CV7*dec_minor_bleed+CU7*dec_tia) -> 3.2364829e-06 | DG7: =J7*CI7+CW7+CR7-CZ7+CS7-DA7+DB7 -> 8.3731218e-05 | DH7: =AG7 -> 0.95488276 | DI7: =AB7+AC7+BF7+BA7+BB7+BC7+CY7+CZ7 -> 0.007561113 | DJ7: =AA7+AZ7+BY7+CX7+CE7+BZ7+CA7+CB7 -> 0.0020129347 | DK7: =AD7+DD7+DA7 -> 0.014875306 | DL7: =K7+AJ7+BI7+CH7+DG7 -> 0.020667887 | DM7: =SUM(DH7:DL7) -> 1 | DN7: =dt*(G7*Warfarin!$H$2+(H7+I7+J7)*c_aspirin) -> 93.988795 | DO7: =dt*(H7*c_lt_minor_stroke+I7*c_lt_major_stroke) -> 17.035751 | DP7: =AH7+BG7+CF7+DE7 -> 283.391 | DQ7: =DN7+DO7+DP7 -> 394.41555 | DR7: =dt*(G7*(u_af-dec_per_year_over_70*MAX(B7-ref_age,0))+H7*(u_minor_stroke-dec_per_year_over_70*MAX(B7-ref_age,0))+I7*(u_major_stroke-dec_per_year_over_70*MAX(B7-ref_age,0))+J7*(u_af-dec_per_year_over_70*MAX(B7-ref_age,0)))-AI7-BH7-CG7-DF7 -> 0.1998049 | DS7: =dt*(G7+H7+I7+J7) -> 0.24741419 | DT7: =DQ7*C7 -> 392.9502 | DU7: =DN7*C7 -> 93.639605 | DV7: =DP7*C7 -> 282.33814 | DW7: =DO7*C7 -> 16.97246 | DX7: =DR7*C7 -> 0.19906258 | DY7: =DS7*C7 -> 0.24649499 | DZ7: =T7+AS7+BR7+CQ7 -> 0.0040575769 | EA7: =U7+AT7+BS7+CR7 -> 0.0019565059 | EB7: =V7+AU7+BT7+CS7 -> 0.0082125056 | EC7: =G7*dt*C7 -> 0.2433927
A8: 2 | B8: =start_age+A8*dt -> 70.5 | C8: =(1+disc_rate)^-(A8*dt) -> 0.99258333 | D8: =IF(A8*dt>=wane_start,(1-wane_decay)^(A8*dt-wane_start),1) -> 1 | E8: =MIN(p_nonvasc_death*MIN(EXP(gomp_int+gomp_slope*INT(B8)),1)/qx_ref,0.999) -> 0.033 | F8: =rr_stroke_per_decade^((B8-ref_age)/10) -> 1.0204802 | G8: =DH7 -> 0.95488276 | H8: =DI7 -> 0.007561113 | I8: =DJ7 -> 0.0020129347 | J8: =DK7 -> 0.014875306 | K8: =DL7 -> 0.020667887 | L8: =1-EXP(LN(1-E8)*dt) -> 0.0083541048 | M8: =G8*(1-L8) -> 0.94690557 | N8: =IF(Warfarin!$B$2=1,EXP(LN(or_apx_stroke)*D8)*(1-EXP(-r_stroke*F8*dt))/(1-(1-EXP(-r_stroke*F8*dt))+EXP(LN(or_apx_stroke)*D8)*(1-EXP(-r_stroke*F8*dt))),(1-EXP(-r_stroke*F8*dt))) -> 0.0041064738 | O8: =IF(Warfarin!$B$2=1,EXP(LN(or_apx_ich)*D8)*(1-EXP(-r_ich*dt))/(1-(1-EXP(-r_ich*dt))+EXP(LN(or_apx_ich)*D8)*(1-EXP(-r_ich*dt))),(1-EXP(-r_ich*dt))) -> 0.0020060282 | P8: =IF(Warfarin!$B$2=1,EXP(LN(or_apx_mb)*D8)*(1-EXP(-r_mb*dt))/(1-(1-EXP(-r_mb*dt))+EXP(LN(or_apx_mb)*D8)*(1-EXP(-r_mb*dt))),(1-EXP(-r_mb*dt))) -> 0.0083541048 | Q8: =IF(Warfarin!$B$2=1,EXP(LN(or_apx_mi)*D8)*(1-EXP(-r_mi*dt))/(1-(1-EXP(-r_mi*dt))+EXP(LN(or_apx_mi)*D8)*(1-EXP(-r_mi*dt))),(1-EXP(-r_mi*dt))) -> 0.0015033869 | R8: =(1-EXP(-r_tia*dt)) -> 0.0020060282 | S8: =(1-EXP(-r_minor*dt)) -> 0.043793769 | T8: =M8*N8 -> 0.0038884429 | U8: =M8*O8 -> 0.0018995192 | V8: =M8*P8 -> 0.0079105483 | W8: =M8*Q8 -> 0.0014235654 | X8: =M8*R8 -> 0.0018995192 | Y8: =M8*S8 -> 0.041468564 | Z8: =T8*f_stroke_fatal -> 0.00092156097 | AA8: =T8*(1-f_stroke_fatal)*f_stroke_major -> 0.00098797169 | AB8: =T8*(1-f_stroke_fatal)*(1-f_stroke_major) -> 0.0019789103 | AC8: =U8*(1-f_bleed_fatal) -> 0.0017399596 | AD8: =V8*(1-f_bleed_fatal) -> 0.0072460623 | AE8: =W8*f_mi_fatal -> 0.00017225141 | AF8: =W8-AE8 -> 0.001251314 | AG8: =M8-T8-U8-V8-AE8 -> 0.93303481 | AH8: =Z8*c_stroke_fatal+AA8*c_stroke_major+AB8*c_stroke_minor+U8*c_ich+V8*c_major_bleed+AE8*c_mi_fatal+AF8*c_mi_nonfatal+X8*c_tia+Y8*c_minor_bleed -> 272.64108 | AI8: =dt*(AF8*dec_mi+AD8*dec_major_bleed+Y8*dec_minor_bleed+X8*dec_tia) -> 0.00038944845 | AJ8: =G8*L8+Z8+U8-AC8+V8-AD8+AE8 -> 0.0098950487 | AK8: =1-EXP(LN(1-E8)*hr_death_prior_stroke*dt) -> 0.019110191 | AL8: =H8*(1-AK8) -> 0.0074166187 | AM8: =(1-EXP(-r_stroke*F8*rr_stroke_prior*rr_asa_stroke*dt)) -> 0.014558589 | AN8: =(1-EXP(-r_ich*rr_asa_ich*dt)) -> 0.0010235777 | AO8: =(1-EXP(-r_mb*rr_asa_mb*dt)) -> 0.0095180967 | AP8: =(1-EXP(-r_mi*rr_asa_mi*dt)) -> 0.0021341352 | AQ8: =(1-EXP(-r_tia*rr_asa_tia*dt)) -> 0.0031276457 | AR8: =(1-EXP(-r_minor*rr_asa_minor*dt)) -> 0.027818195 | AS8: =AL8*AM8 -> 0.0001079755 | AT8: =AL8*AN8 -> 7.5914854e-06 | AU8: =AL8*AO8 -> 7.0592094e-05 | AV8: =AL8*AP8 -> 1.5828067e-05 | AW8: =AL8*AQ8 -> 2.3196555e-05 | AX8: =AL8*AR8 -> 0.00020631695 | AY8: =AS8*f_stroke_fatal_recur -> 4.0176605e-05 | AZ8: =AS8*(1-f_stroke_fatal_recur)*f_stroke_major -> 2.2577033e-05 | BA8: =AS8*(1-f_stroke_fatal_recur)*(1-f_stroke_major) -> 4.5221866e-05 | BB8: =AT8*(1-f_bleed_fatal) -> 6.9538006e-06 | BC8: =AU8*(1-f_bleed_fatal) -> 6.4662358e-05 | BD8: =AV8*f_mi_fatal -> 1.9151961e-06 | BE8: =AV8-BD8 -> 1.3912871e-05 | BF8: =AL8-AS8-AT8-AU8-BD8 -> 0.0072285444 | BG8: =AY8*c_stroke_fatal+AZ8*c_stroke_major+BA8*c_stroke_minor+AT8*c_ich+AU8*c_major_bleed+BD8*c_mi_fatal+BE8*c_mi_nonfatal+AW8*c_tia+AX8*c_minor_bleed -> 4.7216457 | BH8: =dt*(BE8*dec_mi+BC8*dec_major_bleed+AX8*dec_minor_bleed+AW8*dec_tia) -> 3.1898528e-06 | BI8: =H8*AK8+AY8+AT8-BB8+AU8-BC8+BD8 -> 0.00019315353 | BJ8: =1-EXP(LN(1-E8)*hr_death_prior_stroke*dt) -> 0.019110191 | BK8: =I8*(1-BJ8) -> 0.0019744671 | BL8: =(1-EXP(-r_stroke*F8*rr_stroke_prior*rr_asa_stroke*dt)) -> 0.014558589 | BM8: =(1-EXP(-r_ich*rr_asa_ich*dt)) -> 0.0010235777 | BN8: =(1-EXP(-r_mb*rr_asa_mb*dt)) -> 0.0095180967 | BO8: =(1-EXP(-r_mi*rr_asa_mi*dt)) -> 0.0021341352 | BP8: =(1-EXP(-r_tia*rr_asa_tia*dt)) -> 0.0031276457 | BQ8: =(1-EXP(-r_minor*rr_asa_minor*dt)) -> 0.027818195 | BR8: =BK8*BL8 -> 2.8745455e-05 | BS8: =BK8*BM8 -> 2.0210204e-06 | BT8: =BK8*BN8 -> 1.8793169e-05 | BU8: =BK8*BO8 -> 4.2137797e-06 | BV8: =BK8*BP8 -> 6.1754334e-06 | BW8: =BK8*BQ8 -> 5.4926111e-05 | BX8: =BR8*f_stroke_fatal_recur -> 1.0695896e-05 | BY8: =BR8*(1-f_stroke_fatal_recur)*f_stroke_major -> 6.0105031e-06 | BZ8: =BR8*(1-f_stroke_fatal_recur)*(1-f_stroke_major) -> 1.2039056e-05 | CA8: =BS8*(1-f_bleed_fatal) -> 1.8512547e-06 | CB8: =BT8*(1-f_bleed_fatal) -> 1.7214543e-05 | CC8: =BU8*f_mi_fatal -> 5.0986734e-07 | CD8: =BU8-CC8 -> 3.7039123e-06 | CE8: =BK8-BR8-BS8-BT8-CC8 -> 0.0019243976 | CF8: =BX8*c_stroke_fatal+BY8*c_stroke_major+BZ8*c_stroke_minor+BS8*c_ich+BT8*c_major_bleed+CC8*c_mi_fatal+CD8*c_mi_nonfatal+BV8*c_tia+BW8*c_minor_bleed -> 1.257006 | CG8: =dt*(CD8*dec_mi+CB8*dec_major_bleed+BW8*dec_minor_bleed+BV8*dec_tia) -> 8.4920901e-07 | CH8: =I8*BJ8+BX8+BS8-CA8+BT8-CB8+CC8 -> 5.1421721e-05 | CI8: =1-EXP(LN(1-E8)*dt) -> 0.0083541048 | CJ8: =J8*(1-CI8) -> 0.014751036 | CK8: =(1-EXP(-r_stroke*F8*rr_asa_stroke*dt)) -> 0.0066440145 | CL8: =(1-EXP(-r_ich*rr_asa_ich*dt)) -> 0.0010235777 | CM8: =(1-EXP(-r_mb*rr_asa_mb*dt)) -> 0.0095180967 | CN8: =(1-EXP(-r_mi*rr_asa_mi*dt)) -> 0.0021341352 | CO8: =(1-EXP(-r_tia*rr_asa_tia*dt)) -> 0.0031276457 | CP8: =(1-EXP(-r_minor*rr_asa_minor*dt)) -> 0.027818195 | CQ8: =CJ8*CK8 -> 9.8006098e-05 | CR8: =CJ8*CL8 -> 1.5098831e-05 | CS8: =CJ8*CM8 -> 0.00014040179 | CT8: =CJ8*CN8 -> 3.1480705e-05 | CU8: =CJ8*CO8 -> 4.6136014e-05 | CV8: =CJ8*CP8 -> 0.0004103472 | CW8: =CQ8*f_stroke_fatal -> 2.3227445e-05 | CX8: =CQ8*(1-f_stroke_fatal)*f_stroke_major -> 2.4901291e-05 | CY8: =CQ8*(1-f_stroke_fatal)*(1-f_stroke_major) -> 4.9877361e-05 | CZ8: =CR8*(1-f_bleed_fatal) -> 1.3830529e-05 | DA8: =CS8*(1-f_bleed_fatal) -> 0.00012860804 | DB8: =CT8*f_mi_fatal -> 3.8091653e-06 | DC8: =CT8-DB8 -> 2.767154e-05 | DD8: =CJ8-CQ8-CR8-CS8-DB8 -> 0.01449372 | DE8: =CW8*c_stroke_fatal+CX8*c_stroke_major+CY8*c_stroke_minor+CR8*c_ich+CS8*c_major_bleed+DB8*c_mi_fatal+DC8*c_mi_nonfatal+CU8*c_tia+CV8*c_minor_bleed -> 5.6074419 | DF8: =dt*(DC8*dec_mi+DA8*dec_major_bleed+CV8*dec_minor_bleed+CU8*dec_tia) -> 6.3443512e-06 | DG8: =J8*CI8+CW8+CR8-CZ8+CS8-DA8+DB8 -> 0.00016436853 | DH8: =AG8 -> 0.93303481 | DI8: =AB8+AC8+BF8+BA8+BB8+BC8+CY8+CZ8 -> 0.01112796 | DJ8: =AA8+AZ8+BY8+CX8+CE8+BZ8+CA8+CB8 -> 0.002996963 | DK8: =AD8+DD8+DA8 -> 0.021868391 | DL8: =K8+AJ8+BI8+CH8+DG8 -> 0.03097188 | DM8: =SUM(DH8:DL8) -> 1 | DN8: =dt*(G8*Warfarin!$H$2+(H8+I8+J8)*c_aspirin) -> 91.961998 | DO8: =dt*(H8*c_lt_minor_stroke+I8*c_lt_major_stroke) -> 33.581981 | DP8: =AH8+BG8+CF8+DE8 -> 284.22718 | DQ8: =DN8+DO8+DP8 -> 409.77116 | DR8: =dt*(G8*(u_af-dec_per_year_over_70*MAX(B8-ref_age,0))+H8*(u_minor_stroke-dec_per_year_over_70*MAX(B8-ref_age,0))+I8*(u_major_stroke-dec_per_year_over_70*MAX(B8-ref_age,0))+J8*(u_af-dec_per_year_over_70*MAX(B8-ref_age,0)))-AI8-BH8-CG8-DF8 -> 0.19752576 | DS8: =dt*(G8+H8+I8+J8) -> 0.24483303 | DT8: =DQ8*C8 -> 406.73202 | DU8: =DN8*C8 -> 91.279946 | DV8: =DP8*C8 -> 282.11916 | DW8: =DO8*C8 -> 33.332915 | DX8: =DR8*C8 -> 0.19606078 | DY8: =DS8*C8 -> 0.24301718 | DZ8: =T8+AS8+BR8+CQ8 -> 0.00412317 | EA8: =U8+AT8+BS8+CR8 -> 0.0019242306 | EB8: =V8+AU8+BT8+CS8 -> 0.0081403354 | EC8: =G8*dt*C8 -> 0.23695018
A9: 3 | B9: =start_age+A9*dt -> 70.75 | C9: =(1+disc_rate)^-(A9*dt) -> 0.98889565 | D9: =IF(A9*dt>=wane_start,(1-wane_decay)^(A9*dt-wane_start),1) -> 1 | E9: =MIN(p_nonvasc_death*MIN(EXP(gomp_int+gomp_slope*INT(B9)),1)/qx_ref,0.999) -> 0.033 | F9: =rr_stroke_per_decade^((B9-ref_age)/10) -> 1.030877 | G9: =DH8 -> 0.93303481 | H9: =DI8 -> 0.01112796 | I9: =DJ8 -> 0.002996963 | J9: =DK8 -> 0.021868391 | K9: =DL8 -> 0.03097188 | L9: =1-EXP(LN(1-E9)*dt) -> 0.0083541048 | M9: =G9*(1-L9) -> 0.92524014 | N9: =IF(Warfarin!$B$2=1,EXP(LN(or_apx_stroke)*D9)*(1-EXP(-r_stroke*F9*dt))/(1-(1-EXP(-r_stroke*F9*dt))+EXP(LN(or_apx_stroke)*D9)*(1-EXP(-r_stroke*F9*dt))),(1-EXP(-r_stroke*F9*dt))) -> 0.0041482244 | O9: =IF(Warfarin!$B$2=1,EXP(LN(or_apx_ich)*D9)*(1-EXP(-r_ich*dt))/(1-(1-EXP(-r_ich*dt))+EXP(LN(or_apx_ich)*D9)*(1-EXP(-r_ich*dt))),(1-EXP(-r_ich*dt))) -> 0.0020060282 | P9: =IF(Warfarin!$B$2=1,EXP(LN(or_apx_mb)*D9)*(1-EXP(-r_mb*dt))/(1-(1-EXP(-r_mb*dt))+EXP(LN(or_apx_mb)*D9)*(1-EXP(-r_mb*dt))),(1-EXP(-r_mb*dt))) -> 0.0083541048 | Q9: =IF(Warfarin!$B$2=1,EXP(LN(or_apx_mi)*D9)*(1-EXP(-r_mi*dt))/(1-(1-EXP(-r_mi*dt))+EXP(LN(or_apx_mi)*D9)*(1-EXP(-r_mi*dt))),(1-EXP(-r_mi*dt))) -> 0.0015033869 | R9: =(1-EXP(-r_tia*dt)) -> 0.0020060282 | S9: =(1-EXP(-r_minor*dt)) -> 0.043793769 | T9: =M9*N9 -> 0.0038381037 | U9: =M9*O9 -> 0.0018560578 | V9: =M9*P9 -> 0.007729553 | W9: =M9*Q9 -> 0.0013909939 | X9: =M9*R9 -> 0.0018560578 | Y9: =M9*S9 -> 0.040519753 | Z9: =T9*f_stroke_fatal -> 0.00090963058 | AA9: =T9*(1-f_stroke_fatal)*f_stroke_major -> 0.00097518155 | AB9: =T9*(1-f_stroke_fatal)*(1-f_stroke_major) -> 0.0019532916 | AC9: =U9*(1-f_bleed_fatal) -> 0.0017001489 | AD9: =V9*(1-f_bleed_fatal) -> 0.0070802706 | AE9: =W9*f_mi_fatal -> 0.00016831026 | AF9: =W9-AE9 -> 0.0012226836 | AG9: =M9-T9-U9-V9-AE9 -> 0.91164811 | AH9: =Z9*c_stroke_fatal+AA9*c_stroke_major+AB9*c_stroke_minor+U9*c_ich+V9*c_major_bleed+AE9*c_mi_fatal+AF9*c_mi_nonfatal+X9*c_tia+Y9*c_minor_bleed -> 267.83025 | AI9: =dt*(AF9*dec_mi+AD9*dec_major_bleed+Y9*dec_minor_bleed+X9*dec_tia) -> 0.00038053777 | AJ9: =G9*L9+Z9+U9-AC9+V9-AD9+AE9 -> 0.0096778027 | AK9: =1-EXP(LN(1-E9)*hr_death_prior_stroke*dt) -> 0.019110191 | AL9: =H9*(1-AK9) -> 0.010915303 | AM9: =(1-EXP(-r_stroke*F9*rr_stroke_prior*rr_asa_stroke*dt)) -> 0.014705819 | AN9: =(1-EXP(-r_ich*rr_asa_ich*dt)) -> 0.0010235777 | AO9: =(1-EXP(-r_mb*rr_asa_mb*dt)) -> 0.0095180967 | AP9: =(1-EXP(-r_mi*rr_asa_mi*dt)) -> 0.0021341352 | AQ9: =(1-EXP(-r_tia*rr_asa_tia*dt)) -> 0.0031276457 | AR9: =(1-EXP(-r_minor*rr_asa_minor*dt)) -> 0.027818195 | AS9: =AL9*AM9 -> 0.00016051846 | AT9: =AL9*AN9 -> 1.117266e-05 | AU9: =AL9*AO9 -> 0.00010389291 | AV9: =AL9*AP9 -> 2.3294732e-05 | AW9: =AL9*AQ9 -> 3.4139199e-05 | AX9: =AL9*AR9 -> 0.00030364402 | AY9: =AS9*f_stroke_fatal_recur -> 5.9727315e-05 | AZ9: =AS9*(1-f_stroke_fatal_recur)*f_stroke_major -> 3.3563452e-05 | BA9: =AS9*(1-f_stroke_fatal_recur)*(1-f_stroke_major) -> 6.7227696e-05 | BB9: =AT9*(1-f_bleed_fatal) -> 1.0234157e-05 | BC9: =AU9*(1-f_bleed_fatal) -> 9.5165903e-05 | BD9: =AV9*f_mi_fatal -> 2.8186625e-06 | BE9: =AV9-BD9 -> 2.0476069e-05 | BF9: =AL9-AS9-AT9-AU9-BD9 -> 0.0106369 | BG9: =AY9*c_stroke_fatal+AZ9*c_stroke_major+BA9*c_stroke_minor+AT9*c_ich+AU9*c_major_bleed+BD9*c_mi_fatal+BE9*c_mi_nonfatal+AW9*c_tia+AX9*c_minor_bleed -> 7.0044251 | BH9: =dt*(BE9*dec_mi+BC9*dec_major_bleed+AX9*dec_minor_bleed+AW9*dec_tia) -> 4.6946204e-06 | BI9: =H9*AK9+AY9+AT9-BB9+AU9-BC9+BD9 -> 0.00028486893 | BJ9: =1-EXP(LN(1-E9)*hr_death_prior_stroke*dt) -> 0.019110191 | BK9: =I9*(1-BJ9) -> 0.0029396904 | BL9: =(1-EXP(-r_stroke*F9*rr_stroke_prior*rr_asa_stroke*dt)) -> 0.014705819 | BM9: =(1-EXP(-r_ich*rr_asa_ich*dt)) -> 0.0010235777 | BN9: =(1-EXP(-r_mb*rr_asa_mb*dt)) -> 0.0095180967 | BO9: =(1-EXP(-r_mi*rr_asa_mi*dt)) -> 0.0021341352 | BP9: =(1-EXP(-r_tia*rr_asa_tia*dt)) -> 0.0031276457 | BQ9: =(1-EXP(-r_minor*rr_asa_minor*dt)) -> 0.027818195 | BR9: =BK9*BL9 -> 4.3230554e-05 | BS9: =BK9*BM9 -> 3.0090015e-06 | BT9: =BK9*BN9 -> 2.7980258e-05 | BU9: =BK9*BO9 -> 6.2736967e-06 | BV9: =BK9*BP9 -> 9.19431e-06 | BW9: =BK9*BQ9 -> 8.1776882e-05 | BX9: =BR9*f_stroke_fatal_recur -> 1.6085657e-05 | BY9: =BR9*(1-f_stroke_fatal_recur)*f_stroke_major -> 9.0392508e-06 | BZ9: =BR9*(1-f_stroke_fatal_recur)*(1-f_stroke_major) -> 1.8105646e-05 | CA9: =BS9*(1-f_bleed_fatal) -> 2.7562454e-06 | CB9: =BT9*(1-f_bleed_fatal) -> 2.5629916e-05 | CC9: =BU9*f_mi_fatal -> 7.591173e-07 | CD9: =BU9-CC9 -> 5.5145794e-06 | CE9: =BK9-BR9-BS9-BT9-CC9 -> 0.0028647115 | CF9: =BX9*c_stroke_fatal+BY9*c_stroke_major+BZ9*c_stroke_minor+BS9*c_ich+BT9*c_major_bleed+CC9*c_mi_fatal+CD9*c_mi_nonfatal+BV9*c_tia+BW9*c_minor_bleed -> 1.8864196 | CG9: =dt*(CD9*dec_mi+CB9*dec_major_bleed+BW9*dec_minor_bleed+BV9*dec_tia) -> 1.264347e-06 | CH9: =I9*BJ9+BX9+BS9-CA9+BT9-CB9+CC9 -> 7.6720405e-05 | CI9: =1-EXP(LN(1-E9)*dt) -> 0.0083541048 | CJ9: =J9*(1-CI9) -> 0.0216857 | CK9: =(1-EXP(-r_stroke*F9*rr_asa_stroke*dt)) -> 0.0067114773 | CL9: =(1-EXP(-r_ich*rr_asa_ich*dt)) -> 0.0010235777 | CM9: =(1-EXP(-r_mb*rr_asa_mb*dt)) -> 0.0095180967 | CN9: =(1-EXP(-r_mi*rr_asa_mi*dt)) -> 0.0021341352 | CO9: =(1-EXP(-r_tia*rr_asa_tia*dt)) -> 0.0031276457 | CP9: =(1-EXP(-r_minor*rr_asa_minor*dt)) -> 0.027818195 | CQ9: =CJ9*CK9 -> 0.00014554308 | CR9: =CJ9*CL9 -> 2.2196998e-05 | CS9: =CJ9*CM9 -> 0.00020640659 | CT9: =CJ9*CN9 -> 4.6280214e-05 | CU9: =CJ9*CO9 -> 6.7825184e-05 | CV9: =CJ9*CP9 -> 0.00060325702 | CW9: =CQ9*f_stroke_fatal -> 3.449371e-05 | CX9: =CQ9*(1-f_stroke_fatal)*f_stroke_major -> 3.697944e-05 | CY9: =CQ9*(1-f_stroke_fatal)*(1-f_stroke_major) -> 7.406993e-05 | CZ9: =CR9*(1-f_bleed_fatal) -> 2.033245e-05 | DA9: =CS9*(1-f_bleed_fatal) -> 0.00018906843 | DB9: =CT9*f_mi_fatal -> 5.5999059e-06 | DC9: =CT9-DB9 -> 4.0680308e-05 | DD9: =CJ9-CQ9-CR9-CS9-DB9 -> 0.021305953 | DE9: =CW9*c_stroke_fatal+CX9*c_stroke_major+CY9*c_stroke_minor+CR9*c_ich+CS9*c_major_bleed+DB9*c_mi_fatal+DC9*c_mi_nonfatal+CU9*c_tia+CV9*c_minor_bleed -> 8.2976305 | DF9: =dt*(DC9*dec_mi+DA9*dec_major_bleed+CV9*dec_minor_bleed+CU9*dec_tia) -> 9.3269174e-06 | DG9: =J9*CI9+CW9+CR9-CZ9+CS9-DA9+DB9 -> 0.00024198714 | DH9: =AG9 -> 0.91164811 | DI9: =AB9+AC9+BF9+BA9+BB9+BC9+CY9+CZ9 -> 0.014557371 | DJ9: =AA9+AZ9+BY9+CX9+CE9+BZ9+CA9+CB9 -> 0.003965967 | DK9: =AD9+DD9+DA9 -> 0.028575292 | DL9: =K9+AJ9+BI9+CH9+DG9 -> 0.041253259 | DM9: =SUM(DH9:DL9) -> 1 | DN9: =dt*(G9*Warfarin!$H$2+(H9+I9+J9)*c_aspirin) -> 89.976013 | DO9: =dt*(H9*c_lt_minor_stroke+I9*c_lt_major_stroke) -> 49.648746 | DP9: =AH9+BG9+CF9+DE9 -> 285.01872 | DQ9: =DN9+DO9+DP9 -> 424.64348 | DR9: =dt*(G9*(u_af-dec_per_year_over_70*MAX(B9-ref_age,0))+H9*(u_minor_stroke-dec_per_year_over_70*MAX(B9-ref_age,0))+I9*(u_major_stroke-dec_per_year_over_70*MAX(B9-ref_age,0))+J9*(u_af-dec_per_year_over_70*MAX(B9-ref_age,0)))-AI9-BH9-CG9-DF9 -> 0.19525507 | DS9: =dt*(G9+H9+I9+J9) -> 0.24225703 | DT9: =DQ9*C9 -> 419.9281 | DU9: =DN9*C9 -> 88.976889 | DV9: =DP9*C9 -> 281.85378 | DW9: =DO9*C9 -> 49.097429 | DX9: =DR9*C9 -> 0.19308689 | DY9: =DS9*C9 -> 0.23956692 | DZ9: =T9+AS9+BR9+CQ9 -> 0.0041873958 | EA9: =U9+AT9+BS9+CR9 -> 0.0018924364 | EB9: =V9+AU9+BT9+CS9 -> 0.0080678328 | EC9: =G9*dt*C9 -> 0.23066852
A10: 4 | B10: =start_age+A10*dt -> 71 | C10: =(1+disc_rate)^-(A10*dt) -> 0.98522167 | D10: =IF(A10*dt>=wane_start,(1-wane_decay)^(A10*dt-wane_start),1) -> 1 | E10: =MIN(p_nonvasc_death*MIN(EXP(gomp_int+gomp_slope*INT(B10)),1)/qx_ref,0.999) -> 0.036640021 | F10: =rr_stroke_per_decade^((B10-ref_age)/10) -> 1.0413797 | G10: =DH9 -> 0.91164811 | H10: =DI9 -> 0.014557371 | I10: =DJ9 -> 0.003965967 | J10: =DK9 -> 0.028575292 | K10: =DL9 -> 0.041253259 | L10: =1-EXP(LN(1-E10)*dt) -> 0.0092886235 | M10: =G10*(1-L10) -> 0.90318016 | N10: =IF(Warfarin!$B$2=1,EXP(LN(or_apx_stroke)*D10)*(1-EXP(-r_stroke*F10*dt))/(1-(1-EXP(-r_stroke*F10*dt))+EXP(LN(or_apx_stroke)*D10)*(1-EXP(-r_stroke*F10*dt))),(1-EXP(-r_stroke*F10*dt))) -> 0.0041903986 | O10: =IF(Warfarin!$B$2=1,EXP(LN(or_apx_ich)*D10)*(1-EXP(-r_ich*dt))/(1-(1-EXP(-r_ich*dt))+EXP(LN(or_apx_ich)*D10)*(1-EXP(-r_ich*dt))),(1-EXP(-r_ich*dt))) -> 0.0020060282 | P10: =IF(Warfarin!$B$2=1,EXP(LN(or_apx_mb)*D10)*(1-EXP(-r_mb*dt))/(1-(1-EXP(-r_mb*dt))+EXP(LN(or_apx_mb)*D10)*(1-EXP(-r_mb*dt))),(1-EXP(-r_mb*dt))) -> 0.0083541048 | Q10: =IF(Warfarin!$B$2=1,EXP(LN(or_apx_mi)*D10)*(1-EXP(-r_mi*dt))/(1-(1-EXP(-r_mi*dt))+EXP(LN(or_apx_mi)*D10)*(1-EXP(-r_mi*dt))),(1-EXP(-r_mi*dt))) -> 0.0015033869 | R10: =(1-EXP(-r_tia*dt)) -> 0.0020060282 | S10: =(1-EXP(-r_minor*dt)) -> 0.043793769 | T10: =M10*N10 -> 0.0037846848 | U10: =M10*O10 -> 0.0018118048 | V10: =M10*P10 -> 0.0075452616 | W10: =M10*Q10 -> 0.0013578292 | X10: =M10*R10 -> 0.0018118048 | Y10: =M10*S10 -> 0.039553663 | Z10: =T10*f_stroke_fatal -> 0.00089697031 | AA10: =T10*(1-f_stroke_fatal)*f_stroke_major -> 0.00096160894 | AB10: =T10*(1-f_stroke_fatal)*(1-f_stroke_major) -> 0.0019261056 | AC10: =U10*(1-f_bleed_fatal) -> 0.0016596132 | AD10: =V10*(1-f_bleed_fatal) -> 0.0069114597 | AE10: =W10*f_mi_fatal -> 0.00016429733 | AF10: =W10-AE10 -> 0.0011935318 | AG10: =M10-T10-U10-V10-AE10 -> 0.88987411 | AH10: =Z10*c_stroke_fatal+AA10*c_stroke_major+AB10*c_stroke_minor+U10*c_ich+V10*c_major_bleed+AE10*c_mi_fatal+AF10*c_mi_nonfatal+X10*c_tia+Y10*c_minor_bleed -> 262.85189 | AI10: =dt*(AF10*dec_mi+AD10*dec_major_bleed+Y10*dec_minor_bleed+X10*dec_tia) -> 0.00037146482 | AJ10: =G10*L10+Z10+U10-AC10+V10-AD10+AE10 -> 0.010315217 | AK10: =1-EXP(LN(1-E10)*hr_death_prior_stroke*dt) -> 0.021234968 | AL10: =H10*(1-AK10) -> 0.014248245 | AM10: =(1-EXP(-r_stroke*F10*rr_stroke_prior*rr_asa_stroke*dt)) -> 0.014854526 | AN10: =(1-EXP(-r_ich*rr_asa_ich*dt)) -> 0.0010235777 | AO10: =(1-EXP(-r_mb*rr_asa_mb*dt)) -> 0.0095180967 | AP10: =(1-EXP(-r_mi*rr_asa_mi*dt)) -> 0.0021341352 | AQ10: =(1-EXP(-r_tia*rr_asa_tia*dt)) -> 0.0031276457 | AR10: =(1-EXP(-r_minor*rr_asa_minor*dt)) -> 0.027818195 | AS10: =AL10*AM10 -> 0.00021165093 | AT10: =AL10*AN10 -> 1.4584186e-05 | AU10: =AL10*AO10 -> 0.00013561618 | AV10: =AL10*AP10 -> 3.0407682e-05 | AW10: =AL10*AQ10 -> 4.4563463e-05 | AX10: =AL10*AR10 -> 0.00039636047 | AY10: =AS10*f_stroke_fatal_recur -> 7.8753194e-05 | AZ10: =AS10*(1-f_stroke_fatal_recur)*f_stroke_major -> 4.4254946e-05 | BA10: =AS10*(1-f_stroke_fatal_recur)*(1-f_stroke_major) -> 8.8642789e-05 | BB10: =AT10*(1-f_bleed_fatal) -> 1.3359114e-05 | BC10: =AU10*(1-f_bleed_fatal) -> 0.00012422442 | BD10: =AV10*f_mi_fatal -> 3.6793295e-06 | BE10: =AV10-BD10 -> 2.6728352e-05 | BF10: =AL10-AS10-AT10-AU10-BD10 -> 0.013882715 | BG10: =AY10*c_stroke_fatal+AZ10*c_stroke_major+BA10*c_stroke_minor+AT10*c_ich+AU10*c_major_bleed+BD10*c_mi_fatal+BE10*c_mi_nonfatal+AW10*c_tia+AX10*c_minor_bleed -> 9.216253 | BH10: =dt*(BE10*dec_mi+BC10*dec_major_bleed+AX10*dec_minor_bleed+AW10*dec_tia) -> 6.1281033e-06 | BI10: =H10*AK10+AY10+AT10-BB10+AU10-BC10+BD10 -> 0.00040417465 | BJ10: =1-EXP(LN(1-E10)*hr_death_prior_stroke*dt) -> 0.021234968 | BK10: =I10*(1-BJ10) -> 0.0038817498 | BL10: =(1-EXP(-r_stroke*F10*rr_stroke_prior*rr_asa_stroke*dt)) -> 0.014854526 | BM10: =(1-EXP(-r_ich*rr_asa_ich*dt)) -> 0.0010235777 | BN10: =(1-EXP(-r_mb*rr_asa_mb*dt)) -> 0.0095180967 | BO10: =(1-EXP(-r_mi*rr_asa_mi*dt)) -> 0.0021341352 | BP10: =(1-EXP(-r_tia*rr_asa_tia*dt)) -> 0.0031276457 | BQ10: =(1-EXP(-r_minor*rr_asa_minor*dt)) -> 0.027818195 | BR10: =BK10*BL10 -> 5.7661553e-05 | BS10: =BK10*BM10 -> 3.9732725e-06 | BT10: =BK10*BN10 -> 3.694687e-05 | BU10: =BK10*BO10 -> 8.2841788e-06 | BV10: =BK10*BP10 -> 1.2140738e-05 | BW10: =BK10*BQ10 -> 0.00010798327 | BX10: =BR10*f_stroke_fatal_recur -> 2.1455287e-05 | BY10: =BR10*(1-f_stroke_fatal_recur)*f_stroke_major -> 1.2056686e-05 | BZ10: =BR10*(1-f_stroke_fatal_recur)*(1-f_stroke_major) -> 2.4149579e-05 | CA10: =BS10*(1-f_bleed_fatal) -> 3.6395176e-06 | CB10: =BT10*(1-f_bleed_fatal) -> 3.3843333e-05 | CC10: =BU10*f_mi_fatal -> 1.0023856e-06 | CD10: =BU10-CC10 -> 7.2817931e-06 | CE10: =BK10-BR10-BS10-BT10-CC10 -> 0.0037821657 | CF10: =BX10*c_stroke_fatal+BY10*c_stroke_major+BZ10*c_stroke_minor+BS10*c_ich+BT10*c_major_bleed+CC10*c_mi_fatal+CD10*c_mi_nonfatal+BV10*c_tia+BW10*c_minor_bleed -> 2.5108487 | CG10: =dt*(CD10*dec_mi+CB10*dec_major_bleed+BW10*dec_minor_bleed+BV10*dec_tia) -> 1.6695223e-06 | CH10: =I10*BJ10+BX10+BS10-CA10+BT10-CB10+CC10 -> 0.00011011215 | CI10: =1-EXP(LN(1-E10)*dt) -> 0.0092886235 | CJ10: =J10*(1-CI10) -> 0.028309867 | CK10: =(1-EXP(-r_stroke*F10*rr_asa_stroke*dt)) -> 0.0067796227 | CL10: =(1-EXP(-r_ich*rr_asa_ich*dt)) -> 0.0010235777 | CM10: =(1-EXP(-r_mb*rr_asa_mb*dt)) -> 0.0095180967 | CN10: =(1-EXP(-r_mi*rr_asa_mi*dt)) -> 0.0021341352 | CO10: =(1-EXP(-r_tia*rr_asa_tia*dt)) -> 0.0031276457 | CP10: =(1-EXP(-r_minor*rr_asa_minor*dt)) -> 0.027818195 | CQ10: =CJ10*CK10 -> 0.00019193022 | CR10: =CJ10*CL10 -> 2.8977348e-05 | CS10: =CJ10*CM10 -> 0.00026945605 | CT10: =CJ10*CN10 -> 6.0417083e-05 | CU10: =CJ10*CO10 -> 8.8543233e-05 | CV10: =CJ10*CP10 -> 0.0007875294 | CW10: =CQ10*f_stroke_fatal -> 4.5487461e-05 | CX10: =CQ10*(1-f_stroke_fatal)*f_stroke_major -> 4.8765437e-05 | CY10: =CQ10*(1-f_stroke_fatal)*(1-f_stroke_major) -> 9.7677317e-05 | CZ10: =CR10*(1-f_bleed_fatal) -> 2.6543251e-05 | DA10: =CS10*(1-f_bleed_fatal) -> 0.00024682174 | DB10: =CT10*f_mi_fatal -> 7.310467e-06 | DC10: =CT10-DB10 -> 5.3106616e-05 | DD10: =CJ10-CQ10-CR10-CS10-DB10 -> 0.027812193 | DE10: =CW10*c_stroke_fatal+CX10*c_stroke_major+CY10*c_stroke_minor+CR10*c_ich+CS10*c_major_bleed+DB10*c_mi_fatal+DC10*c_mi_nonfatal+CU10*c_tia+CV10*c_minor_bleed -> 10.903524 | DF10: =dt*(DC10*dec_mi+DA10*dec_major_bleed+CV10*dec_minor_bleed+CU10*dec_tia) -> 1.2175941e-05 | DG10: =J10*CI10+CW10+CR10-CZ10+CS10-DA10+DB10 -> 0.00034329146 | DH10: =AG10 -> 0.88987411 | DI10: =AB10+AC10+BF10+BA10+BB10+BC10+CY10+CZ10 -> 0.017818881 | DJ10: =AA10+AZ10+BY10+CX10+CE10+BZ10+CA10+CB10 -> 0.0049104842 | DK10: =AD10+DD10+DA10 -> 0.034970474 | DL10: =K10+AJ10+BI10+CH10+DG10 -> 0.052426054 | DM10: =SUM(DH10:DL10) -> 1 | DN10: =dt*(G10*Warfarin!$H$2+(H10+I10+J10)*c_aspirin) -> 88.030055 | DO10: =dt*(H10*c_lt_minor_stroke+I10*c_lt_major_stroke) -> 65.245885 | DP10: =AH10+BG10+CF10+DE10 -> 285.48252 | DQ10: =DN10+DO10+DP10 -> 438.75846 | DR10: =dt*(G10*(u_af-dec_per_year_over_70*MAX(B10-ref_age,0))+H10*(u_minor_stroke-dec_per_year_over_70*MAX(B10-ref_age,0))+I10*(u_major_stroke-dec_per_year_over_70*MAX(B10-ref_age,0))+J10*(u_af-dec_per_year_over_70*MAX(B10-ref_age,0)))-AI10-BH10-CG10-DF10 -> 0.19299357 | DS10: =dt*(G10+H10+I10+J10) -> 0.23968669 | DT10: =DQ10*C10 -> 432.27434 | DU10: =DN10*C10 -> 86.729118 | DV10: =DP10*C10 -> 281.26356 | DW10: =DO10*C10 -> 64.28166 | DX10: =DR10*C10 -> 0.19014145 | DY10: =DS10*C10 -> 0.23614452 | DZ10: =T10+AS10+BR10+CQ10 -> 0.0042459275 | EA10: =U10+AT10+BS10+CR10 -> 0.0018593396 | EB10: =V10+AU10+BT10+CS10 -> 0.0079872807 | EC10: =G10*dt*C10 -> 0.22454387
A11: 5 | B11: =start_age+A11*dt -> 71.25 | C11: =(1+disc_rate)^-(A11*dt) -> 0.98156135 | D11: =IF(A11*dt>=wane_start,(1-wane_decay)^(A11*dt-wane_start),1) -> 1 | E11: =MIN(p_nonvasc_death*MIN(EXP(gomp_int+gomp_slope*INT(B11)),1)/qx_ref,0.999) -> 0.036640021 | F11: =rr_stroke_per_decade^((B11-ref_age)/10) -> 1.0519895 | G11: =DH10 -> 0.88987411 | H11: =DI10 -> 0.017818881 | I11: =DJ10 -> 0.0049104842 | J11: =DK10 -> 0.034970474 | K11: =DL10 -> 0.052426054 | L11: =1-EXP(LN(1-E11)*dt) -> 0.0092886235 | M11: =G11*(1-L11) -> 0.8816084 | N11: =IF(Warfarin!$B$2=1,EXP(LN(or_apx_stroke)*D11)*(1-EXP(-r_stroke*F11*dt))/(1-(1-EXP(-r_stroke*F11*dt))+EXP(LN(or_apx_stroke)*D11)*(1-EXP(-r_stroke*F11*dt))),(1-EXP(-r_stroke*F11*dt))) -> 0.0042330006 | O11: =IF(Warfarin!$B$2=1,EXP(LN(or_apx_ich)*D11)*(1-EXP(-r_ich*dt))/(1-(1-EXP(-r_ich*dt))+EXP(LN(or_apx_ich)*D11)*(1-EXP(-r_ich*dt))),(1-EXP(-r_ich*dt))) -> 0.0020060282 | P11: =IF(Warfarin!$B$2=1,EXP(LN(or_apx_mb)*D11)*(1-EXP(-r_mb*dt))/(1-(1-EXP(-r_mb*dt))+EXP(LN(or_apx_mb)*D11)*(1-EXP(-r_mb*dt))),(1-EXP(-r_mb*dt))) -> 0.0083541048 | Q11: =IF(Warfarin!$B$2=1,EXP(LN(or_apx_mi)*D11)*(1-EXP(-r_mi*dt))/(1-(1-EXP(-r_mi*dt))+EXP(LN(or_apx_mi)*D11)*(1-EXP(-r_mi*dt))),(1-EXP(-r_mi*dt))) -> 0.0015033869 | R11: =(1-EXP(-r_tia*dt)) -> 0.0020060282 | S11: =(1-EXP(-r_minor*dt)) -> 0.043793769 | T11: =M11*N11 -> 0.0037318489 | U11: =M11*O11 -> 0.0017685313 | V11: =M11*P11 -> 0.007365049 | W11: =M11*Q11 -> 0.0013253985 | X11: =M11*R11 -> 0.0017685313 | Y11: =M11*S11 -> 0.038608955 | Z11: =T11*f_stroke_fatal -> 0.00088444819 | AA11: =T11*(1-f_stroke_fatal)*f_stroke_major -> 0.00094818444 | AB11: =T11*(1-f_stroke_fatal)*(1-f_stroke_major) -> 0.0018992163 | AC11: =U11*(1-f_bleed_fatal) -> 0.0016199746 | AD11: =V11*(1-f_bleed_fatal) -> 0.0067463848 | AE11: =W11*f_mi_fatal -> 0.00016037322 | AF11: =W11-AE11 -> 0.0011650253 | AG11: =M11-T11-U11-V11-AE11 -> 0.8685826 | AH11: =Z11*c_stroke_fatal+AA11*c_stroke_major+AB11*c_stroke_minor+U11*c_ich+V11*c_major_bleed+AE11*c_mi_fatal+AF11*c_mi_nonfatal+X11*c_tia+Y11*c_minor_bleed -> 257.96157 | AI11: =dt*(AF11*dec_mi+AD11*dec_major_bleed+Y11*dec_minor_bleed+X11*dec_tia) -> 0.00036259267 | AJ11: =G11*L11+Z11+U11-AC11+V11-AD11+AE11 -> 0.010077748 | AK11: =1-EXP(LN(1-E11)*hr_death_prior_stroke*dt) -> 0.021234968 | AL11: =H11*(1-AK11) -> 0.017440497 | AM11: =(1-EXP(-r_stroke*F11*rr_stroke_prior*rr_asa_stroke*dt)) -> 0.015004725 | AN11: =(1-EXP(-r_ich*rr_asa_ich*dt)) -> 0.0010235777 | AO11: =(1-EXP(-r_mb*rr_asa_mb*dt)) -> 0.0095180967 | AP11: =(1-EXP(-r_mi*rr_asa_mi*dt)) -> 0.0021341352 | AQ11: =(1-EXP(-r_tia*rr_asa_tia*dt)) -> 0.0031276457 | AR11: =(1-EXP(-r_minor*rr_asa_minor*dt)) -> 0.027818195 | AS11: =AL11*AM11 -> 0.00026168987 | AT11: =AL11*AN11 -> 1.7851704e-05 | AU11: =AL11*AO11 -> 0.00016600034 | AV11: =AL11*AP11 -> 3.7220378e-05 | AW11: =AL11*AQ11 -> 5.4547695e-05 | AX11: =AL11*AR11 -> 0.00048516315 | AY11: =AS11*f_stroke_fatal_recur -> 9.7372183e-05 | AZ11: =AS11*(1-f_stroke_fatal_recur)*f_stroke_major -> 5.4717789e-05 | BA11: =AS11*(1-f_stroke_fatal_recur)*(1-f_stroke_major) -> 0.0001095999 | BB11: =AT11*(1-f_bleed_fatal) -> 1.635216e-05 | BC11: =AU11*(1-f_bleed_fatal) -> 0.00015205631 | BD11: =AV11*f_mi_fatal -> 4.5036658e-06 | BE11: =AV11-BD11 -> 3.2716712e-05 | BF11: =AL11-AS11-AT11-AU11-BD11 -> 0.016990452 | BG11: =AY11*c_stroke_fatal+AZ11*c_stroke_major+BA11*c_stroke_minor+AT11*c_ich+AU11*c_major_bleed+BD11*c_mi_fatal+BE11*c_mi_nonfatal+AW11*c_tia+AX11*c_minor_bleed -> 11.371432 | BH11: =dt*(BE11*dec_mi+BC11*dec_major_bleed+AX11*dec_minor_bleed+AW11*dec_tia) -> 7.5010758e-06 | BI11: =H11*AK11+AY11+AT11-BB11+AU11-BC11+BD11 -> 0.00049570277 | BJ11: =1-EXP(LN(1-E11)*hr_death_prior_stroke*dt) -> 0.021234968 | BK11: =I11*(1-BJ11) -> 0.0048062102 | BL11: =(1-EXP(-r_stroke*F11*rr_stroke_prior*rr_asa_stroke*dt)) -> 0.015004725 | BM11: =(1-EXP(-r_ich*rr_asa_ich*dt)) -> 0.0010235777 | BN11: =(1-EXP(-r_mb*rr_asa_mb*dt)) -> 0.0095180967 | BO11: =(1-EXP(-r_mi*rr_asa_mi*dt)) -> 0.0021341352 | BP11: =(1-EXP(-r_tia*rr_asa_tia*dt)) -> 0.0031276457 | BQ11: =(1-EXP(-r_minor*rr_asa_minor*dt)) -> 0.027818195 | BR11: =BK11*BL11 -> 7.2115863e-05 | BS11: =BK11*BM11 -> 4.9195295e-06 | BT11: =BK11*BN11 -> 4.5745974e-05 | BU11: =BK11*BO11 -> 1.0257102e-05 | BV11: =BK11*BP11 -> 1.5032122e-05 | BW11: =BK11*BQ11 -> 0.00013370009 | BX11: =BR11*f_stroke_fatal_recur -> 2.6833592e-05 | BY11: =BR11*(1-f_stroke_fatal_recur)*f_stroke_major -> 1.5078997e-05 | BZ11: =BR11*(1-f_stroke_fatal_recur)*(1-f_stroke_major) -> 3.0203275e-05 | CA11: =BS11*(1-f_bleed_fatal) -> 4.506289e-06 | CB11: =BT11*(1-f_bleed_fatal) -> 4.1903312e-05 | CC11: =BU11*f_mi_fatal -> 1.2411094e-06 | CD11: =BU11-CC11 -> 9.0159928e-06 | CE11: =BK11-BR11-BS11-BT11-CC11 -> 0.0046821877 | CF11: =BX11*c_stroke_fatal+BY11*c_stroke_major+BZ11*c_stroke_minor+BS11*c_ich+BT11*c_major_bleed+CC11*c_mi_fatal+CD11*c_mi_nonfatal+BV11*c_tia+BW11*c_minor_bleed -> 3.1337117 | CG11: =dt*(CD11*dec_mi+CB11*dec_major_bleed+BW11*dec_minor_bleed+BV11*dec_tia) -> 2.0671284e-06 | CH11: =I11*BJ11+BX11+BS11-CA11+BT11-CB11+CC11 -> 0.00013660458 | CI11: =1-EXP(LN(1-E11)*dt) -> 0.0092886235 | CJ11: =J11*(1-CI11) -> 0.034645647 | CK11: =(1-EXP(-r_stroke*F11*rr_asa_stroke*dt)) -> 0.0068484576 | CL11: =(1-EXP(-r_ich*rr_asa_ich*dt)) -> 0.0010235777 | CM11: =(1-EXP(-r_mb*rr_asa_mb*dt)) -> 0.0095180967 | CN11: =(1-EXP(-r_mi*rr_asa_mi*dt)) -> 0.0021341352 | CO11: =(1-EXP(-r_tia*rr_asa_tia*dt)) -> 0.0031276457 | CP11: =(1-EXP(-r_minor*rr_asa_minor*dt)) -> 0.027818195 | CQ11: =CJ11*CK11 -> 0.00023726924 | CR11: =CJ11*CL11 -> 3.5462511e-05 | CS11: =CJ11*CM11 -> 0.00032976062 | CT11: =CJ11*CN11 -> 7.3938493e-05 | CU11: =CJ11*CO11 -> 0.00010835931 | CV11: =CJ11*CP11 -> 0.00096377936 | CW11: =CQ11*f_stroke_fatal -> 5.6232811e-05 | CX11: =CQ11*(1-f_stroke_fatal)*f_stroke_major -> 6.0285132e-05 | CY11: =CQ11*(1-f_stroke_fatal)*(1-f_stroke_major) -> 0.0001207513 | CZ11: =CR11*(1-f_bleed_fatal) -> 3.248366e-05 | DA11: =CS11*(1-f_bleed_fatal) -> 0.00030206073 | DB11: =CT11*f_mi_fatal -> 8.9465577e-06 | DC11: =CT11-DB11 -> 6.4991935e-05 | DD11: =CJ11-CQ11-CR11-CS11-DB11 -> 0.034034208 | DE11: =CW11*c_stroke_fatal+CX11*c_stroke_major+CY11*c_stroke_minor+CR11*c_ich+CS11*c_major_bleed+DB11*c_mi_fatal+DC11*c_mi_nonfatal+CU11*c_tia+CV11*c_minor_bleed -> 13.431859 | DF11: =dt*(DC11*dec_mi+DA11*dec_major_bleed+CV11*dec_minor_bleed+CU11*dec_tia) -> 1.490093e-05 | DG11: =J11*CI11+CW11+CR11-CZ11+CS11-DA11+DB11 -> 0.00042068568 | DH11: =AG11 -> 0.8685826 | DI11: =AB11+AC11+BF11+BA11+BB11+BC11+CY11+CZ11 -> 0.020940886 | DJ11: =AA11+AZ11+BY11+CX11+CE11+BZ11+CA11+CB11 -> 0.005837067 | DK11: =AD11+DD11+DA11 -> 0.041082653 | DL11: =K11+AJ11+BI11+CH11+DG11 -> 0.063556795 | DM11: =SUM(DH11:DL11) -> 1 | DN11: =dt*(G11*Warfarin!$H$2+(H11+I11+J11)*c_aspirin) -> 86.041973 | DO11: =dt*(H11*c_lt_minor_stroke+I11*c_lt_major_stroke) -> 80.229265 | DP11: =AH11+BG11+CF11+DE11 -> 285.89857 | DQ11: =DN11+DO11+DP11 -> 452.16981 | DR11: =dt*(G11*(u_af-dec_per_year_over_70*MAX(B11-ref_age,0))+H11*(u_minor_stroke-dec_per_year_over_70*MAX(B11-ref_age,0))+I11*(u_major_stroke-dec_per_year_over_70*MAX(B11-ref_age,0))+J11*(u_af-dec_per_year_over_70*MAX(B11-ref_age,0)))-AI11-BH11-CG11-DF11 -> 0.19055744 | DS11: =dt*(G11+H11+I11+J11) -> 0.23689349 | DT11: =DQ11*C11 -> 443.83241 | DU11: =DN11*C11 -> 84.455474 | DV11: =DP11*C11 -> 280.62699 | DW11: =DO11*C11 -> 78.749945 | DX11: =DR11*C11 -> 0.18704382 | DY11: =DS11*C11 -> 0.23252549 | DZ11: =T11+AS11+BR11+CQ11 -> 0.0043029239 | EA11: =U11+AT11+BS11+CR11 -> 0.001826765 | EB11: =V11+AU11+BT11+CS11 -> 0.0079065559 | EC11: =G11*dt*C11 -> 0.21836651
A12: 6 | B12: =start_age+A12*dt -> 71.5 | C12: =(1+disc_rate)^-(A12*dt) -> 0.97791461 | D12: =IF(A12*dt>=wane_start,(1-wane_decay)^(A12*dt-wane_start),1) -> 1 | E12: =MIN(p_nonvasc_death*MIN(EXP(gomp_int+gomp_slope*INT(B12)),1)/qx_ref,0.999) -> 0.036640021 | F12: =rr_stroke_per_decade^((B12-ref_age)/10) -> 1.0627074 | G12: =DH11 -> 0.8685826 | H12: =DI11 -> 0.020940886 | I12: =DJ11 -> 0.005837067 | J12: =DK11 -> 0.041082653 | K12: =DL11 -> 0.063556795 | L12: =1-EXP(LN(1-E12)*dt) -> 0.0092886235 | M12: =G12*(1-L12) -> 0.86051466 | N12: =IF(Warfarin!$B$2=1,EXP(LN(or_apx_stroke)*D12)*(1-EXP(-r_stroke*F12*dt))/(1-(1-EXP(-r_stroke*F12*dt))+EXP(LN(or_apx_stroke)*D12)*(1-EXP(-r_stroke*F12*dt))),(1-EXP(-r_stroke*F12*dt))) -> 0.0042760348 | O12: =IF(Warfarin!$B$2=1,EXP(LN(or_apx_ich)*D12)*(1-EXP(-r_ich*dt))/(1-(1-EXP(-r_ich*dt))+EXP(LN(or_apx_ich)*D12)*(1-EXP(-r_ich*dt))),(1-EXP(-r_ich*dt))) -> 0.0020060282 | P12: =IF(Warfarin!$B$2=1,EXP(LN(or_apx_mb)*D12)*(1-EXP(-r_mb*dt))/(1-(1-EXP(-r_mb*dt))+EXP(LN(or_apx_mb)*D12)*(1-EXP(-r_mb*dt))),(1-EXP(-r_mb*dt))) -> 0.0083541048 | Q12: =IF(Warfarin!$B$2=1,EXP(LN(or_apx_mi)*D12)*(1-EXP(-r_mi*dt))/(1-(1-EXP(-r_mi*dt))+EXP(LN(or_apx_mi)*D12)*(1-EXP(-r_mi*dt))),(1-EXP(-r_mi*dt))) -> 0.0015033869 | R12: =(1-EXP(-r_tia*dt)) -> 0.0020060282 | S12: =(1-EXP(-r_minor*dt)) -> 0.043793769 | T12: =M12*N12 -> 0.0036795907 | U12: =M12*O12 -> 0.0017262166 | V12: =M12*P12 -> 0.0071888296 | W12: =M12*Q12 -> 0.0012936864 | X12: =M12*R12 -> 0.0017262166 | Y12: =M12*S12 -> 0.03768518 | Z12: =T12*f_stroke_fatal -> 0.00087206299 | AA12: =T12*(1-f_stroke_fatal)*f_stroke_major -> 0.00093490672 | AB12: =T12*(1-f_stroke_fatal)*(1-f_stroke_major) -> 0.001872621 | AC12: =U12*(1-f_bleed_fatal) -> 0.0015812144 | AD12: =V12*(1-f_bleed_fatal) -> 0.006584968 | AE12: =W12*f_mi_fatal -> 0.00015653606 | AF12: =W12-AE12 -> 0.0011371504 | AG12: =M12-T12-U12-V12-AE12 -> 0.84776349 | AH12: =Z12*c_stroke_fatal+AA12*c_stroke_major+AB12*c_stroke_minor+U12*c_ich+V12*c_major_bleed+AE12*c_mi_fatal+AF12*c_mi_nonfatal+X12*c_tia+Y12*c_minor_bleed -> 253.1577 | AI12: =dt*(AF12*dec_mi+AD12*dec_major_bleed+Y12*dec_minor_bleed+X12*dec_tia) -> 0.00035391713 | AJ12: =G12*L12+Z12+U12-AC12+V12-AD12+AE12 -> 0.0098453996 | AK12: =1-EXP(LN(1-E12)*hr_death_prior_stroke*dt) -> 0.021234968 | AL12: =H12*(1-AK12) -> 0.020496207 | AM12: =(1-EXP(-r_stroke*F12*rr_stroke_prior*rr_asa_stroke*dt)) -> 0.015156432 | AN12: =(1-EXP(-r_ich*rr_asa_ich*dt)) -> 0.0010235777 | AO12: =(1-EXP(-r_mb*rr_asa_mb*dt)) -> 0.0095180967 | AP12: =(1-EXP(-r_mi*rr_asa_mi*dt)) -> 0.0021341352 | AQ12: =(1-EXP(-r_tia*rr_asa_tia*dt)) -> 0.0031276457 | AR12: =(1-EXP(-r_minor*rr_asa_minor*dt)) -> 0.027818195 | AS12: =AL12*AM12 -> 0.00031064936 | AT12: =AL12*AN12 -> 2.097946e-05 | AU12: =AL12*AO12 -> 0.00019508488 | AV12: =AL12*AP12 -> 4.3741676e-05 | AW12: =AL12*AQ12 -> 6.4104872e-05 | AX12: =AL12*AR12 -> 0.00057016748 | AY12: =AS12*f_stroke_fatal_recur -> 0.00011558952 | AZ12: =AS12*(1-f_stroke_fatal_recur)*f_stroke_major -> 6.4954926e-05 | BA12: =AS12*(1-f_stroke_fatal_recur)*(1-f_stroke_major) -> 0.00013010491 | BB12: =AT12*(1-f_bleed_fatal) -> 1.9217185e-05 | BC12: =AU12*(1-f_bleed_fatal) -> 0.00017869775 | BD12: =AV12*f_mi_fatal -> 5.2927428e-06 | BE12: =AV12-BD12 -> 3.8448933e-05 | BF12: =AL12-AS12-AT12-AU12-BD12 -> 0.0199642 | BG12: =AY12*c_stroke_fatal+AZ12*c_stroke_major+BA12*c_stroke_minor+AT12*c_ich+AU12*c_major_bleed+BD12*c_mi_fatal+BE12*c_mi_nonfatal+AW12*c_tia+AX12*c_minor_bleed -> 13.471005 | BH12: =dt*(BE12*dec_mi+BC12*dec_major_bleed+AX12*dec_minor_bleed+AW12*dec_tia) -> 8.8153221e-06 | BI12: =H12*AK12+AY12+AT12-BB12+AU12-BC12+BD12 -> 0.0005837107 | BJ12: =1-EXP(LN(1-E12)*hr_death_prior_stroke*dt) -> 0.021234968 | BK12: =I12*(1-BJ12) -> 0.005713117 | BL12: =(1-EXP(-r_stroke*F12*rr_stroke_prior*rr_asa_stroke*dt)) -> 0.015156432 | BM12: =(1-EXP(-r_ich*rr_asa_ich*dt)) -> 0.0010235777 | BN12: =(1-EXP(-r_mb*rr_asa_mb*dt)) -> 0.0095180967 | BO12: =(1-EXP(-r_mi*rr_asa_mi*dt)) -> 0.0021341352 | BP12: =(1-EXP(-r_tia*rr_asa_tia*dt)) -> 0.0031276457 | BQ12: =(1-EXP(-r_minor*rr_asa_minor*dt)) -> 0.027818195 | BR12: =BK12*BL12 -> 8.6590468e-05 | BS12: =BK12*BM12 -> 5.8478191e-06 | BT12: =BK12*BN12 -> 5.4378001e-05 | BU12: =BK12*BO12 -> 1.2192564e-05 | BV12: =BK12*BP12 -> 1.7868606e-05 | BW12: =BK12*BQ12 -> 0.0001589286 | BX12: =BR12*f_stroke_fatal_recur -> 3.2219447e-05 | BY12: =BR12*(1-f_stroke_fatal_recur)*f_stroke_major -> 1.810555e-05 | BZ12: =BR12*(1-f_stroke_fatal_recur)*(1-f_stroke_major) -> 3.6265471e-05 | CA12: =BS12*(1-f_bleed_fatal) -> 5.3566023e-06 | CB12: =BT12*(1-f_bleed_fatal) -> 4.9810248e-05 | CC12: =BU12*f_mi_fatal -> 1.4753002e-06 | CD12: =BU12-CC12 -> 1.0717264e-05 | CE12: =BK12-BR12-BS12-BT12-CC12 -> 0.0055648254 | CF12: =BX12*c_stroke_fatal+BY12*c_stroke_major+BZ12*c_stroke_minor+BS12*c_ich+BT12*c_major_bleed+CC12*c_mi_fatal+CD12*c_mi_nonfatal+BV12*c_tia+BW12*c_minor_bleed -> 3.7549107 | CG12: =dt*(CD12*dec_mi+CB12*dec_major_bleed+BW12*dec_minor_bleed+BV12*dec_tia) -> 2.4571848e-06 | CH12: =I12*BJ12+BX12+BS12-CA12+BT12-CB12+CC12 -> 0.00016270364 | CI12: =1-EXP(LN(1-E12)*dt) -> 0.0092886235 | CJ12: =J12*(1-CI12) -> 0.040701052 | CK12: =(1-EXP(-r_stroke*F12*rr_asa_stroke*dt)) -> 0.006917989 | CL12: =(1-EXP(-r_ich*rr_asa_ich*dt)) -> 0.0010235777 | CM12: =(1-EXP(-r_mb*rr_asa_mb*dt)) -> 0.0095180967 | CN12: =(1-EXP(-r_mi*rr_asa_mi*dt)) -> 0.0021341352 | CO12: =(1-EXP(-r_tia*rr_asa_tia*dt)) -> 0.0031276457 | CP12: =(1-EXP(-r_minor*rr_asa_minor*dt)) -> 0.027818195 | CQ12: =CJ12*CK12 -> 0.00028156943 | CR12: =CJ12*CL12 -> 4.1660688e-05 | CS12: =CJ12*CM12 -> 0.00038739655 | CT12: =CJ12*CN12 -> 8.6861547e-05 | CU12: =CJ12*CO12 -> 0.00012729847 | CV12: =CJ12*CP12 -> 0.0011322298 | CW12: =CQ12*f_stroke_fatal -> 6.6731955e-05 | CX12: =CQ12*(1-f_stroke_fatal)*f_stroke_major -> 7.1540879e-05 | CY12: =CQ12*(1-f_stroke_fatal)*(1-f_stroke_major) -> 0.0001432966 | CZ12: =CR12*(1-f_bleed_fatal) -> 3.8161191e-05 | DA12: =CS12*(1-f_bleed_fatal) -> 0.00035485524 | DB12: =CT12*f_mi_fatal -> 1.0510247e-05 | DC12: =CT12-DB12 -> 7.6351299e-05 | DD12: =CJ12-CQ12-CR12-CS12-DB12 -> 0.039979915 | DE12: =CW12*c_stroke_fatal+CX12*c_stroke_major+CY12*c_stroke_minor+CR12*c_ich+CS12*c_major_bleed+DB12*c_mi_fatal+DC12*c_mi_nonfatal+CU12*c_tia+CV12*c_minor_bleed -> 15.884056 | DF12: =dt*(DC12*dec_mi+DA12*dec_major_bleed+CV12*dec_minor_bleed+CU12*dec_tia) -> 1.7505331e-05 | DG12: =J12*CI12+CW12+CR12-CZ12+CS12-DA12+DB12 -> 0.00049488431 | DH12: =AG12 -> 0.84776349 | DI12: =AB12+AC12+BF12+BA12+BB12+BC12+CY12+CZ12 -> 0.023927513 | DJ12: =AA12+AZ12+BY12+CX12+CE12+BZ12+CA12+CB12 -> 0.0067457658 | DK12: =AD12+DD12+DA12 -> 0.046919738 | DL12: =K12+AJ12+BI12+CH12+DG12 -> 0.074643493 | DM12: =SUM(DH12:DL12) -> 1 | DN12: =dt*(G12*Warfarin!$H$2+(H12+I12+J12)*c_aspirin) -> 84.095939 | DO12: =dt*(H12*c_lt_minor_stroke+I12*c_lt_major_stroke) -> 94.718429 | DP12: =AH12+BG12+CF12+DE12 -> 286.26767 | DQ12: =DN12+DO12+DP12 -> 465.08204 | DR12: =dt*(G12*(u_af-dec_per_year_over_70*MAX(B12-ref_age,0))+H12*(u_minor_stroke-dec_per_year_over_70*MAX(B12-ref_age,0))+I12*(u_major_stroke-dec_per_year_over_70*MAX(B12-ref_age,0))+J12*(u_af-dec_per_year_over_70*MAX(B12-ref_age,0)))-AI12-BH12-CG12-DF12 -> 0.18813445 | DS12: =dt*(G12+H12+I12+J12) -> 0.2341108 | DT12: =DQ12*C12 -> 454.81052 | DU12: =DN12*C12 -> 82.238648 | DV12: =DP12*C12 -> 279.94534 | DW12: =DO12*C12 -> 92.626536 | DX12: =DR12*C12 -> 0.18397943 | DY12: =DS12*C12 -> 0.22894037 | DZ12: =T12+AS12+BR12+CQ12 -> 0.0043583999 | EA12: =U12+AT12+BS12+CR12 -> 0.0017947046 | EB12: =V12+AU12+BT12+CS12 -> 0.0078256891 | EC12: =G12*dt*C12 -> 0.2123499
